Workbook

Sheet Data
B1: Market Name | C1: Construction Safety Net Market | AN1: 0.99 | AO1: 0.99 | BP1: 0.99
C2: Market Share | AM2: =VLOOKUP(AM3,$B$120:$D$159,3,0) -> 0.12254789 | AN2: =VLOOKUP(AN3,$B$120:$D$159,3,0) -> 0.1143096 | AO2: =VLOOKUP(AO3,$B$120:$D$159,3,0) -> 0.15483646 | AP2: =VLOOKUP(AP3,$B$120:$D$159,3,0) -> 0.16341377 | AQ2: =VLOOKUP(AQ3,$B$120:$D$159,3,0) -> 0.097694978 | AR2: =VLOOKUP(AR3,$B$120:$D$159,3,0) -> 0.14806968 | AS2: =VLOOKUP(AS3,$B$120:$D$159,3,0) -> 0.11581248 | AT2: =VLOOKUP(AT3,$B$120:$D$159,3,0) -> 0.077070547 | ... BT2: =VLOOKUP(BT3,$B$120:$D$159,3,0) -> 0.14310259
A3: Segment Name in B Column Only | B3: Segment | C3: U.S. | D3: Canada | E3: U.K. | F3: Germany | G3: Italy | H3: France | I3: Spain | J3: Russia | K3: Netherlands | L3: Ireland | M3: Sweden | N3: Poland | O3: Hungary | P3: Slovakia | Q3: Turkey | R3: Rest of Europe | S3: China | T3: Japan | U3: India | V3: South Korea | W3: Singapore | X3: Malaysia | Y3: Thailand | Z3: Indonesia | AA3: Rest of ASEAN | AB3: Australia | AC3: Rest of Asia Pacific | AD3: Brazil | AE3: Argentina | AF3: Mexico | AG3: Rest of Latin America | AH3: GCC | AI3: South Africa | AJ3: Rest of Middle East & Africa | AM3: =C3 -> U.S. | AN3: =D3 -> Canada | AO3: =E3 -> U.K. | AP3: =F3 -> Germany | AQ3: =G3 -> Italy | AR3: =H3 -> France | AS3: =I3 -> Spain | AT3: =J3 -> Russia | ... BT3: =AJ3 -> Rest of Middle East & Africa | BW3: =AM3 -> U.S. | BX3: =AN3 -> Canada | BY3: =AO3 -> U.K. | BZ3: =AP3 -> Germany | CA3: =AQ3 -> Italy | CB3: =AR3 -> France | CC3: =AS3 -> Spain | CD3: =AT3 -> Russia | ... DD3: =BT3 -> Rest of Middle East & Africa
B4: By Component | AL4: By Component | AM4: =AM5*C5+AM17*C17+AM23*C23 -> 0.12254789 | AN4: =AN5*D5+AN17*D17+AN23*D23 -> 0.11173341 | AO4: =AO5*E5+AO17*E17+AO23*E23 -> 0.12917937 | AP4: =AP5*F5+AP17*F17+AP23*F23 -> 0.12403877 | AQ4: =AQ5*G5+AQ17*G17+AQ23*G23 -> 0.11825065 | AR4: =AR5*H5+AR17*H17+AR23*H23 -> 0.12734857 | AS4: =AS5*I5+AS17*I17+AS23*I23 -> 0.12162104 | AT4: =AT5*J5+AT17*J17+AT23*J23 -> 0.077668255 | ... BT4: =BT5*AJ5+BT17*AJ17+BT23*AJ23 -> 0.12900923 | BV4: By Component
B5: Hardware | C5: =1-SUM(C17,C23) -> 0.50201611 | D5: =1-SUM(D17,D23) -> 0.51108623 | E5: =1-SUM(E17,E23) -> 0.52036581 | F5: =1-SUM(F17,F23) -> 0.47232041 | G5: =1-SUM(G17,G23) -> 0.49468867 | H5: =1-SUM(H17,H23) -> 0.51170775 | I5: =1-SUM(I17,I23) -> 0.48019089 | J5: =1-SUM(J17,J23) -> 0.50811648 | ... AJ5: =1-SUM(AJ17,AJ23) -> 0.48160036 | AL5: Hardware | AM5: =AM6*C6+SUMPRODUCT(AM10:AM16,C10:C16) -> 0.1112195 | AN5: =AN6*D6+SUMPRODUCT(AN10:AN16,D10:D16) -> 0.10896507 | AO5: =AO6*E6+SUMPRODUCT(AO10:AO16,E10:E16) -> 0.12151639 | AP5: =AP6*F6+SUMPRODUCT(AP10:AP16,F10:F16) -> 0.11976997 | AQ5: =AQ6*G6+SUMPRODUCT(AQ10:AQ16,G10:G16) -> 0.10316261 | AR5: =AR6*H6+SUMPRODUCT(AR10:AR16,H10:H16) -> 0.11798566 | AS5: =AS6*I6+SUMPRODUCT(AS10:AS16,I10:I16) -> 0.11070606 | AT5: =AT6*J6+SUMPRODUCT(AT10:AT16,J10:J16) -> 0.054672083 | ... BT5: =BT6*AJ6+SUMPRODUCT(BT10:BT16,AJ10:AJ16) -> 0.11650164 | BV5: Hardware | BW5: CMI_Trend_52 | BX5: CMI_Trend_25 | BY5: CMI_Trend_60 | BZ5: CMI_Trend_25 | CA5: CMI_Trend_60 | CB5: CMI_Trend_20 | CC5: CMI_Trend_38 | CD5: CMI_Trend_25 | CE5: CMI_Trend_52 | CF5: CMI_Trend_20 | CG5: CMI_Trend_46 | CH5: CMI_Trend_25 | CI5: CMI_Trend_52 | CJ5: CMI_Trend_52 | CK5: CMI_Trend_56 | CL5: CMI_Trend_25 | CM5: CMI_Trend_46 | CN5: CMI_Trend_60 | CO5: CMI_Trend_25 | CP5: CMI_Trend_25 | CQ5: CMI_Trend_38 | CR5: CMI_Trend_38 | CS5: CMI_Trend_52 | CT5: CMI_Trend_52 | CU5: CMI_Trend_56 | CV5: CMI_Trend_25 | CW5: CMI_Trend_56 | CX5: CMI_Trend_56 | CY5: CMI_Trend_56 | CZ5: CMI_Trend_38 | DA5: CMI_Trend_52 | DB5: CMI_Trend_20 | DC5: CMI_Trend_56 | DD5: CMI_Trend_60
B6: Kiosk Scanner Devices | C6: =1-SUM(C10:C16) -> 0.21041163 | D6: =1-SUM(D10:D16) -> 0.17891163 | E6: =1-SUM(E10:E16) -> 0.21171163 | F6: =1-SUM(F10:F16) -> 0.23071163 | G6: =1-SUM(G10:G16) -> 0.24591163 | H6: =1-SUM(H10:H16) -> 0.24771163 | I6: =1-SUM(I10:I16) -> 0.18281163 | J6: =1-SUM(J10:J16) -> 0.16791163 | ... AJ6: =1-SUM(AJ10:AJ16) -> 0.18281163 | AL6: Kiosk Scanner Devices | AM6: =SUMPRODUCT(AM7:AM9,C7:C9) -> 0.10029207 | AN6: =SUMPRODUCT(AN7:AN9,D7:D9) -> 0.097049339 | AO6: =SUMPRODUCT(AO7:AO9,E7:E9) -> 0.11209756 | AP6: =SUMPRODUCT(AP7:AP9,F7:F9) -> 0.11192878 | AQ6: =SUMPRODUCT(AQ7:AQ9,G7:G9) -> 0.091847156 | AR6: =SUMPRODUCT(AR7:AR9,H7:H9) -> 0.10812436 | AS6: =SUMPRODUCT(AS7:AS9,I7:I9) -> 0.098955534 | AT6: =SUMPRODUCT(AT7:AT9,J7:J9) -> 0.03955753 | ... BT6: =SUMPRODUCT(BT7:BT9,AJ7:AJ9) -> 0.1068153 | BV6: Kiosk Scanner Devices | BW6: CMI_Trend_46 | BX6: CMI_Trend_60 | BY6: CMI_Trend_56 | BZ6: CMI_Trend_52 | CA6: CMI_Trend_25 | CB6: CMI_Trend_60 | CC6: CMI_Trend_60 | CD6: CMI_Trend_52 | CE6: CMI_Trend_52 | CF6: CMI_Trend_60 | CG6: CMI_Trend_25 | CH6: CMI_Trend_25 | CI6: CMI_Trend_60 | CJ6: CMI_Trend_56 | CK6: CMI_Trend_60 | CL6: CMI_Trend_25 | CM6: CMI_Trend_60 | CN6: CMI_Trend_60 | CO6: CMI_Trend_25 | CP6: CMI_Trend_52 | CQ6: CMI_Trend_25 | CR6: CMI_Trend_56 | CS6: CMI_Trend_46 | CT6: CMI_Trend_52 | CU6: CMI_Trend_46 | CV6: CMI_Trend_60 | CW6: CMI_Trend_20 | CX6: CMI_Trend_25 | CY6: CMI_Trend_20 | CZ6: CMI_Trend_38 | DA6: CMI_Trend_52 | DB6: CMI_Trend_52 | DC6: CMI_Trend_25 | DD6: CMI_Trend_46
B7: Single-plane Kiosk Scanners | C7: =1-SUM(C8:C9) -> 0.253469 | D7: =1-SUM(D8:D9) -> 0.233269 | E7: =1-SUM(E8:E9) -> 0.235869 | F7: =1-SUM(F8:F9) -> 0.249169 | G7: =1-SUM(G8:G9) -> 0.231169 | H7: =1-SUM(H8:H9) -> 0.249669 | I7: =1-SUM(I8:I9) -> 0.247469 | J7: =1-SUM(J8:J9) -> 0.236169 | ... AJ7: =1-SUM(AJ8:AJ9) -> 0.226069 | AL7: Single-plane Kiosk Scanners | AM7: 0.093614017 | AN7: 0.089828082 | AO7: 0.10626791 | AP7: 0.10655046 | AQ7: 0.083474925 | AR7: 0.10242372 | AS7: 0.09170323 | AT7: 0.030911608 | AU7: 0.10121616 | AV7: 0.097108627 | AW7: 0.096156347 | AX7: 0.087348652 | AY7: 0.050180968 | AZ7: 0.037528662 | BA7: 0.08763256 | BB7: 0.093167265 | BC7: 0.10834423 | BD7: 0.10552378 | BE7: 0.10168965 | BF7: 0.1067819 | BG7: 0.10760695 | BH7: 0.10352669 | BI7: 0.10733928 | BJ7: 0.10081315 | BK7: 0.096667973 | BL7: 0.09765665 | BM7: 0.095495981 | BN7: 0.10352088 | BO7: 0.09329762 | BP7: 0.10081061 | BQ7: 0.095975852 | BR7: 0.10639825 | BS7: 0.097905393 | BT7: 0.10061837 | BV7: Single-plane Kiosk Scanners | BW7: CMI_Trend_20 | BX7: CMI_Trend_46 | BY7: CMI_Trend_60 | BZ7: CMI_Trend_20 | CA7: CMI_Trend_25 | CB7: CMI_Trend_20 | CC7: CMI_Trend_60 | CD7: CMI_Trend_60 | CE7: CMI_Trend_20 | CF7: CMI_Trend_60 | CG7: CMI_Trend_60 | CH7: CMI_Trend_38 | CI7: CMI_Trend_25 | CJ7: CMI_Trend_38 | CK7: CMI_Trend_46 | CL7: CMI_Trend_52 | CM7: CMI_Trend_46 | CN7: CMI_Trend_20 | CO7: CMI_Trend_20 | CP7: CMI_Trend_20 | CQ7: CMI_Trend_46 | CR7: CMI_Trend_60 | CS7: CMI_Trend_52 | CT7: CMI_Trend_46 | CU7: CMI_Trend_20 | CV7: CMI_Trend_60 | CW7: CMI_Trend_56 | CX7: CMI_Trend_56 | CY7: CMI_Trend_20 | CZ7: CMI_Trend_56 | DA7: CMI_Trend_52 | DB7: CMI_Trend_46 | DC7: CMI_Trend_52 | DD7: CMI_Trend_46
B8: Multi-plane (Bioptic) Kiosk Scanners | C8: 0.66682665 | D8: 0.68392665 | E8: 0.67372665 | F8: 0.66402665 | G8: 0.68242665 | H8: 0.67942665 | I8: 0.66162665 | J8: 0.67912665 | K8: 0.65812665 | L8: 0.67132665 | M8: 0.68082665 | N8: 0.67442665 | O8: 0.67232665 | P8: 0.67182665 | Q8: 0.66312665 | R8: 0.67362665 | S8: 0.66232665 | T8: 0.66922665 | U8: 0.66732665 | V8: 0.66542665 | W8: 0.67782665 | X8: 0.66522665 | Y8: 0.68152665 | Z8: 0.65662665 | AA8: 0.68002665 | AB8: 0.67942665 | AC8: 0.67342665 | AD8: 0.66642665 | AE8: 0.65202665 | AF8: 0.65742665 | AG8: 0.66282665 | AH8: 0.66912665 | AI8: 0.65422665 | AJ8: 0.68382665 | AL8: Multi-plane (Bioptic) Kiosk Scanners | AM8: 0.10158705 | AN8: 0.098212011 | AO8: 0.11298872 | AP8: 0.11287797 | AQ8: 0.093125536 | AR8: 0.10928099 | AS8: 0.10017184 | AT8: 0.040958092 | AU8: 0.10835472 | AV8: 0.10439213 | AW8: 0.10381521 | AX8: 0.096618991 | AY8: 0.060431436 | AZ8: 0.048526247 | BA8: 0.09644856 | BB8: 0.1011403 | BC8: 0.11460847 | BD8: 0.11231248 | BE8: 0.10904672 | BF8: 0.11336897 | BG8: 0.11406293 | BH8: 0.11045323 | BI8: 0.11412798 | BJ8: 0.10795171 | BK8: 0.10409936 | BL8: 0.10531551 | BM8: 0.1036309 | BN8: 0.11051738 | BO8: 0.10127065 | BP8: 0.10809411 | BQ8: 0.10340724 | BR8: 0.11325552 | BS8: 0.10541184 | BT8: 0.10768555 | BV8: Multi-plane (Bioptic) Kiosk Scanners | BW8: CMI_Trend_60 | BX8: CMI_Trend_52 | BY8: CMI_Trend_52 | BZ8: CMI_Trend_46 | CA8: CMI_Trend_60 | CB8: CMI_Trend_20 | CC8: CMI_Trend_20 | CD8: CMI_Trend_56 | CE8: CMI_Trend_56 | CF8: CMI_Trend_56 | CG8: CMI_Trend_25 | CH8: CMI_Trend_25 | CI8: CMI_Trend_52 | CJ8: CMI_Trend_38 | CK8: CMI_Trend_56 | CL8: CMI_Trend_38 | CM8: CMI_Trend_38 | CN8: CMI_Trend_60 | CO8: CMI_Trend_20 | CP8: CMI_Trend_56 | CQ8: CMI_Trend_20 | CR8: CMI_Trend_20 | CS8: CMI_Trend_38 | CT8: CMI_Trend_38 | CU8: CMI_Trend_38 | CV8: CMI_Trend_60 | CW8: CMI_Trend_38 | CX8: CMI_Trend_46 | CY8: CMI_Trend_38 | CZ8: CMI_Trend_46 | DA8: CMI_Trend_20 | DB8: CMI_Trend_38 | DC8: CMI_Trend_52 | DD8: CMI_Trend_20
A9: 0.001 | B9: Presentation Kiosk Scanners | C9: 0.079704348 | D9: 0.082804348 | E9: 0.090404348 | F9: 0.086804348 | G9: 0.086404348 | H9: 0.070904348 | I9: 0.090904348 | J9: 0.084704348 | K9: 0.090604348 | L9: 0.074304348 | M9: 0.069904348 | N9: 0.069404348 | O9: 0.088704348 | P9: 0.091904348 | Q9: 0.082304348 | R9: 0.083704348 | S9: 0.075604348 | T9: 0.071404348 | U9: 0.080104348 | V9: 0.074404348 | W9: 0.091304348 | X9: 0.085704348 | Y9: 0.085104348 | Z9: 0.089504348 | AA9: 0.070104348 | AB9: 0.074104348 | AC9: 0.069304348 | AD9: 0.082104348 | AE9: 0.085004348 | AF9: 0.088104348 | AG9: 0.091304348 | AH9: 0.068204348 | AI9: 0.081704348 | AJ9: 0.090104348 | AL9: Presentation Kiosk Scanners | AM9: 0.11069493 | AN9: 0.10778927 | AO9: 0.12066615 | AP9: 0.12010611 | AQ9: 0.10414978 | AR9: 0.1171143 | AS9: 0.10984585 | AT9: 0.05243455 | AU9: 0.11650936 | AV9: 0.11271234 | AW9: 0.1125642 | AX9: 0.10720883 | AY9: 0.072140912 | AZ9: 0.061089182 | BA9: 0.10651939 | BB9: 0.11024818 | BC9: 0.12176433 | BD9: 0.12006745 | BE9: 0.11745097 | BF9: 0.12089362 | BG9: 0.12143784 | BH9: 0.11836566 | BI9: 0.12188296 | BJ9: 0.11610635 | BK9: 0.1125885 | BL9: 0.11406451 | BM9: 0.11292371 | BN9: 0.11850974 | BO9: 0.11037853 | BP9: 0.11641432 | BQ9: 0.11189638 | BR9: 0.12108883 | BS9: 0.11398673 | BT9: 0.11575864 | BV9: Presentation Kiosk Scanners | BW9: CMI_Trend_52 | BX9: CMI_Trend_60 | BY9: CMI_Trend_20 | BZ9: CMI_Trend_60 | CA9: CMI_Trend_25 | CB9: CMI_Trend_20 | CC9: CMI_Trend_46 | CD9: CMI_Trend_20 | CE9: CMI_Trend_20 | CF9: CMI_Trend_52 | CG9: CMI_Trend_56 | CH9: CMI_Trend_25 | CI9: CMI_Trend_25 | CJ9: CMI_Trend_52 | CK9: CMI_Trend_46 | CL9: CMI_Trend_46 | CM9: CMI_Trend_20 | CN9: CMI_Trend_60 | CO9: CMI_Trend_20 | CP9: CMI_Trend_25 | CQ9: CMI_Trend_60 | CR9: CMI_Trend_56 | CS9: CMI_Trend_60 | CT9: CMI_Trend_52 | CU9: CMI_Trend_25 | CV9: CMI_Trend_56 | CW9: CMI_Trend_25 | CX9: CMI_Trend_60 | CY9: CMI_Trend_38 | CZ9: CMI_Trend_60 | DA9: CMI_Trend_52 | DB9: CMI_Trend_46 | DC9: CMI_Trend_38 | DD9: CMI_Trend_25
B10: Dedicated / Retailer-Supplied Mobile Devices | C10: 0.093461817 | D10: 0.10436182 | E10: 0.098761817 | F10: 0.079961817 | G10: 0.10046182 | H10: 0.089661817 | I10: 0.11056182 | J10: 0.10566182 | K10: 0.087361817 | L10: 0.10236182 | M10: 0.090461817 | N10: 0.082761817 | O10: 0.088561817 | P10: 0.082061817 | Q10: 0.094261817 | R10: 0.098161817 | S10: 0.090761817 | T10: 0.083061817 | U10: 0.088561817 | V10: 0.10126182 | W10: 0.087061817 | X10: 0.079961817 | Y10: 0.085661817 | Z10: 0.10266182 | AA10: 0.10996182 | AB10: 0.077961817 | AC10: 0.095461817 | AD10: 0.10686182 | AE10: 0.088461817 | AF10: 0.082661817 | AG10: 0.10126182 | AH10: 0.079761817 | AI10: 0.089261817 | AJ10: 0.093761817 | AL10: Dedicated / Retailer-Supplied Mobile Devices | AM10: 0.1352375 | AN10: 0.13359666 | AO10: 0.14135413 | AP10: 0.13958344 | AQ10: 0.13385626 | AR10: 0.13822234 | AS10: 0.13591391 | AT10: 0.083359604 | AU10: 0.13848325 | AV10: 0.13513239 | AW10: 0.13613969 | AX10: 0.13574476 | AY10: 0.10369387 | AZ10: 0.094941914 | BA10: 0.13365678 | BB10: 0.13479074 | BC10: 0.14104689 | BD10: 0.14096441 | BE10: 0.14009749 | BF10: 0.14116991 | BG10: 0.14131064 | BH10: 0.13968691 | BI10: 0.14277991 | BJ10: 0.13808024 | BK10: 0.13546378 | BL10: 0.13764 | BM10: 0.13796458 | BN10: 0.14004636 | BO10: 0.1349211 | BP10: 0.13883438 | BQ10: 0.13477165 | BR10: 0.14219687 | BS10: 0.13709307 | BT10: 0.1375128 | BV10: Dedicated / Retailer-Supplied Mobile Devices | BW10: CMI_Trend_56 | BX10: CMI_Trend_38 | BY10: CMI_Trend_52 | BZ10: CMI_Trend_56 | CA10: CMI_Trend_56 | CB10: CMI_Trend_46 | CC10: CMI_Trend_60 | CD10: CMI_Trend_38 | CE10: CMI_Trend_46 | CF10: CMI_Trend_46 | CG10: CMI_Trend_52 | CH10: CMI_Trend_56 | CI10: CMI_Trend_20 | CJ10: CMI_Trend_52 | CK10: CMI_Trend_52 | CL10: CMI_Trend_60 | CM10: CMI_Trend_60 | CN10: CMI_Trend_60 | CO10: CMI_Trend_52 | CP10: CMI_Trend_60 | CQ10: CMI_Trend_60 | CR10: CMI_Trend_38 | CS10: CMI_Trend_56 | CT10: CMI_Trend_38 | CU10: CMI_Trend_46 | CV10: CMI_Trend_60 | CW10: CMI_Trend_56 | CX10: CMI_Trend_38 | CY10: CMI_Trend_56 | CZ10: CMI_Trend_38 | DA10: CMI_Trend_46 | DB10: CMI_Trend_60 | DC10: CMI_Trend_38 | DD10: CMI_Trend_38
B11: Smart-Cart Units | C11: 0.053710556 | D11: 0.069410556 | E11: 0.059010556 | F11: 0.043710556 | G11: 0.037510556 | H11: 0.057510556 | I11: 0.053610556 | J11: 0.066810556 | K11: 0.041310556 | L11: 0.044910556 | M11: 0.038510556 | N11: 0.058210556 | O11: 0.051510556 | P11: 0.052710556 | Q11: 0.065510556 | R11: 0.063010556 | S11: 0.064710556 | T11: 0.061110556 | U11: 0.037510556 | V11: 0.069310556 | W11: 0.043810556 | X11: 0.057510556 | Y11: 0.048210556 | Z11: 0.044410556 | AA11: 0.061810556 | AB11: 0.062610556 | AC11: 0.040810556 | AD11: 0.053810556 | AE11: 0.058010556 | AF11: 0.051310556 | AG11: 0.053910556 | AH11: 0.041810556 | AI11: 0.062510556 | AJ11: 0.065310556 | AL11: Smart-Cart Units | AM11: 0.1429911 | AN11: 0.14174985 | AO11: 0.14788998 | AP11: 0.14573682 | AQ11: 0.14324128 | AR11: 0.14489089 | AS11: 0.14414946 | AT11: 0.093129599 | AU11: 0.14542535 | AV11: 0.14221545 | AW11: 0.14358778 | AX11: 0.14475997 | AY11: 0.11366224 | AZ11: 0.10563683 | BA11: 0.14223015 | BB11: 0.14254435 | BC11: 0.14713873 | BD11: 0.14756628 | BE11: 0.14725209 | BF11: 0.1475757 | BG11: 0.14758895 | BH11: 0.14642283 | BI11: 0.14938178 | BJ11: 0.14502235 | BK11: 0.14269064 | BL11: 0.14508808 | BM11: 0.14587562 | BN11: 0.14685031 | BO11: 0.14267471 | BP11: 0.14591743 | BQ11: 0.14199852 | BR11: 0.14886542 | BS11: 0.14439294 | BT11: 0.14438548 | BV11: Smart-Cart Units | BW11: CMI_Trend_25 | BX11: CMI_Trend_20 | BY11: CMI_Trend_46 | BZ11: CMI_Trend_25 | CA11: CMI_Trend_60 | CB11: CMI_Trend_25 | CC11: CMI_Trend_25 | CD11: CMI_Trend_60 | CE11: CMI_Trend_20 | CF11: CMI_Trend_38 | CG11: CMI_Trend_25 | CH11: CMI_Trend_60 | CI11: CMI_Trend_38 | CJ11: CMI_Trend_56 | CK11: CMI_Trend_60 | CL11: CMI_Trend_38 | CM11: CMI_Trend_46 | CN11: CMI_Trend_56 | CO11: CMI_Trend_56 | CP11: CMI_Trend_20 | CQ11: CMI_Trend_25 | CR11: CMI_Trend_25 | CS11: CMI_Trend_46 | CT11: CMI_Trend_46 | CU11: CMI_Trend_52 | CV11: CMI_Trend_25 | CW11: CMI_Trend_56 | CX11: CMI_Trend_38 | CY11: CMI_Trend_20 | CZ11: CMI_Trend_56 | DA11: CMI_Trend_25 | DB11: CMI_Trend_38 | DC11: CMI_Trend_56 | DD11: CMI_Trend_60
B12: Kiosk Terminals / Display + Controller | C12: 0.22919987 | D12: 0.21569987 | E12: 0.22589987 | F12: 0.23809987 | G12: 0.21479987 | H12: 0.24079987 | I12: 0.23639987 | J12: 0.21609987 | K12: 0.22259987 | L12: 0.23669987 | M12: 0.24539987 | N12: 0.23399987 | O12: 0.23099987 | P12: 0.22869987 | Q12: 0.22529987 | R12: 0.21749987 | S12: 0.22789987 | T12: 0.22009987 | U12: 0.21509987 | V12: 0.22829987 | W12: 0.23459987 | X12: 0.23229987 | Y12: 0.24539987 | Z12: 0.24569987 | AA12: 0.22359987 | AB12: 0.22589987 | AC12: 0.21819987 | AD12: 0.24439987 | AE12: 0.23839987 | AF12: 0.23529987 | AG12: 0.22289987 | AH12: 0.23009987 | AI12: 0.22769987 | AJ12: 0.22379987 | AL12: Kiosk Terminals / Display + Controller | AM12: 0.12656345 | AN12: 0.12447559 | AO12: 0.13404241 | AP12: 0.1326996 | AQ12: 0.12335714 | AR12: 0.13076215 | AS12: 0.12670071 | AT12: 0.072429807 | AU12: 0.13071705 | AV12: 0.1272085 | AW12: 0.12780744 | AX12: 0.12565935 | AY12: 0.092542154 | AZ12: 0.082977392 | BA12: 0.12406565 | BB12: 0.1261167 | BC12: 0.13423188 | BD12: 0.13357883 | BE12: 0.13209356 | BF12: 0.13400369 | BG12: 0.13428702 | BH12: 0.13215137 | BI12: 0.13539433 | BJ12: 0.13031404 | BK12: 0.127379 | BL12: 0.12930775 | BM12: 0.12911442 | BN12: 0.1324347 | BO12: 0.12624705 | BP12: 0.13091049 | BQ12: 0.12668688 | BR12: 0.13473669 | BS12: 0.12892663 | BT12: 0.12982425 | BV12: Kiosk Terminals / Display + Controller | BW12: CMI_Trend_52 | BX12: CMI_Trend_52 | BY12: CMI_Trend_60 | BZ12: CMI_Trend_46 | CA12: CMI_Trend_56 | CB12: CMI_Trend_52 | CC12: CMI_Trend_25 | CD12: CMI_Trend_52 | CE12: CMI_Trend_20 | CF12: CMI_Trend_56 | CG12: CMI_Trend_46 | CH12: CMI_Trend_60 | CI12: CMI_Trend_46 | CJ12: CMI_Trend_60 | CK12: CMI_Trend_52 | CL12: CMI_Trend_46 | CM12: CMI_Trend_46 | CN12: CMI_Trend_56 | CO12: CMI_Trend_52 | CP12: CMI_Trend_52 | CQ12: CMI_Trend_38 | CR12: CMI_Trend_20 | CS12: CMI_Trend_25 | CT12: CMI_Trend_46 | CU12: CMI_Trend_20 | CV12: CMI_Trend_46 | CW12: CMI_Trend_52 | CX12: CMI_Trend_38 | CY12: CMI_Trend_38 | CZ12: CMI_Trend_56 | DA12: CMI_Trend_52 | DB12: CMI_Trend_52 | DC12: CMI_Trend_46 | DD12: CMI_Trend_56
B13: Payment Units | C13: 0.051866343 | D13: 0.053666343 | E13: 0.046666343 | F13: 0.051466343 | G13: 0.036366343 | H13: 0.041966343 | I13: 0.042166343 | J13: 0.060466343 | K13: 0.057366343 | L13: 0.050866343 | M13: 0.067366343 | N13: 0.049866343 | O13: 0.066166343 | P13: 0.037866343 | Q13: 0.053766343 | R13: 0.036566343 | S13: 0.046866343 | T13: 0.066366343 | U13: 0.039266343 | V13: 0.067766343 | W13: 0.060766343 | X13: 0.065166343 | Y13: 0.045266343 | Z13: 0.048866343 | AA13: 0.040366343 | AB13: 0.041866343 | AC13: 0.051666343 | AD13: 0.063666343 | AE13: 0.062766343 | AF13: 0.056666343 | AG13: 0.068166343 | AH13: 0.055066343 | AI13: 0.044666343 | AJ13: 0.056766343 | AL13: Payment Units | AM13: 0.10752989 | AN13: 0.10446112 | AO13: 0.1179982 | AP13: 0.11759429 | AQ13: 0.10031879 | AR13: 0.11439218 | AS13: 0.10648408 | AT13: 0.048446419 | AU13: 0.11367558 | AV13: 0.10982102 | AW13: 0.10952388 | AX13: 0.10352881 | AY13: 0.068071807 | AZ13: 0.056723495 | BA13: 0.10301972 | BB13: 0.10708314 | BC13: 0.11927763 | BD13: 0.11737256 | BE13: 0.11453045 | BF13: 0.11827876 | BG13: 0.11887502 | BH13: 0.11561605 | BI13: 0.11918806 | BJ13: 0.11327257 | BK13: 0.10963848 | BL13: 0.11102419 | BM13: 0.10969441 | BN13: 0.11573235 | BO13: 0.1072135 | BP13: 0.113523 | BQ13: 0.10894636 | BR13: 0.11836671 | BS13: 0.11100691 | BT13: 0.1129532 | BV13: Payment Units | BW13: CMI_Trend_60 | BX13: CMI_Trend_38 | BY13: CMI_Trend_46 | BZ13: CMI_Trend_25 | CA13: CMI_Trend_20 | CB13: CMI_Trend_56 | CC13: CMI_Trend_52 | CD13: CMI_Trend_56 | CE13: CMI_Trend_56 | CF13: CMI_Trend_56 | CG13: CMI_Trend_52 | CH13: CMI_Trend_56 | CI13: CMI_Trend_60 | CJ13: CMI_Trend_56 | CK13: CMI_Trend_60 | CL13: CMI_Trend_20 | CM13: CMI_Trend_56 | CN13: CMI_Trend_38 | CO13: CMI_Trend_38 | CP13: CMI_Trend_46 | CQ13: CMI_Trend_56 | CR13: CMI_Trend_20 | CS13: CMI_Trend_60 | CT13: CMI_Trend_56 | CU13: CMI_Trend_20 | CV13: CMI_Trend_56 | CW13: CMI_Trend_20 | CX13: CMI_Trend_20 | CY13: CMI_Trend_46 | CZ13: CMI_Trend_20 | DA13: CMI_Trend_46 | DB13: CMI_Trend_52 | DC13: CMI_Trend_20 | DD13: CMI_Trend_60
B14: Kiosk Cabinet / Enclosure | C14: 0.1929895 | D14: 0.1923895 | E14: 0.1776895 | F14: 0.2047895 | G14: 0.2060895 | H14: 0.1792895 | I14: 0.2028895 | J14: 0.2023895 | K14: 0.1803895 | L14: 0.1838895 | M14: 0.1841895 | N14: 0.1911895 | O14: 0.1995895 | P14: 0.2010895 | Q14: 0.1771895 | R14: 0.1895895 | S14: 0.1893895 | T14: 0.2018895 | U14: 0.1939895 | V14: 0.2089895 | W14: 0.1915895 | X14: 0.1933895 | Y14: 0.1860895 | Z14: 0.1955895 | AA14: 0.1904895 | AB14: 0.1777895 | AC14: 0.1910895 | AD14: 0.1931895 | AE14: 0.1870895 | AF14: 0.1835895 | AG14: 0.1871895 | AH14: 0.1985895 | AI14: 0.1912895 | AJ14: 0.1919895 | AL14: Kiosk Cabinet / Enclosure | AM14: 0.091631135 | AN14: 0.08774301 | AO14: 0.10459645 | AP14: 0.10497681 | AQ14: 0.08107483 | AR14: 0.10071832 | AS14: 0.089597097 | AT14: 0.028413062 | AU14: 0.099440811 | AV14: 0.09529723 | AW14: 0.094251598 | AX14: 0.085043131 | AY14: 0.047631691 | AZ14: 0.034793578 | BA14: 0.085440032 | BB14: 0.091184383 | BC14: 0.10678632 | BD14: 0.10383544 | BE14: 0.099859951 | BF14: 0.10514371 | BG14: 0.10600135 | BH14: 0.10180407 | BI14: 0.10565094 | BJ14: 0.099037801 | BK14: 0.094819797 | BL14: 0.095751901 | BM14: 0.093472838 | BN14: 0.10178086 | BO14: 0.091314737 | BP14: 0.098999213 | BQ14: 0.094127676 | BR14: 0.10469285 | BS14: 0.096038548 | BT14: 0.098860777 | BV14: Kiosk Cabinet / Enclosure | BW14: CMI_Trend_52 | BX14: CMI_Trend_46 | BY14: CMI_Trend_38 | BZ14: CMI_Trend_38 | CA14: CMI_Trend_46 | CB14: CMI_Trend_20 | CC14: CMI_Trend_20 | CD14: CMI_Trend_20 | CE14: CMI_Trend_46 | CF14: CMI_Trend_20 | CG14: CMI_Trend_38 | CH14: CMI_Trend_20 | CI14: CMI_Trend_20 | CJ14: CMI_Trend_56 | CK14: CMI_Trend_60 | CL14: CMI_Trend_60 | CM14: CMI_Trend_20 | CN14: CMI_Trend_25 | CO14: CMI_Trend_25 | CP14: CMI_Trend_56 | CQ14: CMI_Trend_25 | CR14: CMI_Trend_38 | CS14: CMI_Trend_38 | CT14: CMI_Trend_20 | CU14: CMI_Trend_52 | CV14: CMI_Trend_60 | CW14: CMI_Trend_46 | CX14: CMI_Trend_60 | CY14: CMI_Trend_60 | CZ14: CMI_Trend_38 | DA14: CMI_Trend_56 | DB14: CMI_Trend_46 | DC14: CMI_Trend_46 | DD14: CMI_Trend_56
B15: Receipt Printer | C15: 0.06503502 | D15: 0.07803502 | E15: 0.07053502 | F15: 0.06233502 | G15: 0.07033502 | H15: 0.04903502 | I15: 0.07723502 | J15: 0.06103502 | K15: 0.08133502 | L15: 0.05273502 | M15: 0.04923502 | N15: 0.06183502 | O15: 0.07643502 | P15: 0.07163502 | Q15: 0.05153502 | R15: 0.06733502 | S15: 0.08063502 | T15: 0.08133502 | U15: 0.06753502 | V15: 0.06343502 | W15: 0.06753502 | X15: 0.08183502 | Y15: 0.05183502 | Z15: 0.07073502 | AA15: 0.06643502 | AB15: 0.07673502 | AC15: 0.07693502 | AD15: 0.06763502 | AE15: 0.07173502 | AF15: 0.05763502 | AG15: 0.08193502 | AH15: 0.06443502 | AI15: 0.07363502 | AJ15: 0.07793502 | AL15: Receipt Printer | AM15: 0.082793053 | AN15: 0.078449452 | AO15: 0.097146447 | AP15: 0.097962784 | AQ15: 0.070377157 | AR15: 0.093117057 | AS15: 0.080209664 | AT15: 0.022377581 | AU15: 0.091527738 | AV15: 0.087223489 | AW15: 0.085761772 | AX15: 0.074766989 | AY15: 0.036269079 | AZ15: 0.02260279 | BA15: 0.075667523 | BB15: 0.082346301 | BC15: 0.099842436 | BD15: 0.096310183 | BE15: 0.091704658 | BF15: 0.097841959 | BG15: 0.09884491 | BH15: 0.094126023 | BI15: 0.098125685 | BJ15: 0.091124729 | BK15: 0.086582127 | BL15: 0.087262075 | BM15: 0.084455307 | BN15: 0.094025255 | BO15: 0.082476655 | BP15: 0.090925473 | BQ15: 0.085890006 | BR15: 0.097091588 | BS15: 0.08771767 | BT15: 0.091026835 | BV15: Receipt Printer | BW15: CMI_Trend_46 | BX15: CMI_Trend_20 | BY15: CMI_Trend_60 | BZ15: CMI_Trend_25 | CA15: CMI_Trend_20 | CB15: CMI_Trend_56 | CC15: CMI_Trend_60 | CD15: CMI_Trend_56 | CE15: CMI_Trend_46 | CF15: CMI_Trend_56 | CG15: CMI_Trend_60 | CH15: CMI_Trend_20 | CI15: CMI_Trend_46 | CJ15: CMI_Trend_52 | CK15: CMI_Trend_25 | CL15: CMI_Trend_38 | CM15: CMI_Trend_20 | CN15: CMI_Trend_56 | CO15: CMI_Trend_60 | CP15: CMI_Trend_52 | CQ15: CMI_Trend_25 | CR15: CMI_Trend_46 | CS15: CMI_Trend_60 | CT15: CMI_Trend_52 | CU15: CMI_Trend_38 | CV15: CMI_Trend_20 | CW15: CMI_Trend_20 | CX15: CMI_Trend_60 | CY15: CMI_Trend_25 | CZ15: CMI_Trend_60 | DA15: CMI_Trend_56 | DB15: CMI_Trend_20 | DC15: CMI_Trend_25 | DD15: CMI_Trend_38
B16: Others (Scale / Bagging Hardware, Power & Internal Electronics, Mounting / Wiring / Minor Internal Hardware, Embedded Scan Modules, Network & Accessories) | C16: 0.10332527 | D16: 0.10752527 | E16: 0.10972527 | F16: 0.088925265 | G16: 0.088525265 | H16: 0.094025265 | I16: 0.094325265 | J16: 0.11962527 | K16: 0.10132527 | L16: 0.10122527 | M16: 0.099625265 | N16: 0.097525265 | O16: 0.11882527 | P16: 0.096225265 | Q16: 0.089425265 | R16: 0.10452527 | S16: 0.10302527 | T16: 0.11382527 | U16: 0.11862527 | V16: 0.099125265 | W16: 0.11202527 | X16: 0.11732527 | Y16: 0.098225265 | Z16: 0.096825265 | AA16: 0.10352527 | AB16: 0.10782527 | AC16: 0.089825265 | AD16: 0.10282527 | AE16: 0.099225265 | AF16: 0.10552527 | AG16: 0.090825265 | AH16: 0.094425265 | AI16: 0.093625265 | AJ16: 0.10762527 | AL16: Others (Scale / Bagging Hardware, Power & Internal Electronics, Mounting / Wiring / Minor Internal Hardware, Embedded Scan Modules, Network & Accessories) | AM16: 0.11752599 | AN16: 0.11497238 | AO16: 0.12642434 | AP16: 0.12552734 | AQ16: 0.11241814 | AR16: 0.12298941 | AS16: 0.11710151 | AT16: 0.061042081 | AU16: 0.12262547 | AV16: 0.11895263 | AW16: 0.11912609 | AX16: 0.11515139 | AY16: 0.080923212 | AZ16: 0.07051159 | BA16: 0.11407268 | BB16: 0.11707924 | BC16: 0.12713135 | BD16: 0.12588381 | BE16: 0.12375429 | BF16: 0.12653722 | BG16: 0.12696914 | BH16: 0.12430012 | BI16: 0.12769931 | BJ16: 0.12222246 | BK16: 0.1189555 | BL16: 0.1206264 | BM16: 0.11989346 | BN16: 0.12450414 | BO16: 0.11720959 | BP16: 0.12265461 | BQ16: 0.11826337 | BR16: 0.12696394 | BS16: 0.12041804 | BT16: 0.12181359 | BV16: Others (Scale / Bagging Hardware, Power & Internal Electronics, Mounting / Wiring / Minor Internal Hardware, Embedded Scan Modules, Network & Accessories) | BW16: CMI_Trend_38 | BX16: CMI_Trend_60 | BY16: CMI_Trend_46 | BZ16: CMI_Trend_38 | CA16: CMI_Trend_60 | CB16: CMI_Trend_56 | CC16: CMI_Trend_52 | CD16: CMI_Trend_46 | CE16: CMI_Trend_38 | CF16: CMI_Trend_60 | CG16: CMI_Trend_60 | CH16: CMI_Trend_25 | CI16: CMI_Trend_38 | CJ16: CMI_Trend_52 | CK16: CMI_Trend_46 | CL16: CMI_Trend_60 | CM16: CMI_Trend_25 | CN16: CMI_Trend_52 | CO16: CMI_Trend_46 | CP16: CMI_Trend_38 | CQ16: CMI_Trend_56 | CR16: CMI_Trend_38 | CS16: CMI_Trend_46 | CT16: CMI_Trend_60 | CU16: CMI_Trend_38 | CV16: CMI_Trend_52 | CW16: CMI_Trend_38 | CX16: CMI_Trend_38 | CY16: CMI_Trend_56 | CZ16: CMI_Trend_60 | DA16: CMI_Trend_46 | DB16: CMI_Trend_56 | DC16: CMI_Trend_38 | DD16: CMI_Trend_52
B17: Software | C17: 0.17226105 | D17: 0.17346105 | E17: 0.16956105 | F17: 0.18166105 | G17: 0.16406105 | H17: 0.17076105 | I17: 0.18516105 | J17: 0.16726105 | K17: 0.16986105 | L17: 0.18606105 | M17: 0.16886105 | N17: 0.18166105 | O17: 0.17006105 | P17: 0.17606105 | Q17: 0.18506105 | R17: 0.17106105 | S17: 0.17786105 | T17: 0.17626105 | U17: 0.16096105 | V17: 0.17396105 | W17: 0.16536105 | X17: 0.17986105 | Y17: 0.17166105 | Z17: 0.15496105 | AA17: 0.18276105 | AB17: 0.15786105 | AC17: 0.16236105 | AD17: 0.16246105 | AE17: 0.18386105 | AF17: 0.18616105 | AG17: 0.18676105 | AH17: 0.16956105 | AI17: 0.16226105 | AJ17: 0.17886105 | AL17: Software | AM17: =SUMPRODUCT(AM18:AM22,C18:C22) -> 0.12570371 | AN17: =((((((((((((((SUMPRODUCT(AN18:AN22,D18:D22))*0.99)*0.99)*0.99)*0.99)*0.99)*0.99)*0.99)*0.99)*0.99)*0.99)*0.99)*0.99)*0.99)*0.99 -> 0.10716311 | AO17: =((((((((((SUMPRODUCT(AO18:AO22,E18:E22))*0.99)*0.99)*0.99)*0.99)*0.99)*0.99)/0.99)/0.99)/0.99)/0.99 -> 0.13057581 | AP17: =((((((((((((((((SUMPRODUCT(AP18:AP22,F18:F22))*0.99)*0.99)*0.99)*0.99)*0.99)*0.99)*0.99)*0.99)*0.99)/0.99)/0.99)/0.99)/0.99)*0.99)*0.99)*0.99 -> 0.12179527 | AQ17: =SUMPRODUCT(AQ18:AQ22,G18:G22) -> 0.12315277 | AR17: =SUMPRODUCT(AR18:AR22,H18:H22) -> 0.12991999 | AS17: =((((((((SUMPRODUCT(AS18:AS22,I18:I22))*0.99)*0.99)*0.99)*0.99)/0.99)/0.99)/0.99)*0.99 -> 0.12341688 | AT17: =(((((((((((((((((((((SUMPRODUCT(AT18:AT22,J18:J22))/0.99)/0.99)/0.99)/0.99)/0.99)/0.99)/0.99)/0.99)/0.99)/0.99)/0.99)/0.99)/0.99)/0.99)/0.99)/0.99)/0.99)/0.99)/0.99)/0.99)/0.99 -> 0.089175119 | AU17: =((((SUMPRODUCT(AU18:AU22,K18:K22))/0.99)/0.99)/0.99)/0.99 -> 0.13565184 | AV17: =((((((SUMPRODUCT(AV18:AV22,L18:L22))/0.99)/0.99)/0.99)/0.99)/0.99)/0.99 -> 0.13359597 | AW17: =(((((((((((SUMPRODUCT(AW18:AW22,M18:M22))/0.99)/0.99)/0.99)/0.99)/0.99)/0.99)/0.99)/0.99)/0.99)/0.99)/0.99 -> 0.1420517 | AX17: =((((((((((((((SUMPRODUCT(AX18:AX22,N18:N22))*0.99)*0.99)*0.99)*0.99)*0.99)*0.99)*0.99)*0.99)/0.99)/0.99)/0.99)/0.99)/0.99)*0.99 -> 0.11961424 | AY17: =((((((((((SUMPRODUCT(AY18:AY22,O18:O22))/0.99)/0.99)/0.99)/0.99)/0.99)/0.99)/0.99)/0.99)*0.99)*0.99 -> 0.097095423 | AZ17: =(((((((((((((SUMPRODUCT(AZ18:AZ22,P18:P22))/0.99)/0.99)/0.99)/0.99)/0.99)/0.99)/0.99)/0.99)/0.99)/0.99)/0.99)/0.99)/0.99 -> 0.092920255 | BA17: =(((((((((SUMPRODUCT(BA18:BA22,Q18:Q22))*0.99)*0.99)*0.99)*0.99)*0.99)*0.99)*0.99)*0.99)*0.99 -> 0.11302043 | BB17: =SUMPRODUCT(BB18:BB22,R18:R22) -> 0.1248944 | BC17: =(((((((((((((((((SUMPRODUCT(BC18:BC22,S18:S22))*0.99)*0.99)*0.99)*0.99)*0.99)*0.99)*0.99)*0.99)*0.99)*0.99)/0.99)/0.99)/0.99)/0.99)/0.99)/0.99)/0.99 -> 0.13003987 | BD17: =(((((((((SUMPRODUCT(BD18:BD22,T18:T22))*0.99)/0.99)/0.99)/0.99)/0.99)/0.99)/0.99)/0.99)*0.99 -> 0.13948824 | BE17: =(((((((SUMPRODUCT(BE18:BE22,U18:U22))/0.99)/0.99)/0.99)/0.99)/0.99)/0.99)/0.99 -> 0.1412229 | BF17: =(((((((((SUMPRODUCT(BF18:BF22,V18:V22))/0.99)/0.99)/0.99)/0.99)/0.99)/0.99)*0.99)*0.99)*0.99 -> 0.13761875 | BG17: =(((SUMPRODUCT(BG18:BG22,W18:W22))/0.99)/0.99)*0.99 -> 0.13458588 | BH17: =(((((SUMPRODUCT(BH18:BH22,X18:X22))/0.99)/0.99)/0.99)*0.99)*0.99 -> 0.13262755 | BI17: =(((((SUMPRODUCT(BI18:BI22,Y18:Y22))/0.99)/0.99)/0.99)/0.99)/0.99 -> 0.14184823 | BJ17: =(((((((((((SUMPRODUCT(BJ18:BJ22,Z18:Z22))*0.99)*0.99)*0.99)*0.99)*0.99)*0.99)*0.99)*0.99)*0.99)*0.99)*0.99 -> 0.11602706 | BK17: =((((((((SUMPRODUCT(BK18:BK22,AA18:AA22))/0.99)/0.99)/0.99)/0.99)/0.99)/0.99)/0.99)/0.99 -> 0.13721227 | BL17: =(((((((((((SUMPRODUCT(BL18:BL22,AB18:AB22))/0.99)/0.99)/0.99)/0.99)/0.99)/0.99)/0.99)/0.99)/0.99)/0.99)/0.99 -> 0.14327007 | BM17: =((SUMPRODUCT(BM18:BM22,AC18:AC22))/0.99)/0.99 -> 0.13069206 | BN17: =((SUMPRODUCT(BN18:BN22,AD18:AD22))/0.99)/0.99 -> 0.13455162 | BO17: =SUMPRODUCT(BO18:BO22,AE18:AE22) -> 0.12593747 | BP17: =((((((((((((SUMPRODUCT(BP18:BP22,AF18:AF22))/0.99)/0.99)/0.99)/0.99)/0.99)/0.99)/0.99)/0.99)/0.99)*0.99)*0.99)*0.99 -> 0.13777641 | BQ17: =((((((((SUMPRODUCT(BQ18:BQ22,AG18:AG22))/0.99)/0.99)/0.99)/0.99)/0.99)/0.99)/0.99)/0.99 -> 0.13661523 | BR17: =SUMPRODUCT(BR18:BR22,AH18:AH22) -> 0.13412823 | BS17: =(((((((((SUMPRODUCT(BS18:BS22,AI18:AI22))/0.99)/0.99)/0.99)/0.99)/0.99)/0.99)/0.99)/0.99)/0.99 -> 0.14092927 | BT17: =(((SUMPRODUCT(BT18:BT22,AJ18:AJ22))/0.99)/0.99)/0.99 -> 0.13308135 | BV17: Software | BW17: CMI_Trend_60 | BX17: CMI_Trend_25 | BY17: CMI_Trend_25 | BZ17: CMI_Trend_52 | CA17: CMI_Trend_38 | CB17: CMI_Trend_56 | CC17: CMI_Trend_52 | CD17: CMI_Trend_52 | CE17: CMI_Trend_56 | CF17: CMI_Trend_20 | CG17: CMI_Trend_46 | CH17: CMI_Trend_52 | CI17: CMI_Trend_46 | CJ17: CMI_Trend_52 | CK17: CMI_Trend_20 | CL17: CMI_Trend_56 | CM17: CMI_Trend_20 | CN17: CMI_Trend_56 | CO17: CMI_Trend_25 | CP17: CMI_Trend_38 | CQ17: CMI_Trend_56 | CR17: CMI_Trend_56 | CS17: CMI_Trend_46 | CT17: CMI_Trend_56 | CU17: CMI_Trend_25 | CV17: CMI_Trend_25 | CW17: CMI_Trend_56 | CX17: CMI_Trend_56 | CY17: CMI_Trend_38 | CZ17: CMI_Trend_56 | DA17: CMI_Trend_60 | DB17: CMI_Trend_52 | DC17: CMI_Trend_25 | DD17: CMI_Trend_20
B18: Scanning & Decoding software | C18: =1-SUM(C19:C22) -> 0.31824149 | D18: =1-SUM(D19:D22) -> 0.32424149 | E18: =1-SUM(E19:E22) -> 0.31814149 | F18: =1-SUM(F19:F22) -> 0.30774149 | G18: =1-SUM(G19:G22) -> 0.28364149 | H18: =1-SUM(H19:H22) -> 0.32704149 | I18: =1-SUM(I19:I22) -> 0.32214149 | J18: =1-SUM(J19:J22) -> 0.28574149 | ... AJ18: =1-SUM(AJ19:AJ22) -> 0.31774149 | AL18: Scanning & Decoding software | AM18: 0.11230834 | AN18: 0.10948583 | AO18: 0.12202616 | AP18: 0.12138654 | AQ18: 0.10610266 | AR18: 0.11850193 | AS18: 0.11155954 | AT18: 0.054467539 | AU18: 0.1179539 | AV18: 0.11418621 | AW18: 0.11411404 | AX18: 0.10908476 | AY18: 0.07421518 | AZ18: 0.063314635 | BA18: 0.10830338 | BB18: 0.11186159 | BC18: 0.12303195 | BD18: 0.1214412 | BE18: 0.11893973 | BF18: 0.12222656 | BG18: 0.12274426 | BH18: 0.11976731 | BI18: 0.12325671 | BJ18: 0.11755089 | BK18: 0.1140923 | BL18: 0.11561434 | BM18: 0.11456987 | BN18: 0.11992554 | BO18: 0.11199194 | BP18: 0.1178882 | BQ18: 0.11340018 | BR18: 0.12247646 | BS18: 0.11550573 | BT18: 0.11718874 | BV18: Scanning & Decoding software | BW18: CMI_Trend_56 | BX18: CMI_Trend_38 | BY18: CMI_Trend_38 | BZ18: CMI_Trend_52 | CA18: CMI_Trend_60 | CB18: CMI_Trend_46 | CC18: CMI_Trend_38 | CD18: CMI_Trend_46 | CE18: CMI_Trend_52 | CF18: CMI_Trend_38 | CG18: CMI_Trend_20 | CH18: CMI_Trend_38 | CI18: CMI_Trend_38 | CJ18: CMI_Trend_20 | CK18: CMI_Trend_56 | CL18: CMI_Trend_46 | CM18: CMI_Trend_20 | CN18: CMI_Trend_46 | CO18: CMI_Trend_52 | CP18: CMI_Trend_60 | CQ18: CMI_Trend_46 | CR18: CMI_Trend_20 | CS18: CMI_Trend_52 | CT18: CMI_Trend_52 | CU18: CMI_Trend_20 | CV18: CMI_Trend_60 | CW18: CMI_Trend_20 | CX18: CMI_Trend_25 | CY18: CMI_Trend_46 | CZ18: CMI_Trend_60 | DA18: CMI_Trend_46 | DB18: CMI_Trend_25 | DC18: CMI_Trend_38 | DD18: CMI_Trend_60
B19: Computer Vision Software | C19: 0.081608 | D19: 0.072408 | E19: 0.076608 | F19: 0.070208 | G19: 0.091908 | H19: 0.081308 | I19: 0.093308 | J19: 0.089208 | K19: 0.092708 | L19: 0.076008 | M19: 0.085908 | N19: 0.075608 | O19: 0.092508 | P19: 0.073708 | Q19: 0.093008 | R19: 0.073308 | S19: 0.092608 | T19: 0.071108 | U19: 0.092008 | V19: 0.086308 | W19: 0.078908 | X19: 0.072308 | Y19: 0.086608 | Z19: 0.090808 | AA19: 0.089608 | AB19: 0.073708 | AC19: 0.071008 | AD19: 0.085608 | AE19: 0.088308 | AF19: 0.084808 | AG19: 0.082308 | AH19: 0.086308 | AI19: 0.089708 | AJ19: 0.083508 | AL19: Computer Vision Software | AM19: 0.14496433 | AN19: 0.14382477 | AO19: 0.1495533 | AP19: 0.1473028 | AQ19: 0.14562969 | AR19: 0.14658798 | AS19: 0.14624534 | AT19: 0.09561598 | AU19: 0.14719206 | AV19: 0.14401802 | AW19: 0.14548325 | AX19: 0.14705427 | AY19: 0.1161991 | AZ19: 0.1083586 | BA19: 0.14441201 | BB19: 0.14451758 | BC19: 0.14868905 | BD19: 0.1492464 | BE19: 0.14907287 | BF19: 0.14920592 | BG19: 0.14918673 | BH19: 0.14813706 | BI19: 0.1510619 | BJ19: 0.14678905 | BK19: 0.14452982 | BL19: 0.14698356 | BM19: 0.14788891 | BN19: 0.14858186 | BO19: 0.14464793 | BP19: 0.14772001 | BQ19: 0.1438377 | BR19: 0.15056252 | BS19: 0.14625069 | BT19: 0.14613451 | BV19: Computer Vision Software | BW19: CMI_Trend_56 | BX19: CMI_Trend_20 | BY19: CMI_Trend_25 | BZ19: CMI_Trend_25 | CA19: CMI_Trend_52 | CB19: CMI_Trend_52 | CC19: CMI_Trend_60 | CD19: CMI_Trend_56 | CE19: CMI_Trend_25 | CF19: CMI_Trend_56 | CG19: CMI_Trend_25 | CH19: CMI_Trend_25 | CI19: CMI_Trend_38 | CJ19: CMI_Trend_38 | CK19: CMI_Trend_25 | CL19: CMI_Trend_56 | CM19: CMI_Trend_25 | CN19: CMI_Trend_56 | CO19: CMI_Trend_46 | CP19: CMI_Trend_38 | CQ19: CMI_Trend_25 | CR19: CMI_Trend_60 | CS19: CMI_Trend_25 | CT19: CMI_Trend_46 | CU19: CMI_Trend_25 | CV19: CMI_Trend_46 | CW19: CMI_Trend_52 | CX19: CMI_Trend_56 | CY19: CMI_Trend_60 | CZ19: CMI_Trend_56 | DA19: CMI_Trend_56 | DB19: CMI_Trend_46 | DC19: CMI_Trend_56 | DD19: CMI_Trend_52
B20: POS & Payment Integration Software | C20: 0.27722772 | D20: 0.28582772 | E20: 0.28112772 | F20: 0.29432772 | G20: 0.28732772 | H20: 0.26172772 | I20: 0.27132772 | J20: 0.28042772 | K20: 0.28392772 | L20: 0.26252772 | M20: 0.26772772 | N20: 0.28372772 | O20: 0.28152772 | P20: 0.29192772 | Q20: 0.27582772 | R20: 0.28782772 | S20: 0.28662772 | T20: 0.27572772 | U20: 0.28932772 | V20: 0.27752772 | W20: 0.27652772 | X20: 0.28212772 | Y20: 0.28232772 | Z20: 0.27652772 | AA20: 0.26212772 | AB20: 0.26672772 | AC20: 0.27532772 | AD20: 0.28482772 | AE20: 0.27832772 | AF20: 0.26382772 | AG20: 0.28062772 | AH20: 0.29332772 | AI20: 0.29342772 | AJ20: 0.26662772 | AL20: POS & Payment Integration Software | AM20: 0.12923915 | AN20: 0.12728918 | AO20: 0.13629787 | AP20: 0.13482307 | AQ20: 0.12659582 | AR20: 0.13306341 | AS20: 0.12954272 | AT20: 0.075801339 | AU20: 0.1331127 | AV20: 0.1296528 | AW20: 0.13037771 | AX20: 0.12877041 | AY20: 0.095982143 | AZ20: 0.086668108 | BA20: 0.12702424 | BB20: 0.1287924 | BC20: 0.13633412 | BD20: 0.13585707 | BE20: 0.13456255 | BF20: 0.13621427 | BG20: 0.13645361 | BH20: 0.13447587 | BI20: 0.13767257 | BJ20: 0.1327097 | BK20: 0.12987292 | BL20: 0.13187801 | BM20: 0.13184445 | BN20: 0.13478268 | BO20: 0.12892275 | BP20: 0.13335478 | BQ20: 0.1291808 | BR20: 0.13703794 | BS20: 0.13144575 | BT20: 0.13219595 | BV20: POS & Payment Integration Software | BW20: CMI_Trend_20 | BX20: CMI_Trend_56 | BY20: CMI_Trend_60 | BZ20: CMI_Trend_56 | CA20: CMI_Trend_20 | CB20: CMI_Trend_38 | CC20: CMI_Trend_56 | CD20: CMI_Trend_56 | CE20: CMI_Trend_56 | CF20: CMI_Trend_38 | CG20: CMI_Trend_38 | CH20: CMI_Trend_20 | CI20: CMI_Trend_46 | CJ20: CMI_Trend_52 | CK20: CMI_Trend_52 | CL20: CMI_Trend_60 | CM20: CMI_Trend_38 | CN20: CMI_Trend_38 | CO20: CMI_Trend_20 | CP20: CMI_Trend_20 | CQ20: CMI_Trend_52 | CR20: CMI_Trend_38 | CS20: CMI_Trend_60 | CT20: CMI_Trend_56 | CU20: CMI_Trend_46 | CV20: CMI_Trend_56 | CW20: CMI_Trend_38 | CX20: CMI_Trend_56 | CY20: CMI_Trend_52 | CZ20: CMI_Trend_38 | DA20: CMI_Trend_20 | DB20: CMI_Trend_20 | DC20: CMI_Trend_56 | DD20: CMI_Trend_52
B21: Store Operations & Workflow Software | C21: 0.21782178 | D21: 0.21702178 | E21: 0.21672178 | F21: 0.21882178 | G21: 0.22262178 | H21: 0.22382178 | I21: 0.21282178 | J21: 0.23102178 | K21: 0.21792178 | L21: 0.20472178 | M21: 0.22862178 | N21: 0.21212178 | O21: 0.20252178 | P21: 0.21102178 | Q21: 0.22712178 | R21: 0.20742178 | S21: 0.22482178 | T21: 0.22092178 | U21: 0.21362178 | V21: 0.22612178 | W21: 0.20412178 | X21: 0.22202178 | Y21: 0.21962178 | Z21: 0.20352178 | AA21: 0.21452178 | AB21: 0.22582178 | AC21: 0.23192178 | AD21: 0.21412178 | AE21: 0.22712178 | AF21: 0.20672178 | AG21: 0.22232178 | AH21: 0.20422178 | AI21: 0.21932178 | AJ21: 0.22522178 | AL21: Store Operations & Workflow Software | AM21: 0.13658156 | AN21: 0.13500999 | AO21: 0.1424871 | AP21: 0.14065011 | AQ21: 0.13548312 | AR21: 0.13937831 | AS21: 0.13734152 | AT21: 0.085053201 | AU21: 0.13968664 | AV21: 0.13636022 | AW21: 0.1374308 | AX21: 0.13730752 | AY21: 0.10542185 | AZ21: 0.096795844 | BA21: 0.13514295 | BB21: 0.13613481 | BC21: 0.14210289 | BD21: 0.14210882 | BE21: 0.14133772 | BF21: 0.14228034 | BG21: 0.14239896 | BH21: 0.14085456 | BI21: 0.14392433 | BJ21: 0.13928364 | BK21: 0.13671653 | BL21: 0.1389311 | BM21: 0.13933594 | BN21: 0.1412258 | BO21: 0.13626516 | BP21: 0.1400622 | BQ21: 0.13602441 | BR21: 0.14335284 | BS21: 0.13835848 | BT21: 0.13870415 | BV21: Store Operations & Workflow Software | BW21: CMI_Trend_38 | BX21: CMI_Trend_52 | BY21: CMI_Trend_20 | BZ21: CMI_Trend_60 | CA21: CMI_Trend_25 | CB21: CMI_Trend_25 | CC21: CMI_Trend_46 | CD21: CMI_Trend_60 | CE21: CMI_Trend_52 | CF21: CMI_Trend_56 | CG21: CMI_Trend_56 | CH21: CMI_Trend_20 | CI21: CMI_Trend_38 | CJ21: CMI_Trend_60 | CK21: CMI_Trend_56 | CL21: CMI_Trend_52 | CM21: CMI_Trend_25 | CN21: CMI_Trend_25 | CO21: CMI_Trend_25 | CP21: CMI_Trend_25 | CQ21: CMI_Trend_38 | CR21: CMI_Trend_60 | CS21: CMI_Trend_20 | CT21: CMI_Trend_25 | CU21: CMI_Trend_60 | CV21: CMI_Trend_20 | CW21: CMI_Trend_60 | CX21: CMI_Trend_56 | CY21: CMI_Trend_20 | CZ21: CMI_Trend_56 | DA21: CMI_Trend_52 | DB21: CMI_Trend_52 | DC21: CMI_Trend_52 | DD21: CMI_Trend_60
B22: Others (Analytics & Dashboard Software, etc.) | C22: 0.10510101 | D22: 0.10050101 | E22: 0.10740101 | F22: 0.10890101 | G22: 0.11450101 | H22: 0.10610101 | I22: 0.10040101 | J22: 0.11360101 | K22: 0.094301005 | L22: 0.11120101 | M22: 0.10080101 | N22: 0.11980101 | O22: 0.094501005 | P22: 0.10390101 | Q22: 0.10130101 | R22: 0.10250101 | S22: 0.091401005 | T22: 0.11410101 | U22: 0.093001005 | V22: 0.095001005 | W22: 0.10500101 | X22: 0.10510101 | Y22: 0.10250101 | Z22: 0.12050101 | AA22: 0.12070101 | AB22: 0.10880101 | AC22: 0.090101005 | AD22: 0.11230101 | AE22: 0.11730101 | AF22: 0.096901005 | AG22: 0.10490101 | AH22: 0.11300101 | AI22: 0.11740101 | AJ22: 0.10690101 | AL22: Others (Analytics & Dashboard Software, etc.) | AM22: 0.11943911 | AN22: 0.11698409 | AO22: 0.128037 | AP22: 0.12704562 | AQ22: 0.11473379 | AR22: 0.12463481 | AS22: 0.11913355 | AT22: 0.063452728 | AU22: 0.12433836 | AV22: 0.1207003 | AW22: 0.12096383 | AX22: 0.1173758 | AY22: 0.083382804 | AZ22: 0.073150452 | BA22: 0.11618808 | BB22: 0.11899236 | BC22: 0.12863445 | BD22: 0.12751276 | BE22: 0.12551962 | BF22: 0.12811779 | BG22: 0.12851825 | BH22: 0.12596214 | BI22: 0.12932826 | BJ22: 0.12393535 | BK22: 0.12073865 | BL22: 0.12246414 | BM22: 0.12184543 | BN22: 0.12618294 | BO22: 0.11912272 | BP22: 0.12440228 | BQ22: 0.12004653 | BR22: 0.12860934 | BS22: 0.12221921 | BT22: 0.12350935 | BV22: Others (Analytics & Dashboard Software, etc.) | BW22: CMI_Trend_46 | BX22: CMI_Trend_60 | BY22: CMI_Trend_60 | BZ22: CMI_Trend_38 | CA22: CMI_Trend_25 | CB22: CMI_Trend_52 | CC22: CMI_Trend_46 | CD22: CMI_Trend_25 | CE22: CMI_Trend_25 | CF22: CMI_Trend_52 | CG22: CMI_Trend_56 | CH22: CMI_Trend_25 | CI22: CMI_Trend_38 | CJ22: CMI_Trend_20 | CK22: CMI_Trend_56 | CL22: CMI_Trend_46 | CM22: CMI_Trend_60 | CN22: CMI_Trend_25 | CO22: CMI_Trend_56 | CP22: CMI_Trend_60 | CQ22: CMI_Trend_56 | CR22: CMI_Trend_60 | CS22: CMI_Trend_46 | CT22: CMI_Trend_60 | CU22: CMI_Trend_20 | CV22: CMI_Trend_56 | CW22: CMI_Trend_52 | CX22: CMI_Trend_56 | CY22: CMI_Trend_38 | CZ22: CMI_Trend_52 | DA22: CMI_Trend_46 | DB22: CMI_Trend_20 | DC22: CMI_Trend_25 | DD22: CMI_Trend_60
A23: 0.99 | B23: Services | C23: 0.32572284 | D23: 0.31545272 | E23: 0.31007314 | F23: 0.34601855 | G23: 0.34125028 | H23: 0.3175312 | I23: 0.33464806 | J23: 0.32462247 | K23: 0.33159148 | L23: 0.32474473 | M23: 0.30457129 | N23: 0.31007314 | O23: 0.32975753 | P23: 0.33880501 | Q23: 0.33635975 | R23: 0.31912062 | S23: 0.32437794 | T23: 0.30481582 | U23: 0.30689429 | V23: 0.31312972 | W23: 0.30750561 | X23: 0.32792358 | Y23: 0.33330317 | Z23: 0.32205494 | AA23: 0.33868275 | AB23: 0.31374104 | AC23: 0.30065886 | AD23: 0.31679762 | AE23: 0.34076123 | AF23: 0.30836145 | AG23: 0.31679762 | AH23: 0.30713882 | AI23: 0.32144363 | AJ23: 0.33953859 | AL23: Services | AM23: =SUMPRODUCT(AM24:AM25,C24:C25) -> 0.13833864 | AN23: =((((((((((((((SUMPRODUCT(AN24:AN25,D24:D25))*0.99)*0.99)*0.99)*0.99)*0.99)*0.99)*0.99)*0.99)*0.99)*0.99)*0.99)*0.99)*0.99)*0.99 -> 0.11873169 | AO23: =((((((((((SUMPRODUCT(AO24:AO25,E24:E25))*0.99)*0.99)*0.99)*0.99)*0.99)*0.99)/0.99)/0.99)/0.99)/0.99 -> 0.14127576 | AP23: =((((((((((((((((SUMPRODUCT(AP24:AP25,F24:F25))*0.99)*0.99)*0.99)*0.99)*0.99)*0.99)*0.99)*0.99)*0.99)/0.99)/0.99)/0.99)/0.99)*0.99)*0.99)*0.99 -> 0.13104359 | AQ23: =SUMPRODUCT(AQ24:AQ25,G24:G25) -> 0.13776606 | AR23: =SUMPRODUCT(AR24:AR25,H24:H25) -> 0.14105422 | AS23: =((((((((SUMPRODUCT(AS24:AS25,I24:I25))*0.99)*0.99)*0.99)*0.99)/0.99)/0.99)/0.99)*0.99 -> 0.13628944 | AT23: =(((((((((((((((((((((SUMPRODUCT(AT24:AT25,J24:J25))/0.99)/0.99)/0.99)/0.99)/0.99)/0.99)/0.99)/0.99)/0.99)/0.99)/0.99)/0.99)/0.99)/0.99)/0.99)/0.99)/0.99)/0.99)/0.99)/0.99)/0.99 -> 0.10773421 | AU23: =((((SUMPRODUCT(AU24:AU25,K24:K25))/0.99)/0.99)/0.99)/0.99 -> 0.14701345 | AV23: =((((((SUMPRODUCT(AV24:AV25,L24:L25))/0.99)/0.99)/0.99)/0.99)/0.99)/0.99 -> 0.14668027 | AW23: =(((((((((((SUMPRODUCT(AW24:AW25,M24:M25))/0.99)/0.99)/0.99)/0.99)/0.99)/0.99)/0.99)/0.99)/0.99)/0.99)/0.99 -> 0.15561511 | AX23: =((((((((((((((SUMPRODUCT(AX24:AX25,N24:N25))*0.99)*0.99)*0.99)*0.99)*0.99)*0.99)*0.99)*0.99)/0.99)/0.99)/0.99)/0.99)/0.99)*0.99 -> 0.13366049 | AY23: =((((((((((SUMPRODUCT(AY24:AY25,O24:O25))/0.99)/0.99)/0.99)/0.99)/0.99)/0.99)/0.99)/0.99)*0.99)*0.99 -> 0.11459374 | AZ23: =(((((((((((((SUMPRODUCT(AZ24:AZ25,P24:P25))/0.99)/0.99)/0.99)/0.99)/0.99)/0.99)/0.99)/0.99)/0.99)/0.99)/0.99)/0.99)/0.99 -> 0.11327906 | BA23: =(((((((((SUMPRODUCT(BA24:BA25,Q24:Q25))*0.99)*0.99)*0.99)*0.99)*0.99)*0.99)*0.99)*0.99)*0.99 -> 0.12528264 | BB23: =SUMPRODUCT(BB24:BB25,R24:R25) -> 0.13806213 | BC23: =(((((((((((((((((SUMPRODUCT(BC24:BC25,S24:S25))*0.99)*0.99)*0.99)*0.99)*0.99)*0.99)*0.99)*0.99)*0.99)*0.99)/0.99)/0.99)/0.99)/0.99)/0.99)/0.99)/0.99 -> 0.13926438 | BD23: =(((((((((SUMPRODUCT(BD24:BD25,T24:T25))*0.99)/0.99)/0.99)/0.99)/0.99)/0.99)/0.99)/0.99)*0.99 -> 0.15097116 | BE23: =(((((((SUMPRODUCT(BE24:BE25,U24:U25))/0.99)/0.99)/0.99)/0.99)/0.99)/0.99)/0.99 -> 0.15339328 | BF23: =(((((((((SUMPRODUCT(BF24:BF25,V24:V25))/0.99)/0.99)/0.99)/0.99)/0.99)/0.99)*0.99)*0.99)*0.99 -> 0.14813844 | BG23: =(((SUMPRODUCT(BG24:BG25,W24:W25))/0.99)/0.99)*0.99 -> 0.14535714 | BH23: =(((((SUMPRODUCT(BH24:BH25,X24:X25))/0.99)/0.99)/0.99)*0.99)*0.99 -> 0.1436885 | BI23: =(((((SUMPRODUCT(BI24:BI25,Y24:Y25))/0.99)/0.99)/0.99)/0.99)/0.99 -> 0.15273971 | BJ23: =(((((((((((SUMPRODUCT(BJ24:BJ25,Z24:Z25))*0.99)*0.99)*0.99)*0.99)*0.99)*0.99)*0.99)*0.99)*0.99)*0.99)*0.99 -> 0.12626269 | BK23: =((((((((SUMPRODUCT(BK24:BK25,AA24:AA25))/0.99)/0.99)/0.99)/0.99)/0.99)/0.99)/0.99)/0.99 -> 0.14986922 | BL23: =(((((((((((SUMPRODUCT(BL24:BL25,AB24:AB25))/0.99)/0.99)/0.99)/0.99)/0.99)/0.99)/0.99)/0.99)/0.99)/0.99)/0.99 -> 0.15704252 | BM23: =((SUMPRODUCT(BM24:BM25,AC24:AC25))/0.99)/0.99 -> 0.14399834 | BN23: =((SUMPRODUCT(BN24:BN25,AD24:AD25))/0.99)/0.99 -> 0.14577837 | BO23: =SUMPRODUCT(BO24:BO25,AE24:AE25) -> 0.13781477 | BP23: =((((((((((((SUMPRODUCT(BP24:BP25,AF24:AF25))/0.99)/0.99)/0.99)/0.99)/0.99)/0.99)/0.99)/0.99)/0.99)*0.99)*0.99)*0.99 -> 0.15031813 | BQ23: =((((((((SUMPRODUCT(BQ24:BQ25,AG24:AG25))/0.99)/0.99)/0.99)/0.99)/0.99)/0.99)/0.99)/0.99 -> 0.14939186 | BR23: =SUMPRODUCT(BR24:BR25,AH24:AH25) -> 0.1447405 | BS23: =(((((((((SUMPRODUCT(BS24:BS25,AI24:AI25))/0.99)/0.99)/0.99)/0.99)/0.99)/0.99)/0.99)/0.99)/0.99 -> 0.15316907 | BT23: =(((SUMPRODUCT(BT24:BT25,AJ24:AJ25))/0.99)/0.99)/0.99 -> 0.14460485 | BV23: Services | BW23: CMI_Trend_38 | BX23: CMI_Trend_52 | BY23: CMI_Trend_38 | BZ23: CMI_Trend_20 | CA23: CMI_Trend_20 | CB23: CMI_Trend_20 | CC23: CMI_Trend_46 | CD23: CMI_Trend_52 | CE23: CMI_Trend_56 | CF23: CMI_Trend_25 | CG23: CMI_Trend_46 | CH23: CMI_Trend_46 | CI23: CMI_Trend_20 | CJ23: CMI_Trend_38 | CK23: CMI_Trend_52 | CL23: CMI_Trend_52 | CM23: CMI_Trend_38 | CN23: CMI_Trend_38 | CO23: CMI_Trend_52 | CP23: CMI_Trend_38 | CQ23: CMI_Trend_52 | CR23: CMI_Trend_25 | CS23: CMI_Trend_46 | CT23: CMI_Trend_60 | CU23: CMI_Trend_60 | CV23: CMI_Trend_38 | CW23: CMI_Trend_60 | CX23: CMI_Trend_20 | CY23: CMI_Trend_46 | CZ23: CMI_Trend_25 | DA23: CMI_Trend_25 | DB23: CMI_Trend_56 | DC23: CMI_Trend_38 | DD23: CMI_Trend_52
B24: Managed Services | C24: 0.57425743 | D24: 0.56085743 | E24: 0.58995743 | F24: 0.57145743 | G24: 0.58395743 | H24: 0.58865743 | I24: 0.56355743 | J24: 0.57235743 | K24: 0.57095743 | L24: 0.58505743 | M24: 0.59065743 | N24: 0.56085743 | O24: 0.58635743 | P24: 0.58435743 | Q24: 0.57815743 | R24: 0.58705743 | S24: 0.57845743 | T24: 0.57135743 | U24: 0.57535743 | V24: 0.57485743 | W24: 0.58185743 | X24: 0.56305743 | Y24: 0.55955743 | Z24: 0.58815743 | AA24: 0.56915743 | AB24: 0.57325743 | AC24: 0.57455743 | AD24: 0.58365743 | AE24: 0.55865743 | AF24: 0.56225743 | AG24: 0.58945743 | AH24: 0.56345743 | AI24: 0.56705743 | AJ24: 0.57835743 | AL24: Managed Services | AM24: 0.14400086 | AN24: 0.14281164 | AO24: 0.14874115 | AP24: 0.14653817 | AQ24: 0.14446349 | AR24: 0.14575934 | AS24: 0.14522198 | AT24: 0.094401949 | AU24: 0.14632943 | AV24: 0.14313788 | AW24: 0.14455775 | AX24: 0.14593403 | AY24: 0.11496042 | AZ24: 0.10702964 | BA24: 0.14334667 | BB24: 0.14355411 | BC24: 0.14793207 | BD24: 0.14842604 | BE24: 0.14818384 | BF24: 0.14840993 | BG24: 0.14840658 | BH24: 0.14730005 | BI24: 0.15024155 | BJ24: 0.14592642 | BK24: 0.1436318 | BL24: 0.14605805 | BM24: 0.14690588 | BN24: 0.14773639 | BO24: 0.14368446 | BP24: 0.14683986 | BQ24: 0.14293968 | BR24: 0.14973387 | BS24: 0.1453436 | BT24: 0.14528051 | BV24: Managed Services | BW24: CMI_Trend_60 | BX24: CMI_Trend_52 | BY24: CMI_Trend_46 | BZ24: CMI_Trend_60 | CA24: CMI_Trend_46 | CB24: CMI_Trend_56 | CC24: CMI_Trend_60 | CD24: CMI_Trend_60 | CE24: CMI_Trend_56 | CF24: CMI_Trend_25 | CG24: CMI_Trend_60 | CH24: CMI_Trend_60 | CI24: CMI_Trend_25 | CJ24: CMI_Trend_38 | CK24: CMI_Trend_46 | CL24: CMI_Trend_38 | CM24: CMI_Trend_46 | CN24: CMI_Trend_25 | CO24: CMI_Trend_52 | CP24: CMI_Trend_60 | CQ24: CMI_Trend_60 | CR24: CMI_Trend_60 | CS24: CMI_Trend_25 | CT24: CMI_Trend_52 | CU24: CMI_Trend_20 | CV24: CMI_Trend_60 | CW24: CMI_Trend_38 | CX24: CMI_Trend_60 | CY24: CMI_Trend_20 | CZ24: CMI_Trend_56 | DA24: CMI_Trend_20 | DB24: CMI_Trend_52 | DC24: CMI_Trend_60 | DD24: CMI_Trend_25
B25: Professional Services | C25: =1-C24 -> 0.42574257 | D25: =1-D24 -> 0.43914257 | E25: =1-E24 -> 0.41004257 | F25: =1-F24 -> 0.42854257 | G25: =1-G24 -> 0.41604257 | H25: =1-H24 -> 0.41134257 | I25: =1-I24 -> 0.43644257 | J25: =1-J24 -> 0.42764257 | ... AJ25: =1-AJ24 -> 0.42164257 | AL25: Professional Services | AM25: 0.13070124 | AN25: 0.12882662 | AO25: 0.13753033 | AP25: 0.1359834 | AQ25: 0.12836554 | AR25: 0.13432089 | AS25: 0.13109569 | AT25: 0.077643657 | AU25: 0.13442177 | AV25: 0.13098844 | AW25: 0.13178218 | AX25: 0.1304704 | AY25: 0.097861866 | AZ25: 0.088684838 | BA25: 0.12864091 | BB25: 0.13025449 | BC25: 0.13748285 | BD25: 0.13710198 | BE25: 0.13591168 | BF25: 0.1374222 | BG25: 0.1376375 | BH25: 0.13574606 | BI25: 0.13891748 | BJ25: 0.13401876 | BK25: 0.13123569 | BL25: 0.13328249 | BM25: 0.13333622 | BN25: 0.13606569 | BO25: 0.13038484 | BP25: 0.13469043 | BQ25: 0.13054357 | BR25: 0.13829542 | BS25: 0.13282228 | BT25: 0.13349193 | BV25: Professional Services | BW25: CMI_Trend_38 | BX25: CMI_Trend_56 | BY25: CMI_Trend_38 | BZ25: CMI_Trend_52 | CA25: CMI_Trend_38 | CB25: CMI_Trend_60 | CC25: CMI_Trend_46 | CD25: CMI_Trend_25 | CE25: CMI_Trend_60 | CF25: CMI_Trend_38 | CG25: CMI_Trend_56 | CH25: CMI_Trend_52 | CI25: CMI_Trend_20 | CJ25: CMI_Trend_60 | CK25: CMI_Trend_52 | CL25: CMI_Trend_60 | CM25: CMI_Trend_46 | CN25: CMI_Trend_52 | CO25: CMI_Trend_46 | CP25: CMI_Trend_60 | CQ25: CMI_Trend_46 | CR25: CMI_Trend_56 | CS25: CMI_Trend_20 | CT25: CMI_Trend_46 | CU25: CMI_Trend_52 | CV25: CMI_Trend_25 | CW25: CMI_Trend_46 | CX25: CMI_Trend_60 | CY25: CMI_Trend_25 | CZ25: CMI_Trend_52 | DA25: CMI_Trend_52 | DB25: CMI_Trend_60 | DC25: CMI_Trend_46 | DD25: CMI_Trend_60
AY26: =AY4-AY2 -> 2.8928821e-05 | AZ26: =AZ4-AZ2 -> -1.5372824e-05
B27: By Product Type | AL27: By Product Type | BV27: By Product Type
B28: Fixed-Position Self-Scanning Kiosks | C28: =C55 -> 0.8676332 | D28: =D55 -> 0.8811332 | E28: =E55 -> 0.8727332 | F28: =F55 -> 0.8764332 | G28: =G55 -> 0.8517332 | H28: =H55 -> 0.8803332 | I28: =I55 -> 0.8671332 | J28: =J55 -> 0.8523332 | ... AJ28: =AJ55 -> 0.8774332 | AL28: Fixed-Position Self-Scanning Kiosks | AM28: =SUMPRODUCT(AM29:AM31,C29:C31) -> 0.11499798 | AN28: =SUMPRODUCT(AN29:AN31,D29:D31) -> 0.10754378 | AO28: =SUMPRODUCT(AO29:AO31,E29:E31) -> 0.14755071 | AP28: =SUMPRODUCT(AP29:AP31,F29:F31) -> 0.15643188 | AQ28: =SUMPRODUCT(AQ29:AQ31,G29:G31) -> 0.089225007 | AR28: =SUMPRODUCT(AR29:AR31,H29:H31) -> 0.1412737 | AS28: =SUMPRODUCT(AS29:AS31,I29:I31) -> 0.10818509 | AT28: =SUMPRODUCT(AT29:AT31,J29:J31) -> 0.068624908 | ... BT28: =SUMPRODUCT(BT29:BT31,AJ29:AJ31) -> 0.13614676 | BV28: Fixed-Position Self-Scanning Kiosks | BW28: CMI_Trend_52 | BX28: CMI_Trend_52 | BY28: CMI_Trend_56 | BZ28: CMI_Trend_56 | CA28: CMI_Trend_20 | CB28: CMI_Trend_46 | CC28: CMI_Trend_20 | CD28: CMI_Trend_52 | CE28: CMI_Trend_52 | CF28: CMI_Trend_56 | CG28: CMI_Trend_56 | CH28: CMI_Trend_56 | CI28: CMI_Trend_25 | CJ28: CMI_Trend_38 | CK28: CMI_Trend_46 | CL28: CMI_Trend_20 | CM28: CMI_Trend_56 | CN28: CMI_Trend_52 | CO28: CMI_Trend_25 | CP28: CMI_Trend_52 | CQ28: CMI_Trend_25 | CR28: CMI_Trend_20 | CS28: CMI_Trend_46 | CT28: CMI_Trend_20 | CU28: CMI_Trend_38 | CV28: CMI_Trend_38 | CW28: CMI_Trend_52 | CX28: CMI_Trend_25 | CY28: CMI_Trend_38 | CZ28: CMI_Trend_60 | DA28: CMI_Trend_20 | DB28: CMI_Trend_25 | DC28: CMI_Trend_38 | DD28: CMI_Trend_25
B29: Single-Plane Self-Scanning Kiosks | C29: 0.37799855 | D29: 0.36609855 | E29: 0.36199855 | F29: 0.38649855 | G29: 0.36679855 | H29: 0.37899855 | I29: 0.38259855 | J29: 0.36959855 | K29: 0.39509855 | L29: 0.39329855 | M29: 0.37209855 | N29: 0.37969855 | O29: 0.38099855 | P29: 0.36589855 | Q29: 0.37049855 | R29: 0.37189855 | S29: 0.36239855 | T29: 0.38409855 | U29: 0.37239855 | V29: 0.36289855 | W29: 0.37399855 | X29: 0.37499855 | Y29: 0.38049855 | Z29: 0.37649855 | AA29: 0.36769855 | AB29: 0.38049855 | AC29: 0.36809855 | AD29: 0.37019855 | AE29: 0.36419855 | AF29: 0.39009855 | AG29: 0.37399855 | AH29: 0.38859855 | AI29: 0.37639855 | AJ29: 0.39249855 | AL29: Single-Plane Self-Scanning Kiosks | AM29: 0.10635961 | AN29: 0.098786495 | AO29: 0.13873346 | AP29: 0.14798896 | AQ29: 0.080544311 | AR29: 0.13258846 | AS29: 0.099703867 | AT29: 0.060003192 | AU29: 0.12592559 | AV29: 0.12032184 | AW29: 0.11294171 | AX29: 0.087029482 | AY29: 0.074651209 | AZ29: 0.067457257 | BA29: 0.092631885 | BB29: 0.10500642 | BC29: 0.1509951 | BD29: 0.13588581 | BE29: 0.12077089 | BF29: 0.14233556 | BG29: 0.14549158 | BH29: 0.13087737 | BI29: 0.13837216 | BJ29: 0.125084 | BK29: 0.11794724 | BL29: 0.11443059 | BM29: 0.1040472 | BN29: 0.13065751 | BO29: 0.10650458 | BP29: 0.12228706 | BQ29: 0.11656502 | BR29: 0.13465397 | BS29: 0.11649277 | BT29: 0.12762544 | BV29: Single-Plane Self-Scanning Kiosks | BW29: CMI_Trend_38 | BX29: CMI_Trend_20 | BY29: CMI_Trend_38 | BZ29: CMI_Trend_52 | CA29: CMI_Trend_60 | CB29: CMI_Trend_20 | CC29: CMI_Trend_38 | CD29: CMI_Trend_60 | CE29: CMI_Trend_25 | CF29: CMI_Trend_56 | CG29: CMI_Trend_56 | CH29: CMI_Trend_56 | CI29: CMI_Trend_38 | CJ29: CMI_Trend_52 | CK29: CMI_Trend_46 | CL29: CMI_Trend_46 | CM29: CMI_Trend_52 | CN29: CMI_Trend_60 | CO29: CMI_Trend_25 | CP29: CMI_Trend_60 | CQ29: CMI_Trend_46 | CR29: CMI_Trend_52 | CS29: CMI_Trend_60 | CT29: CMI_Trend_20 | CU29: CMI_Trend_20 | CV29: CMI_Trend_46 | CW29: CMI_Trend_52 | CX29: CMI_Trend_25 | CY29: CMI_Trend_25 | CZ29: CMI_Trend_46 | DA29: CMI_Trend_25 | DB29: CMI_Trend_60 | DC29: CMI_Trend_25 | DD29: CMI_Trend_20
B30: Multi-Plane Self-Scanning Kiosks | C30: 0.44083482 | D30: 0.44323482 | E30: 0.44653482 | F30: 0.42473482 | G30: 0.43403482 | H30: 0.44803482 | I30: 0.42543482 | J30: 0.42943482 | K30: 0.44533482 | L30: 0.43563482 | M30: 0.43693482 | N30: 0.44813482 | O30: 0.43643482 | P30: 0.42693482 | Q30: 0.44803482 | R30: 0.45133482 | S30: 0.45593482 | T30: 0.42573482 | U30: 0.45803482 | V30: 0.44123482 | W30: 0.42783482 | X30: 0.44843482 | Y30: 0.43083482 | Z30: 0.45183482 | AA30: 0.43173482 | AB30: 0.42543482 | AC30: 0.45713482 | AD30: 0.44473482 | AE30: 0.45653482 | AF30: 0.44933482 | AG30: 0.42663482 | AH30: 0.45083482 | AI30: 0.44093482 | AJ30: 0.44153482 | AL30: Multi-Plane Self-Scanning Kiosks | AM30: 0.12248521 | AN30: 0.1149121 | AO30: 0.15485906 | AP30: 0.16411457 | AQ30: 0.096669917 | AR30: 0.14871406 | AS30: 0.11582947 | AT30: 0.076128798 | AU30: 0.1420512 | AV30: 0.13644745 | AW30: 0.12906731 | AX30: 0.10315509 | AY30: 0.090776816 | AZ30: 0.083582863 | BA30: 0.10875749 | BB30: 0.12113203 | BC30: 0.16712071 | BD30: 0.15201141 | BE30: 0.13689649 | BF30: 0.15846116 | BG30: 0.16161718 | BH30: 0.14700298 | BI30: 0.15449776 | BJ30: 0.14120961 | BK30: 0.13407285 | BL30: 0.1305562 | BM30: 0.12017281 | BN30: 0.14678312 | BO30: 0.12263019 | BP30: 0.13841267 | BQ30: 0.13269063 | BR30: 0.15077957 | BS30: 0.13261838 | BT30: 0.14375105 | BV30: Multi-Plane Self-Scanning Kiosks | BW30: CMI_Trend_52 | BX30: CMI_Trend_20 | BY30: CMI_Trend_38 | BZ30: CMI_Trend_52 | CA30: CMI_Trend_38 | CB30: CMI_Trend_20 | CC30: CMI_Trend_60 | CD30: CMI_Trend_52 | CE30: CMI_Trend_38 | CF30: CMI_Trend_56 | CG30: CMI_Trend_60 | CH30: CMI_Trend_60 | CI30: CMI_Trend_46 | CJ30: CMI_Trend_52 | CK30: CMI_Trend_60 | CL30: CMI_Trend_20 | CM30: CMI_Trend_56 | CN30: CMI_Trend_25 | CO30: CMI_Trend_38 | CP30: CMI_Trend_60 | CQ30: CMI_Trend_60 | CR30: CMI_Trend_38 | CS30: CMI_Trend_52 | CT30: CMI_Trend_56 | CU30: CMI_Trend_38 | CV30: CMI_Trend_20 | CW30: CMI_Trend_56 | CX30: CMI_Trend_20 | CY30: CMI_Trend_38 | CZ30: CMI_Trend_46 | DA30: CMI_Trend_56 | DB30: CMI_Trend_56 | DC30: CMI_Trend_46 | DD30: CMI_Trend_60
B31: Presentation Self-Scanning Kiosks | C31: =1-SUM(C29:C30) -> 0.18116663 | D31: =1-SUM(D29:D30) -> 0.19066663 | E31: =1-SUM(E29:E30) -> 0.19146663 | F31: =1-SUM(F29:F30) -> 0.18876663 | G31: =1-SUM(G29:G30) -> 0.19916663 | H31: =1-SUM(H29:H30) -> 0.17296663 | I31: =1-SUM(I29:I30) -> 0.19196663 | J31: =1-SUM(J29:J30) -> 0.20096663 | ... AJ31: =1-SUM(AJ29:AJ30) -> 0.16596663 | AL31: Presentation Self-Scanning Kiosks | AM31: 0.1148029 | AN31: 0.10722978 | AO31: 0.14717675 | AP31: 0.15643225 | AQ31: 0.088987601 | AR31: 0.14103174 | AS31: 0.10814716 | AT31: 0.068446482 | AU31: 0.13436888 | AV31: 0.12876513 | AW31: 0.121385 | AX31: 0.095472772 | AY31: 0.083094499 | AZ31: 0.075900547 | BA31: 0.10107517 | BB31: 0.11344971 | BC31: 0.15943839 | BD31: 0.14432909 | BE31: 0.12921418 | BF31: 0.15077885 | BG31: 0.15393486 | BH31: 0.13932066 | BI31: 0.14681545 | BJ31: 0.13352729 | BK31: 0.12639053 | BL31: 0.12287388 | BM31: 0.11249049 | BN31: 0.1391008 | BO31: 0.11494787 | BP31: 0.13073035 | BQ31: 0.12500831 | BR31: 0.14309726 | BS31: 0.12493606 | BT31: 0.13606873 | BV31: Presentation Self-Scanning Kiosks | BW31: CMI_Trend_38 | BX31: CMI_Trend_20 | BY31: CMI_Trend_56 | BZ31: CMI_Trend_46 | CA31: CMI_Trend_56 | CB31: CMI_Trend_52 | CC31: CMI_Trend_38 | CD31: CMI_Trend_52 | CE31: CMI_Trend_46 | CF31: CMI_Trend_20 | CG31: CMI_Trend_46 | CH31: CMI_Trend_25 | CI31: CMI_Trend_46 | CJ31: CMI_Trend_20 | CK31: CMI_Trend_38 | CL31: CMI_Trend_52 | CM31: CMI_Trend_38 | CN31: CMI_Trend_60 | CO31: CMI_Trend_60 | CP31: CMI_Trend_20 | CQ31: CMI_Trend_56 | CR31: CMI_Trend_25 | CS31: CMI_Trend_20 | CT31: CMI_Trend_25 | CU31: CMI_Trend_20 | CV31: CMI_Trend_52 | CW31: CMI_Trend_38 | CX31: CMI_Trend_52 | CY31: CMI_Trend_46 | CZ31: CMI_Trend_20 | DA31: CMI_Trend_25 | DB31: CMI_Trend_25 | DC31: CMI_Trend_20 | DD31: CMI_Trend_25
B32: Mobile Self-Scanning Solutions | C32: =C62 -> 0.1323668 | D32: =D62 -> 0.1188668 | E32: =E62 -> 0.1272668 | F32: =F62 -> 0.1235668 | G32: =G62 -> 0.1482668 | H32: =H62 -> 0.1196668 | I32: =I62 -> 0.1328668 | J32: =J62 -> 0.1476668 | ... AJ32: =AJ62 -> 0.1225668 | AL32: Mobile Self-Scanning Solutions | AM32: =SUMPRODUCT(AM33:AM35,C33:C35) -> 0.17203577 | AN32: =SUMPRODUCT(AN33:AN35,D33:D35) -> 0.16446311 | AO32: =SUMPRODUCT(AO33:AO35,E33:E35) -> 0.2047986 | AP32: =SUMPRODUCT(AP33:AP35,F33:F35) -> 0.21293484 | AQ32: =SUMPRODUCT(AQ33:AQ35,G33:G35) -> 0.14635156 | AR32: =SUMPRODUCT(AR33:AR35,H33:H35) -> 0.19806459 | AS32: =SUMPRODUCT(AS33:AS35,I33:I35) -> 0.16559138 | AT32: =SUMPRODUCT(AT33:AT35,J33:J35) -> 0.1258188 | ... BT32: =SUMPRODUCT(BT33:BT35,AJ33:AJ35) -> 0.19289804 | BV32: Mobile Self-Scanning Solutions | BW32: CMI_Trend_46 | BX32: CMI_Trend_52 | BY32: CMI_Trend_46 | BZ32: CMI_Trend_56 | CA32: CMI_Trend_60 | CB32: CMI_Trend_60 | CC32: CMI_Trend_60 | CD32: CMI_Trend_20 | CE32: CMI_Trend_56 | CF32: CMI_Trend_46 | CG32: CMI_Trend_60 | CH32: CMI_Trend_46 | CI32: CMI_Trend_25 | CJ32: CMI_Trend_38 | CK32: CMI_Trend_38 | CL32: CMI_Trend_20 | CM32: CMI_Trend_20 | CN32: CMI_Trend_46 | CO32: CMI_Trend_38 | CP32: CMI_Trend_38 | CQ32: CMI_Trend_46 | CR32: CMI_Trend_56 | CS32: CMI_Trend_56 | CT32: CMI_Trend_46 | CU32: CMI_Trend_60 | CV32: CMI_Trend_52 | CW32: CMI_Trend_25 | CX32: CMI_Trend_56 | CY32: CMI_Trend_60 | CZ32: CMI_Trend_38 | DA32: CMI_Trend_52 | DB32: CMI_Trend_52 | DC32: CMI_Trend_25 | DD32: CMI_Trend_56
B33: Dedicated Mobile Self-Scanning Devices | C33: 0.50546101 | D33: 0.50976101 | E33: 0.50276101 | F33: 0.52026101 | G33: 0.49716101 | H33: 0.51546101 | I33: 0.50586101 | J33: 0.50286101 | K33: 0.50336101 | L33: 0.50486101 | M33: 0.50626101 | N33: 0.52106101 | O33: 0.49056101 | P33: 0.49616101 | Q33: 0.51456101 | R33: 0.49566101 | S33: 0.51196101 | T33: 0.49616101 | U33: 0.51806101 | V33: 0.51796101 | W33: 0.49086101 | X33: 0.49326101 | Y33: 0.51976101 | Z33: 0.50016101 | AA33: 0.49636101 | AB33: 0.51266101 | AC33: 0.49536101 | AD33: 0.51446101 | AE33: 0.51276101 | AF33: 0.50786101 | AG33: 0.52216101 | AH33: 0.51326101 | AI33: 0.51556101 | AJ33: 0.51776101 | AL33: Dedicated Mobile Self-Scanning Devices | AM33: 0.15546195 | AN33: 0.14788884 | AO33: 0.1878358 | AP33: 0.19709131 | AQ33: 0.12964666 | AR33: 0.1816908 | AS33: 0.14880621 | AT33: 0.10910554 | AU33: 0.17502794 | AV33: 0.16942419 | AW33: 0.16204405 | AX33: 0.13613183 | AY33: 0.12375356 | AZ33: 0.1165596 | BA33: 0.14173423 | BB33: 0.15410877 | BC33: 0.20009745 | BD33: 0.18498815 | BE33: 0.16987324 | BF33: 0.1914379 | BG33: 0.19459392 | BH33: 0.17997972 | BI33: 0.1874745 | BJ33: 0.17418635 | BK33: 0.16704959 | BL33: 0.16353294 | BM33: 0.15314955 | BN33: 0.17975986 | BO33: 0.15560693 | BP33: 0.17138941 | BQ33: 0.16566737 | BR33: 0.18375632 | BS33: 0.16559512 | BT33: 0.17672779 | BV33: Dedicated Mobile Self-Scanning Devices | BW33: CMI_Trend_52 | BX33: CMI_Trend_46 | BY33: CMI_Trend_60 | BZ33: CMI_Trend_46 | CA33: CMI_Trend_20 | CB33: CMI_Trend_52 | CC33: CMI_Trend_52 | CD33: CMI_Trend_60 | CE33: CMI_Trend_60 | CF33: CMI_Trend_52 | CG33: CMI_Trend_20 | CH33: CMI_Trend_25 | CI33: CMI_Trend_52 | CJ33: CMI_Trend_60 | CK33: CMI_Trend_52 | CL33: CMI_Trend_60 | CM33: CMI_Trend_20 | CN33: CMI_Trend_25 | CO33: CMI_Trend_60 | CP33: CMI_Trend_56 | CQ33: CMI_Trend_52 | CR33: CMI_Trend_38 | CS33: CMI_Trend_60 | CT33: CMI_Trend_56 | CU33: CMI_Trend_20 | CV33: CMI_Trend_56 | CW33: CMI_Trend_20 | CX33: CMI_Trend_20 | CY33: CMI_Trend_60 | CZ33: CMI_Trend_60 | DA33: CMI_Trend_38 | DB33: CMI_Trend_46 | DC33: CMI_Trend_46 | DD33: CMI_Trend_52
B34: Smartphone-Based Self-Scanning | C34: 0.22930479 | D34: 0.21900479 | E34: 0.21340479 | F34: 0.23590479 | G34: 0.24160479 | H34: 0.21690479 | I34: 0.21620479 | J34: 0.22750479 | K34: 0.21530479 | L34: 0.24460479 | M34: 0.21530479 | N34: 0.22460479 | O34: 0.21560479 | P34: 0.24620479 | Q34: 0.22060479 | R34: 0.23120479 | S34: 0.22350479 | T34: 0.22690479 | U34: 0.22780479 | V34: 0.24580479 | W34: 0.22000479 | X34: 0.24360479 | Y34: 0.22270479 | Z34: 0.21430479 | AA34: 0.21510479 | AB34: 0.23330479 | AC34: 0.23440479 | AD34: 0.24290479 | AE34: 0.22660479 | AF34: 0.22430479 | AG34: 0.24210479 | AH34: 0.23160479 | AI34: 0.21510479 | AJ34: 0.22310479 | AL34: Smartphone-Based Self-Scanning | AM34: 0.179642 | AN34: 0.17206888 | AO34: 0.21201585 | AP34: 0.22127135 | AQ34: 0.1538267 | AR34: 0.20587084 | AS34: 0.17298626 | AT34: 0.13328558 | AU34: 0.19920798 | AV34: 0.19360423 | AW34: 0.1862241 | AX34: 0.16031187 | AY34: 0.1479336 | AZ34: 0.14073965 | BA34: 0.16591427 | BB34: 0.17828881 | BC34: 0.22427749 | BD34: 0.20916819 | BE34: 0.19405328 | BF34: 0.21561795 | BG34: 0.21877396 | BH34: 0.20415976 | BI34: 0.21165455 | BJ34: 0.19836639 | BK34: 0.19122963 | BL34: 0.18771298 | BM34: 0.17732959 | BN34: 0.2039399 | BO34: 0.17978697 | BP34: 0.19556945 | BQ34: 0.18984741 | BR34: 0.20793636 | BS34: 0.18977516 | BT34: 0.20090783 | BV34: Smartphone-Based Self-Scanning | BW34: CMI_Trend_56 | BX34: CMI_Trend_52 | BY34: CMI_Trend_20 | BZ34: CMI_Trend_20 | CA34: CMI_Trend_52 | CB34: CMI_Trend_52 | CC34: CMI_Trend_56 | CD34: CMI_Trend_60 | CE34: CMI_Trend_56 | CF34: CMI_Trend_56 | CG34: CMI_Trend_38 | CH34: CMI_Trend_38 | CI34: CMI_Trend_60 | CJ34: CMI_Trend_60 | CK34: CMI_Trend_20 | CL34: CMI_Trend_56 | CM34: CMI_Trend_20 | CN34: CMI_Trend_25 | CO34: CMI_Trend_60 | CP34: CMI_Trend_60 | CQ34: CMI_Trend_46 | CR34: CMI_Trend_52 | CS34: CMI_Trend_38 | CT34: CMI_Trend_38 | CU34: CMI_Trend_52 | CV34: CMI_Trend_25 | CW34: CMI_Trend_60 | CX34: CMI_Trend_38 | CY34: CMI_Trend_46 | CZ34: CMI_Trend_52 | DA34: CMI_Trend_46 | DB34: CMI_Trend_56 | DC34: CMI_Trend_56 | DD34: CMI_Trend_60
B35: Smart-Cart-Based Self-Scanning | C35: =1-SUM(C33:C34) -> 0.2652342 | D35: =1-SUM(D33:D34) -> 0.2712342 | E35: =1-SUM(E33:E34) -> 0.2838342 | F35: =1-SUM(F33:F34) -> 0.2438342 | G35: =1-SUM(G33:G34) -> 0.2612342 | H35: =1-SUM(H33:H34) -> 0.2676342 | I35: =1-SUM(I33:I34) -> 0.2779342 | J35: =1-SUM(J33:J34) -> 0.2696342 | ... AJ35: =1-SUM(AJ33:AJ34) -> 0.2591342 | AL35: Smart-Cart-Based Self-Scanning | AM35: 0.1970449 | AN35: 0.18947179 | AO35: 0.22941875 | AP35: 0.23867426 | AQ35: 0.17122961 | AR35: 0.22327375 | AS35: 0.19038916 | AT35: 0.15068849 | AU35: 0.21661089 | AV35: 0.21100714 | AW35: 0.203627 | AX35: 0.17771478 | AY35: 0.1653365 | AZ35: 0.15814255 | BA35: 0.18331718 | BB35: 0.19569172 | BC35: 0.2416804 | BD35: 0.2265711 | BE35: 0.21145618 | BF35: 0.23302085 | BG35: 0.23617687 | BH35: 0.22156267 | BI35: 0.22905745 | BJ35: 0.2157693 | BK35: 0.20863254 | BL35: 0.20511589 | BM35: 0.1947325 | BN35: 0.22134281 | BO35: 0.19718988 | BP35: 0.21297236 | BQ35: 0.20725032 | BR35: 0.22533926 | BS35: 0.20717807 | BT35: 0.21831074 | BV35: Smart-Cart-Based Self-Scanning | BW35: CMI_Trend_38 | BX35: CMI_Trend_52 | BY35: CMI_Trend_46 | BZ35: CMI_Trend_20 | CA35: CMI_Trend_46 | CB35: CMI_Trend_60 | CC35: CMI_Trend_52 | CD35: CMI_Trend_20 | CE35: CMI_Trend_52 | CF35: CMI_Trend_25 | CG35: CMI_Trend_46 | CH35: CMI_Trend_52 | CI35: CMI_Trend_56 | CJ35: CMI_Trend_52 | CK35: CMI_Trend_20 | CL35: CMI_Trend_52 | CM35: CMI_Trend_38 | CN35: CMI_Trend_60 | CO35: CMI_Trend_46 | CP35: CMI_Trend_20 | CQ35: CMI_Trend_56 | CR35: CMI_Trend_20 | CS35: CMI_Trend_52 | CT35: CMI_Trend_56 | CU35: CMI_Trend_56 | CV35: CMI_Trend_56 | CW35: CMI_Trend_52 | CX35: CMI_Trend_20 | CY35: CMI_Trend_20 | CZ35: CMI_Trend_60 | DA35: CMI_Trend_60 | DB35: CMI_Trend_38 | DC35: CMI_Trend_60 | DD35: CMI_Trend_52
B37: By Model Type | AL37: By Model Type | BV37: By Model Type
B38: Cash Model | C38: 0.30125496 | D38: 0.31665496 | E38: 0.28595496 | F38: 0.28515496 | G38: 0.31445496 | H38: 0.31085496 | I38: 0.30145496 | J38: 0.28605496 | K38: 0.30855496 | L38: 0.28555496 | M38: 0.30405496 | N38: 0.31715496 | O38: 0.28585496 | P38: 0.29935496 | Q38: 0.31715496 | R38: 0.30575496 | S38: 0.31035496 | T38: 0.28815496 | U38: 0.30655496 | V38: 0.31785496 | W38: 0.30165496 | X38: 0.29935496 | Y38: 0.28845496 | Z38: 0.29845496 | AA38: 0.28495496 | AB38: 0.30955496 | AC38: 0.29235496 | AD38: 0.28715496 | AE38: 0.29045496 | AF38: 0.29465496 | AG38: 0.30285496 | AH38: 0.31445496 | AI38: 0.29015496 | AJ38: 0.30615496 | AL38: Cash Model | AM38: 0.10438052 | AN38: 0.096542626 | AO38: 0.13627129 | AP38: 0.1448278 | AQ38: 0.079870807 | AR38: 0.13015191 | AS38: 0.09765031 | AT38: 0.058507976 | AU38: 0.12365375 | AV38: 0.11692986 | AW38: 0.11045098 | AX38: 0.085876391 | AY38: 0.072078985 | AZ38: 0.065985514 | BA38: 0.09130349 | BB38: 0.10393865 | BC38: 0.14908841 | BD38: 0.13359853 | BE38: 0.11990423 | BF38: 0.14060941 | BG38: 0.142896 | BH38: 0.12989973 | BI38: 0.13673897 | BJ38: 0.12307104 | BK38: 0.11486949 | BL38: 0.11190669 | BM38: 0.10262762 | BN38: 0.12853379 | BO38: 0.10447867 | BP38: 0.12053637 | BQ38: 0.11374957 | BR38: 0.13364475 | BS38: 0.11419185 | BT38: 0.12506262 | BV38: Cash Model | BW38: CMI_Trend_25 | BX38: CMI_Trend_52 | BY38: CMI_Trend_46 | BZ38: CMI_Trend_25 | CA38: CMI_Trend_56 | CB38: CMI_Trend_46 | CC38: CMI_Trend_20 | CD38: CMI_Trend_38 | CE38: CMI_Trend_38 | CF38: CMI_Trend_52 | CG38: CMI_Trend_38 | CH38: CMI_Trend_52 | CI38: CMI_Trend_38 | CJ38: CMI_Trend_20 | CK38: CMI_Trend_52 | CL38: CMI_Trend_60 | CM38: CMI_Trend_52 | CN38: CMI_Trend_56 | CO38: CMI_Trend_20 | CP38: CMI_Trend_46 | CQ38: CMI_Trend_46 | CR38: CMI_Trend_60 | CS38: CMI_Trend_38 | CT38: CMI_Trend_46 | CU38: CMI_Trend_52 | CV38: CMI_Trend_38 | CW38: CMI_Trend_20 | CX38: CMI_Trend_60 | CY38: CMI_Trend_25 | CZ38: CMI_Trend_20 | DA38: CMI_Trend_38 | DB38: CMI_Trend_56 | DC38: CMI_Trend_52 | DD38: CMI_Trend_46
B39: Cashless Model | C39: =1-C38 -> 0.69874504 | D39: =1-D38 -> 0.68334504 | E39: =1-E38 -> 0.71404504 | F39: =1-F38 -> 0.71484504 | G39: =1-G38 -> 0.68554504 | H39: =1-H38 -> 0.68914504 | I39: =1-I38 -> 0.69854504 | J39: =1-J38 -> 0.71394504 | ... AJ39: =1-AJ38 -> 0.69384504 | AL39: Cashless Model | AM39: 0.13038052 | AN39: 0.12254263 | AO39: 0.16227129 | AP39: 0.1708278 | AQ39: 0.10587081 | AR39: 0.15615191 | AS39: 0.12365031 | AT39: 0.084507976 | AU39: 0.14965375 | AV39: 0.14292986 | AW39: 0.13645098 | AX39: 0.11187639 | AY39: 0.098078985 | AZ39: 0.091985514 | BA39: 0.11730349 | BB39: 0.12993865 | BC39: 0.17508841 | BD39: 0.15959853 | BE39: 0.14590423 | BF39: 0.16660941 | BG39: 0.168896 | BH39: 0.15589973 | BI39: 0.16273897 | BJ39: 0.14907104 | BK39: 0.14086949 | BL39: 0.13790669 | BM39: 0.12862762 | BN39: 0.15453379 | BO39: 0.13047867 | BP39: 0.14653637 | BQ39: 0.13974957 | BR39: 0.15964475 | BS39: 0.14019185 | BT39: 0.15106262 | BV39: Cashless Model | BW39: CMI_Trend_60 | BX39: CMI_Trend_25 | BY39: CMI_Trend_60 | BZ39: CMI_Trend_46 | CA39: CMI_Trend_52 | CB39: CMI_Trend_20 | CC39: CMI_Trend_38 | CD39: CMI_Trend_20 | CE39: CMI_Trend_56 | CF39: CMI_Trend_52 | CG39: CMI_Trend_38 | CH39: CMI_Trend_56 | CI39: CMI_Trend_38 | CJ39: CMI_Trend_52 | CK39: CMI_Trend_25 | CL39: CMI_Trend_46 | CM39: CMI_Trend_56 | CN39: CMI_Trend_38 | CO39: CMI_Trend_56 | CP39: CMI_Trend_56 | CQ39: CMI_Trend_52 | CR39: CMI_Trend_38 | CS39: CMI_Trend_38 | CT39: CMI_Trend_20 | CU39: CMI_Trend_56 | CV39: CMI_Trend_38 | CW39: CMI_Trend_25 | CX39: CMI_Trend_20 | CY39: CMI_Trend_52 | CZ39: CMI_Trend_52 | DA39: CMI_Trend_60 | DB39: CMI_Trend_56 | DC39: CMI_Trend_56 | DD39: CMI_Trend_20
B41: By Technology | AL41: By Technology | BV41: By Technology
B42: Barcode Scanning (1D/2D) | C42: =1-SUM(C43:C44) -> 0.85110498 | D42: =1-SUM(D43:D44) -> 0.85130498 | E42: =1-SUM(E43:E44) -> 0.86910498 | F42: =1-SUM(F43:F44) -> 0.85120498 | G42: =1-SUM(G43:G44) -> 0.85190498 | H42: =1-SUM(H43:H44) -> 0.85470498 | I42: =1-SUM(I43:I44) -> 0.85260498 | J42: =1-SUM(J43:J44) -> 0.82760498 | ... AJ42: =1-SUM(AJ43:AJ44) -> 0.85340498 | AL42: Barcode Scanning (1D/2D) | AM42: 0.11471423 | AN42: 0.10631734 | AO42: 0.14787641 | AP42: 0.15588301 | AQ42: 0.089544123 | AR42: 0.14015802 | AS42: 0.10799313 | AT42: 0.068057792 | AU42: 0.13337776 | AV42: 0.12738058 | AW42: 0.1214646 | AX42: 0.095838307 | AY42: 0.0822333 | AZ42: 0.075792729 | BA42: 0.1001812 | BB42: 0.11439717 | BC42: 0.15825083 | BD42: 0.14430275 | BE42: 0.13108555 | BF42: 0.15029572 | BG42: 0.15326611 | BH42: 0.14115125 | BI42: 0.14631088 | BJ42: 0.13316426 | BK42: 0.1252656 | BL42: 0.1209885 | BM42: 0.11268833 | BN42: 0.1394707 | BO42: 0.11618779 | BP42: 0.13139788 | BQ42: 0.12287688 | BR42: 0.14268107 | BS42: 0.12381576 | BT42: 0.13514283 | BV42: Barcode Scanning (1D/2D) | BW42: CMI_Trend_52 | BX42: CMI_Trend_25 | BY42: CMI_Trend_20 | BZ42: CMI_Trend_38 | CA42: CMI_Trend_52 | CB42: CMI_Trend_56 | CC42: CMI_Trend_46 | CD42: CMI_Trend_20 | CE42: CMI_Trend_56 | CF42: CMI_Trend_20 | CG42: CMI_Trend_46 | CH42: CMI_Trend_20 | CI42: CMI_Trend_25 | CJ42: CMI_Trend_20 | CK42: CMI_Trend_25 | CL42: CMI_Trend_46 | CM42: CMI_Trend_20 | CN42: CMI_Trend_52 | CO42: CMI_Trend_20 | CP42: CMI_Trend_52 | CQ42: CMI_Trend_52 | CR42: CMI_Trend_46 | CS42: CMI_Trend_46 | CT42: CMI_Trend_46 | CU42: CMI_Trend_38 | CV42: CMI_Trend_52 | CW42: CMI_Trend_60 | CX42: CMI_Trend_52 | CY42: CMI_Trend_25 | CZ42: CMI_Trend_20 | DA42: CMI_Trend_20 | DB42: CMI_Trend_52 | DC42: CMI_Trend_60 | DD42: CMI_Trend_20
A43: 0.001 | B43: RFID-Based Scanning | C43: 0.035471548 | D43: 0.032171548 | E43: 0.029771548 | F43: 0.041171548 | G43: 0.028371548 | H43: 0.029471548 | I43: 0.033871548 | J43: 0.042171548 | K43: 0.035271548 | L43: 0.029371548 | M43: 0.035071548 | N43: 0.030771548 | O43: 0.035071548 | P43: 0.029271548 | Q43: 0.038671548 | R43: 0.036871548 | S43: 0.041371548 | T43: 0.033671548 | U43: 0.030671548 | V43: 0.039571548 | W43: 0.030871548 | X43: 0.035671548 | Y43: 0.038171548 | Z43: 0.042571548 | AA43: 0.032771548 | AB43: 0.029171548 | AC43: 0.040271548 | AD43: 0.031271548 | AE43: 0.028771548 | AF43: 0.037071548 | AG43: 0.042071548 | AH43: 0.040871548 | AI43: 0.033771548 | AJ43: 0.030171548 | AL43: RFID-Based Scanning | AM43: 0.12771423 | AN43: 0.11931734 | AO43: 0.16087641 | AP43: 0.16888301 | AQ43: 0.10254412 | AR43: 0.15315802 | AS43: 0.12099313 | AT43: 0.081057792 | AU43: 0.14637776 | AV43: 0.14038058 | AW43: 0.1344646 | AX43: 0.10883831 | AY43: 0.0952333 | AZ43: 0.088792729 | BA43: 0.1131812 | BB43: 0.12739717 | BC43: 0.17125083 | BD43: 0.15730275 | BE43: 0.14408555 | BF43: 0.16329572 | BG43: 0.16626611 | BH43: 0.15415125 | BI43: 0.15931088 | BJ43: 0.14616426 | BK43: 0.1382656 | BL43: 0.1339885 | BM43: 0.12568833 | BN43: 0.1524707 | BO43: 0.12918779 | BP43: 0.14439788 | BQ43: 0.13587688 | BR43: 0.15568107 | BS43: 0.13681576 | BT43: 0.14814283 | BV43: RFID-Based Scanning | BW43: CMI_Trend_52 | BX43: CMI_Trend_25 | BY43: CMI_Trend_20 | BZ43: CMI_Trend_56 | CA43: CMI_Trend_38 | CB43: CMI_Trend_46 | CC43: CMI_Trend_25 | CD43: CMI_Trend_38 | CE43: CMI_Trend_56 | CF43: CMI_Trend_20 | CG43: CMI_Trend_25 | CH43: CMI_Trend_38 | CI43: CMI_Trend_38 | CJ43: CMI_Trend_46 | CK43: CMI_Trend_38 | CL43: CMI_Trend_46 | CM43: CMI_Trend_20 | CN43: CMI_Trend_20 | CO43: CMI_Trend_20 | CP43: CMI_Trend_38 | CQ43: CMI_Trend_46 | CR43: CMI_Trend_20 | CS43: CMI_Trend_52 | CT43: CMI_Trend_60 | CU43: CMI_Trend_60 | CV43: CMI_Trend_46 | CW43: CMI_Trend_46 | CX43: CMI_Trend_38 | CY43: CMI_Trend_60 | CZ43: CMI_Trend_56 | DA43: CMI_Trend_52 | DB43: CMI_Trend_52 | DC43: CMI_Trend_20 | DD43: CMI_Trend_20
B44: Computer Vision and AI Scanning | C44: 0.11342347 | D44: 0.11652347 | E44: 0.10112347 | F44: 0.10762347 | G44: 0.11972347 | H44: 0.11582347 | I44: 0.11352347 | J44: 0.13022347 | K44: 0.11992347 | L44: 0.11912347 | M44: 0.10192347 | N44: 0.11372347 | O44: 0.12242347 | P44: 0.12352347 | Q44: 0.12882347 | R44: 0.10942347 | S44: 0.12662347 | T44: 0.11332347 | U44: 0.099223468 | V44: 0.11592347 | W44: 0.11362347 | X44: 0.10002347 | Y44: 0.12972347 | Z44: 0.11682347 | AA44: 0.11952347 | AB44: 0.13062347 | AC44: 0.12022347 | AD44: 0.11062347 | AE44: 0.097923468 | AF44: 0.10762347 | AG44: 0.13002347 | AH44: 0.12702347 | AI44: 0.12912347 | AJ44: 0.11642347 | AL44: Computer Vision and AI Scanning | AM44: 0.17971423 | AN44: 0.17131734 | AO44: 0.21287641 | AP44: 0.22088301 | AQ44: 0.15454412 | AR44: 0.20515802 | AS44: 0.17299313 | AT44: 0.13305779 | AU44: 0.19837776 | AV44: 0.19238058 | AW44: 0.1864646 | AX44: 0.16083831 | AY44: 0.1472333 | AZ44: 0.14079273 | BA44: 0.1651812 | BB44: 0.17939717 | BC44: 0.22325083 | BD44: 0.20930275 | BE44: 0.19608555 | BF44: 0.21529572 | BG44: 0.21826611 | BH44: 0.20615125 | BI44: 0.21131088 | BJ44: 0.19816426 | BK44: 0.1902656 | BL44: 0.1859885 | BM44: 0.17768833 | BN44: 0.2044707 | BO44: 0.18118779 | BP44: 0.19639788 | BQ44: 0.18787688 | BR44: 0.20768107 | BS44: 0.18881576 | BT44: 0.20014283 | BV44: Computer Vision and AI Scanning | BW44: CMI_Trend_20 | BX44: CMI_Trend_46 | BY44: CMI_Trend_52 | BZ44: CMI_Trend_25 | CA44: CMI_Trend_60 | CB44: CMI_Trend_46 | CC44: CMI_Trend_60 | CD44: CMI_Trend_56 | CE44: CMI_Trend_25 | CF44: CMI_Trend_38 | CG44: CMI_Trend_38 | CH44: CMI_Trend_38 | CI44: CMI_Trend_56 | CJ44: CMI_Trend_25 | CK44: CMI_Trend_60 | CL44: CMI_Trend_25 | CM44: CMI_Trend_46 | CN44: CMI_Trend_60 | CO44: CMI_Trend_60 | CP44: CMI_Trend_60 | CQ44: CMI_Trend_46 | CR44: CMI_Trend_52 | CS44: CMI_Trend_20 | CT44: CMI_Trend_52 | CU44: CMI_Trend_56 | CV44: CMI_Trend_52 | CW44: CMI_Trend_56 | CX44: CMI_Trend_56 | CY44: CMI_Trend_46 | CZ44: CMI_Trend_38 | DA44: CMI_Trend_52 | DB44: CMI_Trend_60 | DC44: CMI_Trend_52 | DD44: CMI_Trend_46
B46: By Retail Format | AL46: By Retail Format | BV46: By Retail Format
B47: Supermarkets & Hypermarkets | C47: =1-SUM(C48:C52) -> 0.54723569 | D47: =1-SUM(D48:D52) -> 0.53313569 | E47: =1-SUM(E48:E52) -> 0.52293569 | F47: =1-SUM(F48:F52) -> 0.52803569 | G47: =1-SUM(G48:G52) -> 0.53563569 | H47: =1-SUM(H48:H52) -> 0.53673569 | I47: =1-SUM(I48:I52) -> 0.52493569 | J47: =1-SUM(J48:J52) -> 0.55673569 | ... AJ47: =1-SUM(AJ48:AJ52) -> 0.53253569 | AL47: Supermarkets & Hypermarkets | AM47: 0.12173181 | AN47: 0.11341404 | AO47: 0.15382301 | AP47: 0.16285473 | AQ47: 0.09730473 | AR47: 0.14786098 | AS47: 0.11506409 | AT47: 0.07564497 | AU47: 0.14079486 | AV47: 0.13478265 | AW47: 0.12790964 | AX47: 0.10258283 | AY47: 0.090084499 | AZ47: 0.083349892 | BA47: 0.10812083 | BB47: 0.12118025 | BC47: 0.16602427 | BD47: 0.15151779 | BE47: 0.13678492 | BF47: 0.15741823 | BG47: 0.16006077 | BH47: 0.14754762 | BI47: 0.15450841 | BJ47: 0.14076684 | BK47: 0.13279274 | BL47: 0.12916947 | BM47: 0.12041667 | BN47: 0.14595593 | BO47: 0.12247556 | BP47: 0.13827121 | BQ47: 0.13121419 | BR47: 0.15080974 | BS47: 0.13192253 | BT47: 0.14218902 | BV47: Supermarkets & Hypermarkets | BW47: CMI_Trend_56 | BX47: CMI_Trend_25 | BY47: CMI_Trend_38 | BZ47: CMI_Trend_38 | CA47: CMI_Trend_52 | CB47: CMI_Trend_60 | CC47: CMI_Trend_20 | CD47: CMI_Trend_52 | CE47: CMI_Trend_25 | CF47: CMI_Trend_46 | CG47: CMI_Trend_38 | CH47: CMI_Trend_20 | CI47: CMI_Trend_46 | CJ47: CMI_Trend_20 | CK47: CMI_Trend_25 | CL47: CMI_Trend_38 | CM47: CMI_Trend_46 | CN47: CMI_Trend_52 | CO47: CMI_Trend_25 | CP47: CMI_Trend_25 | CQ47: CMI_Trend_56 | CR47: CMI_Trend_25 | CS47: CMI_Trend_38 | CT47: CMI_Trend_56 | CU47: CMI_Trend_52 | CV47: CMI_Trend_56 | CW47: CMI_Trend_60 | CX47: CMI_Trend_46 | CY47: CMI_Trend_60 | CZ47: CMI_Trend_46 | DA47: CMI_Trend_38 | DB47: CMI_Trend_25 | DC47: CMI_Trend_38 | DD47: CMI_Trend_52
B48: Convenience Stores | C48: 0.1414 | D48: 0.1265 | E48: 0.1511 | F48: 0.1289 | G48: 0.1423 | H48: 0.1351 | I48: 0.1427 | J48: 0.1418 | K48: 0.1443 | L48: 0.1518 | M48: 0.1381 | N48: 0.138 | O48: 0.1434 | P48: 0.1322 | Q48: 0.1537 | R48: 0.1413 | S48: 0.1429 | T48: 0.1426 | U48: 0.1522 | V48: 0.1378 | W48: 0.1518 | X48: 0.1461 | Y48: 0.1334 | Z48: 0.1329 | AA48: 0.1345 | AB48: 0.1335 | AC48: 0.1318 | AD48: 0.1256 | AE48: 0.1386 | AF48: 0.146 | AG48: 0.1389 | AH48: 0.136 | AI48: 0.1515 | AJ48: 0.1532 | AL48: Convenience Stores | AM48: 0.13060437 | AN48: 0.1222866 | AO48: 0.16269557 | AP48: 0.17172729 | AQ48: 0.10617729 | AR48: 0.15673354 | AS48: 0.12393665 | AT48: 0.08451753 | AU48: 0.14966742 | AV48: 0.14365521 | AW48: 0.1367822 | AX48: 0.11145539 | AY48: 0.098957058 | AZ48: 0.092222451 | BA48: 0.11699339 | BB48: 0.13005281 | BC48: 0.17489683 | BD48: 0.16039035 | BE48: 0.14565748 | BF48: 0.16629079 | BG48: 0.16893333 | BH48: 0.15642018 | BI48: 0.16338097 | BJ48: 0.1496394 | BK48: 0.1416653 | BL48: 0.13804203 | BM48: 0.12928923 | BN48: 0.15482849 | BO48: 0.13134812 | BP48: 0.14714377 | BQ48: 0.14008675 | BR48: 0.1596823 | BS48: 0.14079509 | BT48: 0.15106158 | BV48: Convenience Stores | BW48: CMI_Trend_38 | BX48: CMI_Trend_38 | BY48: CMI_Trend_20 | BZ48: CMI_Trend_38 | CA48: CMI_Trend_52 | CB48: CMI_Trend_38 | CC48: CMI_Trend_52 | CD48: CMI_Trend_25 | CE48: CMI_Trend_20 | CF48: CMI_Trend_25 | CG48: CMI_Trend_56 | CH48: CMI_Trend_20 | CI48: CMI_Trend_46 | CJ48: CMI_Trend_25 | CK48: CMI_Trend_52 | CL48: CMI_Trend_25 | CM48: CMI_Trend_52 | CN48: CMI_Trend_56 | CO48: CMI_Trend_56 | CP48: CMI_Trend_38 | CQ48: CMI_Trend_20 | CR48: CMI_Trend_52 | CS48: CMI_Trend_56 | CT48: CMI_Trend_25 | CU48: CMI_Trend_52 | CV48: CMI_Trend_60 | CW48: CMI_Trend_38 | CX48: CMI_Trend_52 | CY48: CMI_Trend_25 | CZ48: CMI_Trend_56 | DA48: CMI_Trend_46 | DB48: CMI_Trend_20 | DC48: CMI_Trend_56 | DD48: CMI_Trend_20
B49: Specialty and Discount Stores | C49: 0.099009901 | D49: 0.1057099 | E49: 0.093609901 | F49: 0.1051099 | G49: 0.1133099 | H49: 0.098809901 | I49: 0.097109901 | J49: 0.085409901 | K49: 0.098609901 | L49: 0.099009901 | M49: 0.088009901 | N49: 0.095309901 | O49: 0.1027099 | P49: 0.087109901 | Q49: 0.1051099 | R49: 0.1043099 | S49: 0.097009901 | T49: 0.093809901 | U49: 0.099209901 | V49: 0.085209901 | W49: 0.086309901 | X49: 0.088509901 | Y49: 0.097809901 | Z49: 0.1144099 | AA49: 0.086909901 | AB49: 0.098809901 | AC49: 0.1069099 | AD49: 0.092009901 | AE49: 0.1129099 | AF49: 0.097409901 | AG49: 0.092009901 | AH49: 0.1021099 | AI49: 0.1084099 | AJ49: 0.1142099 | AL49: Specialty and Discount Stores | AM49: 0.1143353 | AN49: 0.10601753 | AO49: 0.1464265 | AP49: 0.15545823 | AQ49: 0.089908226 | AR49: 0.14046447 | AS49: 0.10766759 | AT49: 0.068248466 | AU49: 0.13339836 | AV49: 0.12738615 | AW49: 0.12051313 | AX49: 0.095186328 | AY49: 0.082687995 | AZ49: 0.075953388 | BA49: 0.10072432 | BB49: 0.11378374 | BC49: 0.15862777 | BD49: 0.14412128 | BE49: 0.12938841 | BF49: 0.15002173 | BG49: 0.15266427 | BH49: 0.14015111 | BI49: 0.1471119 | BJ49: 0.13337034 | BK49: 0.12539624 | BL49: 0.12177297 | BM49: 0.11302017 | BN49: 0.13855943 | BO49: 0.11507906 | BP49: 0.1308747 | BQ49: 0.12381768 | BR49: 0.14341324 | BS49: 0.12452603 | BT49: 0.13479252 | BV49: Specialty and Discount Stores | BW49: CMI_Trend_46 | BX49: CMI_Trend_60 | BY49: CMI_Trend_60 | BZ49: CMI_Trend_25 | CA49: CMI_Trend_46 | CB49: CMI_Trend_20 | CC49: CMI_Trend_38 | CD49: CMI_Trend_20 | CE49: CMI_Trend_20 | CF49: CMI_Trend_46 | CG49: CMI_Trend_20 | CH49: CMI_Trend_25 | CI49: CMI_Trend_20 | CJ49: CMI_Trend_46 | CK49: CMI_Trend_46 | CL49: CMI_Trend_56 | CM49: CMI_Trend_52 | CN49: CMI_Trend_60 | CO49: CMI_Trend_46 | CP49: CMI_Trend_38 | CQ49: CMI_Trend_52 | CR49: CMI_Trend_20 | CS49: CMI_Trend_52 | CT49: CMI_Trend_20 | CU49: CMI_Trend_38 | CV49: CMI_Trend_60 | CW49: CMI_Trend_25 | CX49: CMI_Trend_38 | CY49: CMI_Trend_60 | CZ49: CMI_Trend_60 | DA49: CMI_Trend_38 | DB49: CMI_Trend_52 | DC49: CMI_Trend_46 | DD49: CMI_Trend_60
B50: Department Stores | C50: 0.056341252 | D50: 0.047641252 | E50: 0.068041252 | F50: 0.072541252 | G50: 0.069941252 | H50: 0.066941252 | I50: 0.067741252 | J50: 0.042541252 | K50: 0.068741252 | L50: 0.053141252 | M50: 0.069241252 | N50: 0.062141252 | O50: 0.051941252 | P50: 0.054141252 | Q50: 0.040941252 | R50: 0.046941252 | S50: 0.050141252 | T50: 0.053841252 | U50: 0.046741252 | V50: 0.056841252 | W50: 0.062041252 | X50: 0.056441252 | Y50: 0.050341252 | Z50: 0.061041252 | AA50: 0.061841252 | AB50: 0.059741252 | AC50: 0.054441252 | AD50: 0.053741252 | AE50: 0.060541252 | AF50: 0.064841252 | AG50: 0.069741252 | AH50: 0.054741252 | AI50: 0.070641252 | AJ50: 0.058041252 | AL50: Department Stores | AM50: 0.10391152 | AN50: 0.095593754 | AO50: 0.13600272 | AP50: 0.14503445 | AQ50: 0.079484448 | AR50: 0.1300407 | AS50: 0.097243808 | AT50: 0.057824688 | AU50: 0.12297458 | AV50: 0.11696237 | AW50: 0.11008935 | AX50: 0.084762549 | AY50: 0.072264216 | AZ50: 0.065529609 | BA50: 0.090300546 | BB50: 0.10335997 | BC50: 0.14820399 | BD50: 0.13369751 | BE50: 0.11896463 | BF50: 0.13959795 | BG50: 0.14224049 | BH50: 0.12972733 | BI50: 0.13668813 | BJ50: 0.12294656 | BK50: 0.11497246 | BL50: 0.11134919 | BM50: 0.10259639 | BN50: 0.12813565 | BO50: 0.10465528 | BP50: 0.12045092 | BQ50: 0.1133939 | BR50: 0.13298946 | BS50: 0.11410225 | BT50: 0.12436874 | BV50: Department Stores | BW50: CMI_Trend_20 | BX50: CMI_Trend_20 | BY50: CMI_Trend_38 | BZ50: CMI_Trend_60 | CA50: CMI_Trend_25 | CB50: CMI_Trend_56 | CC50: CMI_Trend_20 | CD50: CMI_Trend_25 | CE50: CMI_Trend_56 | CF50: CMI_Trend_38 | CG50: CMI_Trend_60 | CH50: CMI_Trend_46 | CI50: CMI_Trend_60 | CJ50: CMI_Trend_52 | CK50: CMI_Trend_20 | CL50: CMI_Trend_60 | CM50: CMI_Trend_52 | CN50: CMI_Trend_52 | CO50: CMI_Trend_60 | CP50: CMI_Trend_38 | CQ50: CMI_Trend_60 | CR50: CMI_Trend_25 | CS50: CMI_Trend_38 | CT50: CMI_Trend_56 | CU50: CMI_Trend_56 | CV50: CMI_Trend_60 | CW50: CMI_Trend_56 | CX50: CMI_Trend_46 | CY50: CMI_Trend_20 | CZ50: CMI_Trend_60 | DA50: CMI_Trend_46 | DB50: CMI_Trend_46 | DC50: CMI_Trend_56 | DD50: CMI_Trend_38
B51: Warehouse Clubs | C51: 0.10891089 | D51: 0.12551089 | E51: 0.12171089 | F51: 0.11911089 | G51: 0.098810891 | H51: 0.099510891 | I51: 0.11741089 | J51: 0.12491089 | K51: 0.10961089 | L51: 0.096210891 | M51: 0.10491089 | N51: 0.11781089 | O51: 0.094310891 | P51: 0.10721089 | Q51: 0.10091089 | R51: 0.10321089 | S51: 0.10991089 | T51: 0.10191089 | U51: 0.11701089 | V51: 0.10141089 | W51: 0.12481089 | X51: 0.093710891 | Y51: 0.10041089 | Z51: 0.10651089 | AA51: 0.10331089 | AB51: 0.10501089 | AC51: 0.10591089 | AD51: 0.11651089 | AE51: 0.10651089 | AF51: 0.11371089 | AG51: 0.11961089 | AH51: 0.10291089 | AI51: 0.10661089 | AJ51: 0.10751089 | AL51: Warehouse Clubs | AM51: 0.13913581 | AN51: 0.13081804 | AO51: 0.17122701 | AP51: 0.18025874 | AQ51: 0.11470874 | AR51: 0.16526499 | AS51: 0.1324681 | AT51: 0.093048977 | AU51: 0.15819887 | AV51: 0.15218666 | AW51: 0.14531364 | AX51: 0.11998684 | AY51: 0.10748851 | AZ51: 0.1007539 | BA51: 0.12552484 | BB51: 0.13858426 | BC51: 0.18342828 | BD51: 0.1689218 | BE51: 0.15418892 | BF51: 0.17482224 | BG51: 0.17746478 | BH51: 0.16495162 | BI51: 0.17191242 | BJ51: 0.15817085 | BK51: 0.15019675 | BL51: 0.14657348 | BM51: 0.13782068 | BN51: 0.16335994 | BO51: 0.13987957 | BP51: 0.15567521 | BQ51: 0.14861819 | BR51: 0.16821375 | BS51: 0.14932654 | BT51: 0.15959303 | BV51: Warehouse Clubs | BW51: CMI_Trend_46 | BX51: CMI_Trend_60 | BY51: CMI_Trend_25 | BZ51: CMI_Trend_38 | CA51: CMI_Trend_56 | CB51: CMI_Trend_25 | CC51: CMI_Trend_20 | CD51: CMI_Trend_25 | CE51: CMI_Trend_46 | CF51: CMI_Trend_46 | CG51: CMI_Trend_56 | CH51: CMI_Trend_25 | CI51: CMI_Trend_20 | CJ51: CMI_Trend_38 | CK51: CMI_Trend_46 | CL51: CMI_Trend_52 | CM51: CMI_Trend_25 | CN51: CMI_Trend_25 | CO51: CMI_Trend_56 | CP51: CMI_Trend_52 | CQ51: CMI_Trend_25 | CR51: CMI_Trend_38 | CS51: CMI_Trend_52 | CT51: CMI_Trend_52 | CU51: CMI_Trend_60 | CV51: CMI_Trend_25 | CW51: CMI_Trend_20 | CX51: CMI_Trend_20 | CY51: CMI_Trend_60 | CZ51: CMI_Trend_60 | DA51: CMI_Trend_20 | DB51: CMI_Trend_56 | DC51: CMI_Trend_25 | DD51: CMI_Trend_25
B52: Pharmacies & Drugstores | C52: 0.047102262 | D52: 0.061502262 | E52: 0.042602262 | F52: 0.046302262 | G52: 0.040002262 | H52: 0.062902262 | I52: 0.050102262 | J52: 0.048602262 | K52: 0.031302262 | L52: 0.048802262 | M52: 0.041802262 | N52: 0.032702262 | O52: 0.052502262 | P52: 0.045502262 | Q52: 0.053302262 | R52: 0.049902262 | S52: 0.045302262 | T52: 0.062802262 | U52: 0.052902262 | V52: 0.032902262 | W52: 0.061702262 | X52: 0.055002262 | Y52: 0.045702262 | Z52: 0.043702262 | AA52: 0.045602262 | AB52: 0.041602262 | AC52: 0.050602262 | AD52: 0.030902262 | AE52: 0.056602262 | AF52: 0.062602262 | AG52: 0.057502262 | AH52: 0.047902262 | AI52: 0.032602262 | AJ52: 0.034502262 | AL52: Pharmacies & Drugstores | AM52: 0.10904371 | AN52: 0.10072594 | AO52: 0.14113491 | AP52: 0.15016664 | AQ52: 0.084616637 | AR52: 0.13517289 | AS52: 0.102376 | AT52: 0.062956877 | AU52: 0.12810677 | AV52: 0.12209456 | AW52: 0.11522154 | AX52: 0.089894738 | AY52: 0.077396406 | AZ52: 0.070661798 | BA52: 0.095432735 | BB52: 0.10849216 | BC52: 0.15333618 | BD52: 0.1388297 | BE52: 0.12409682 | BF52: 0.14473014 | BG52: 0.14737268 | BH52: 0.13485952 | BI52: 0.14182032 | BJ52: 0.12807875 | BK52: 0.12010465 | BL52: 0.11648138 | BM52: 0.10772858 | BN52: 0.13326784 | BO52: 0.10978747 | BP52: 0.12558311 | BQ52: 0.11852609 | BR52: 0.13812165 | BS52: 0.11923444 | BT52: 0.12950093 | BV52: Pharmacies & Drugstores | BW52: CMI_Trend_56 | BX52: CMI_Trend_52 | BY52: CMI_Trend_25 | BZ52: CMI_Trend_20 | CA52: CMI_Trend_46 | CB52: CMI_Trend_46 | CC52: CMI_Trend_25 | CD52: CMI_Trend_20 | CE52: CMI_Trend_20 | CF52: CMI_Trend_46 | CG52: CMI_Trend_52 | CH52: CMI_Trend_20 | CI52: CMI_Trend_20 | CJ52: CMI_Trend_46 | CK52: CMI_Trend_56 | CL52: CMI_Trend_52 | CM52: CMI_Trend_60 | CN52: CMI_Trend_56 | CO52: CMI_Trend_20 | CP52: CMI_Trend_60 | CQ52: CMI_Trend_25 | CR52: CMI_Trend_56 | CS52: CMI_Trend_46 | CT52: CMI_Trend_52 | CU52: CMI_Trend_38 | CV52: CMI_Trend_25 | CW52: CMI_Trend_56 | CX52: CMI_Trend_60 | CY52: CMI_Trend_20 | CZ52: CMI_Trend_20 | DA52: CMI_Trend_52 | DB52: CMI_Trend_56 | DC52: CMI_Trend_60 | DD52: CMI_Trend_46
B54: Cross - By Product Type By Technology | AL54: Cross - By Product Type By Technology | AM54: =AM55*C55+AM62*C62 -> 0.12254789 | AN54: =AN55*D55+AN62*D62 -> 0.1143096 | AO54: =AO55*E55+AO62*E62 -> 0.15483646 | AP54: =AP55*F55+AP62*F62 -> 0.16341377 | AQ54: =AQ55*G55+AQ62*G62 -> 0.097694978 | AR54: =AR55*H55+AR62*H62 -> 0.14806968 | AS54: =AS55*I55+AS62*I62 -> 0.11581248 | AT54: =AT55*J55+AT62*J62 -> 0.074813909 | ... BT54: =BT55*AJ55+BT62*AJ62 -> 0.14310259 | BV54: Cross - By Product Type By Technology
B55: Fixed-Position Self-Scanning Kiosks | C55: =C71 -> 0.8676332 | D55: =D71 -> 0.8811332 | E55: =E71 -> 0.8727332 | F55: =F71 -> 0.8764332 | G55: =G71 -> 0.8517332 | H55: =H71 -> 0.8803332 | I55: =I71 -> 0.8671332 | J55: =J71 -> 0.8523332 | ... AJ55: =AJ71 -> 0.8774332 | AL55: Fixed-Position Self-Scanning Kiosks | AM55: =AM56*C56+SUMPRODUCT(AM60:AM61,C60:C61) -> 0.11499798 | AN55: =AN56*D56+SUMPRODUCT(AN60:AN61,D60:D61) -> 0.10754378 | AO55: =AO56*E56+SUMPRODUCT(AO60:AO61,E60:E61) -> 0.14755071 | AP55: =AP56*F56+SUMPRODUCT(AP60:AP61,F60:F61) -> 0.15643188 | AQ55: =AQ56*G56+SUMPRODUCT(AQ60:AQ61,G60:G61) -> 0.089225007 | AR55: =AR56*H56+SUMPRODUCT(AR60:AR61,H60:H61) -> 0.1412737 | AS55: =AS56*I56+SUMPRODUCT(AS60:AS61,I60:I61) -> 0.10818509 | AT55: =AT56*J56+SUMPRODUCT(AT60:AT61,J60:J61) -> 0.065977307 | ... BT55: =BT56*AJ56+SUMPRODUCT(BT60:BT61,AJ60:AJ61) -> 0.13614676 | BV55: Fixed-Position Self-Scanning Kiosks | BW55: CMI_Trend_56 | BX55: CMI_Trend_60 | BY55: CMI_Trend_52 | BZ55: CMI_Trend_56 | CA55: CMI_Trend_60 | CB55: CMI_Trend_38 | CC55: CMI_Trend_38 | CD55: CMI_Trend_25 | CE55: CMI_Trend_38 | CF55: CMI_Trend_20 | CG55: CMI_Trend_46 | CH55: CMI_Trend_25 | CI55: CMI_Trend_56 | CJ55: CMI_Trend_20 | CK55: CMI_Trend_60 | CL55: CMI_Trend_25 | CM55: CMI_Trend_46 | CN55: CMI_Trend_46 | CO55: CMI_Trend_38 | CP55: CMI_Trend_52 | CQ55: CMI_Trend_20 | CR55: CMI_Trend_46 | CS55: CMI_Trend_46 | CT55: CMI_Trend_20 | CU55: CMI_Trend_38 | CV55: CMI_Trend_60 | CW55: CMI_Trend_60 | CX55: CMI_Trend_52 | CY55: CMI_Trend_60 | CZ55: CMI_Trend_38 | DA55: CMI_Trend_56 | DB55: CMI_Trend_46 | DC55: CMI_Trend_60 | DD55: CMI_Trend_20
B56: Barcode-Based Fixed Kiosks | C56: =1-SUM(C60:C61) -> 0.85289578 | D56: =1-SUM(D60:D61) -> 0.82809578 | E56: =1-SUM(E60:E61) -> 0.84089578 | F56: =1-SUM(F60:F61) -> 0.83219578 | G56: =1-SUM(G60:G61) -> 0.86409578 | H56: =1-SUM(H60:H61) -> 0.84209578 | I56: =1-SUM(I60:I61) -> 0.84069578 | J56: =1-SUM(J60:J61) -> 0.86119578 | ... AJ56: =1-SUM(AJ60:AJ61) -> 0.86069578 | AL56: Barcode-Based Fixed Kiosks | AM56: =SUMPRODUCT(AM57:AM59,C57:C59) -> 0.10519646 | AN56: =SUMPRODUCT(AN57:AN59,D57:D59) -> 0.096021764 | AO56: =SUMPRODUCT(AO57:AO59,E57:E59) -> 0.13914251 | AP56: =SUMPRODUCT(AP57:AP59,F57:F59) -> 0.14840054 | AQ56: =SUMPRODUCT(AQ57:AQ59,G57:G59) -> 0.078088328 | AR56: =SUMPRODUCT(AR57:AR59,H57:H59) -> 0.13256993 | AS56: =SUMPRODUCT(AS57:AS59,I57:I59) -> 0.097519478 | AT56: =SUMPRODUCT(AT57:AT59,J57:J59) -> 0.056524051 | ... BT56: =SUMPRODUCT(BT57:BT59,AJ57:AJ59) -> 0.12843609 | BV56: Barcode-Based Fixed Kiosks | BW56: CMI_Trend_52 | BX56: CMI_Trend_25 | BY56: CMI_Trend_56 | BZ56: CMI_Trend_52 | CA56: CMI_Trend_46 | CB56: CMI_Trend_56 | CC56: CMI_Trend_60 | CD56: CMI_Trend_56 | CE56: CMI_Trend_56 | CF56: CMI_Trend_60 | CG56: CMI_Trend_38 | CH56: CMI_Trend_38 | CI56: CMI_Trend_60 | CJ56: CMI_Trend_20 | CK56: CMI_Trend_25 | CL56: CMI_Trend_60 | CM56: CMI_Trend_38 | CN56: CMI_Trend_60 | CO56: CMI_Trend_25 | CP56: CMI_Trend_52 | CQ56: CMI_Trend_46 | CR56: CMI_Trend_25 | CS56: CMI_Trend_25 | CT56: CMI_Trend_60 | CU56: CMI_Trend_56 | CV56: CMI_Trend_52 | CW56: CMI_Trend_20 | CX56: CMI_Trend_46 | CY56: CMI_Trend_38 | CZ56: CMI_Trend_38 | DA56: CMI_Trend_38 | DB56: CMI_Trend_56 | DC56: CMI_Trend_46 | DD56: CMI_Trend_52
B57: Single-Plane Self-Scanning Kiosks | C57: =1-SUM(C58:C59) -> 0.37522574 | D57: =1-SUM(D58:D59) -> 0.40062574 | E57: =1-SUM(E58:E59) -> 0.35382574 | F57: =1-SUM(F58:F59) -> 0.35122574 | G57: =1-SUM(G58:G59) -> 0.36852574 | H57: =1-SUM(H58:H59) -> 0.38772574 | I57: =1-SUM(I58:I59) -> 0.38792574 | J57: =1-SUM(J58:J59) -> 0.37212574 | ... AJ57: =1-SUM(AJ58:AJ59) -> 0.38412574 | AL57: Single-Plane Self-Scanning Kiosks | AM57: 0.093681628 | AN57: 0.084803985 | AO57: 0.12989238 | AP57: 0.13958625 | AQ57: 0.063382576 | AR57: 0.12326523 | AS57: 0.085850082 | AT57: 0.04420595 | AU57: 0.11514631 | AV57: 0.10944337 | AW57: 0.10036604 | AX57: 0.0714787 | AY57: 0.058247772 | AZ57: 0.050168957 | BA57: 0.07846736 | BB57: 0.091415222 | BC57: 0.14467009 | BD57: 0.12689352 | BE57: 0.11094137 | BF57: 0.13507451 | BG57: 0.13871548 | BH57: 0.12149817 | BI57: 0.12971314 | BJ57: 0.11646765 | BK57: 0.10816378 | BL57: 0.10296177 | BM57: 0.091191398 | BN57: 0.12126875 | BO57: 0.095547778 | BP57: 0.11320568 | BQ57: 0.10601225 | BR57: 0.1257926 | BS57: 0.10430259 | BT57: 0.11839935 | BV57: Single-Plane Self-Scanning Kiosks | BW57: CMI_Trend_46 | BX57: CMI_Trend_52 | BY57: CMI_Trend_60 | BZ57: CMI_Trend_52 | CA57: CMI_Trend_46 | CB57: CMI_Trend_46 | CC57: CMI_Trend_56 | CD57: CMI_Trend_46 | CE57: CMI_Trend_60 | CF57: CMI_Trend_25 | CG57: CMI_Trend_52 | CH57: CMI_Trend_38 | CI57: CMI_Trend_52 | CJ57: CMI_Trend_46 | CK57: CMI_Trend_46 | CL57: CMI_Trend_52 | CM57: CMI_Trend_25 | CN57: CMI_Trend_38 | CO57: CMI_Trend_25 | CP57: CMI_Trend_60 | CQ57: CMI_Trend_56 | CR57: CMI_Trend_46 | CS57: CMI_Trend_56 | CT57: CMI_Trend_56 | CU57: CMI_Trend_25 | CV57: CMI_Trend_52 | CW57: CMI_Trend_38 | CX57: CMI_Trend_20 | CY57: CMI_Trend_52 | CZ57: CMI_Trend_60 | DA57: CMI_Trend_25 | DB57: CMI_Trend_46 | DC57: CMI_Trend_60 | DD57: CMI_Trend_52
B58: Multi-Plane Self-Scanning Kiosks | C58: 0.43816871 | D58: 0.42526871 | E58: 0.45176871 | F58: 0.45156871 | G58: 0.44556871 | H58: 0.42756871 | I58: 0.43276871 | J58: 0.43846871 | K58: 0.44146871 | L58: 0.44356871 | M58: 0.42486871 | N58: 0.43946871 | O58: 0.45056871 | P58: 0.43096871 | Q58: 0.45016871 | R58: 0.44836871 | S58: 0.42366871 | T58: 0.42556871 | U58: 0.42626871 | V58: 0.44376871 | W58: 0.42486871 | X58: 0.42886871 | Y58: 0.42596871 | Z58: 0.42326871 | AA58: 0.45306871 | AB58: 0.43586871 | AC58: 0.43376871 | AD58: 0.42306871 | AE58: 0.43376871 | AF58: 0.42226871 | AG58: 0.43266871 | AH58: 0.42416871 | AI58: 0.42546871 | AJ58: 0.43916871 | AL58: Multi-Plane Self-Scanning Kiosks | AM58: 0.11569228 | AN58: 0.10703696 | AO58: 0.14701273 | AP58: 0.15586754 | AQ58: 0.09111727 | AR58: 0.14144974 | AS58: 0.10853448 | AT58: 0.067721584 | AU58: 0.13407675 | AV58: 0.1293494 | AW58: 0.12129795 | AX58: 0.097590365 | AY58: 0.079609676 | AZ58: 0.073727283 | BA58: 0.10256176 | BB58: 0.11342587 | BC58: 0.16078856 | BD58: 0.14453793 | BE58: 0.13084741 | BF58: 0.15185417 | BG58: 0.15516123 | BH58: 0.13950083 | BI58: 0.14666229 | BJ58: 0.13578246 | BK58: 0.12787076 | BL58: 0.12347714 | BM58: 0.11320205 | BN58: 0.13963694 | BO58: 0.11755843 | BP58: 0.13252048 | BQ58: 0.12673484 | BR58: 0.14326057 | BS58: 0.12502518 | BT58: 0.13771416 | BV58: Multi-Plane Self-Scanning Kiosks | BW58: CMI_Trend_46 | BX58: CMI_Trend_25 | BY58: CMI_Trend_46 | BZ58: CMI_Trend_56 | CA58: CMI_Trend_52 | CB58: CMI_Trend_38 | CC58: CMI_Trend_52 | CD58: CMI_Trend_56 | CE58: CMI_Trend_56 | CF58: CMI_Trend_20 | CG58: CMI_Trend_20 | CH58: CMI_Trend_25 | CI58: CMI_Trend_56 | CJ58: CMI_Trend_20 | CK58: CMI_Trend_20 | CL58: CMI_Trend_60 | CM58: CMI_Trend_46 | CN58: CMI_Trend_38 | CO58: CMI_Trend_56 | CP58: CMI_Trend_56 | CQ58: CMI_Trend_38 | CR58: CMI_Trend_60 | CS58: CMI_Trend_38 | CT58: CMI_Trend_52 | CU58: CMI_Trend_60 | CV58: CMI_Trend_60 | CW58: CMI_Trend_60 | CX58: CMI_Trend_25 | CY58: CMI_Trend_25 | CZ58: CMI_Trend_56 | DA58: CMI_Trend_38 | DB58: CMI_Trend_60 | DC58: CMI_Trend_56 | DD58: CMI_Trend_52
B59: Presentation Self-Scanning Kiosks | C59: 0.18660555 | D59: 0.17410555 | E59: 0.19440555 | F59: 0.19720555 | G59: 0.18590555 | H59: 0.18470555 | I59: 0.17930555 | J59: 0.18940555 | K59: 0.18430555 | L59: 0.17580555 | M59: 0.18470555 | N59: 0.17450555 | O59: 0.20180555 | P59: 0.19960555 | Q59: 0.18460555 | R59: 0.20190555 | S59: 0.18760555 | T59: 0.20110555 | U59: 0.18620555 | V59: 0.19280555 | W59: 0.20300555 | X59: 0.17110555 | Y59: 0.17710555 | Z59: 0.17730555 | AA59: 0.18650555 | AB59: 0.18380555 | AC59: 0.19340555 | AD59: 0.20210555 | AE59: 0.17130555 | AF59: 0.18260555 | AG59: 0.17300555 | AH59: 0.18970555 | AI59: 0.17120555 | AJ59: 0.17670555 | AL59: Presentation Self-Scanning Kiosks | AM59: 0.1037052 | AN59: 0.094928809 | AO59: 0.13768893 | AP59: 0.1470007 | AQ59: 0.076012862 | AR59: 0.13154639 | AS59: 0.09618048 | AT59: 0.054803484 | AU59: 0.12376717 | AV59: 0.11850851 | AW59: 0.10989836 | AX59: 0.083369864 | AY59: 0.063885679 | AZ59: 0.061052129 | BA59: 0.089439868 | BB59: 0.1014388 | BC59: 0.15201039 | BD59: 0.13492873 | BE59: 0.12000651 | BF59: 0.14271591 | BG59: 0.14620482 | BH59: 0.12969652 | BI59: 0.13743173 | BJ59: 0.12526355 | BK59: 0.11713827 | BL59: 0.1123044 | BM59: 0.10121497 | BN59: 0.12963356 | BO59: 0.10557135 | BP59: 0.12200157 | BQ59: 0.11544925 | BR59: 0.13374745 | BS59: 0.11373959 | BT59: 0.12719525 | BV59: Presentation Self-Scanning Kiosks | BW59: CMI_Trend_46 | BX59: CMI_Trend_56 | BY59: CMI_Trend_46 | BZ59: CMI_Trend_60 | CA59: CMI_Trend_38 | CB59: CMI_Trend_56 | CC59: CMI_Trend_25 | CD59: CMI_Trend_52 | CE59: CMI_Trend_56 | CF59: CMI_Trend_20 | CG59: CMI_Trend_56 | CH59: CMI_Trend_20 | CI59: CMI_Trend_52 | CJ59: CMI_Trend_52 | CK59: CMI_Trend_38 | CL59: CMI_Trend_20 | CM59: CMI_Trend_56 | CN59: CMI_Trend_38 | CO59: CMI_Trend_52 | CP59: CMI_Trend_60 | CQ59: CMI_Trend_25 | CR59: CMI_Trend_56 | CS59: CMI_Trend_60 | CT59: CMI_Trend_38 | CU59: CMI_Trend_56 | CV59: CMI_Trend_56 | CW59: CMI_Trend_60 | CX59: CMI_Trend_25 | CY59: CMI_Trend_20 | CZ59: CMI_Trend_20 | DA59: CMI_Trend_56 | DB59: CMI_Trend_56 | DC59: CMI_Trend_56 | DD59: CMI_Trend_25
A60: 0.001 | B60: RFID-Based Fixed Kiosks | C60: 0.033790919 | D60: 0.041390919 | E60: 0.032190919 | F60: 0.042690919 | G60: 0.034390919 | H60: 0.036690919 | I60: 0.041390919 | J60: 0.038190919 | K60: 0.036790919 | L60: 0.032690919 | M60: 0.042790919 | N60: 0.028990919 | O60: 0.042190919 | P60: 0.042490919 | Q60: 0.030090919 | R60: 0.041490919 | S60: 0.035190919 | T60: 0.041690919 | U60: 0.032090919 | V60: 0.033590919 | W60: 0.029090919 | X60: 0.036390919 | Y60: 0.042890919 | Z60: 0.035590919 | AA60: 0.041790919 | AB60: 0.031890919 | AC60: 0.042190919 | AD60: 0.037190919 | AE60: 0.035990919 | AF60: 0.029390919 | AG60: 0.036390919 | AH60: 0.029490919 | AI60: 0.039090919 | AJ60: 0.040190919 | AL60: RFID-Based Fixed Kiosks | AM60: 0.12427548 | AN60: 0.11570686 | AO60: 0.15368893 | AP60: 0.16221654 | AQ60: 0.1019326 | AR60: 0.14854091 | AS60: 0.11738041 | AT60: 0.084804008 | AU60: 0.14145881 | AV60: 0.1371119 | AW60: 0.12946048 | AX60: 0.10777278 | AY60: 0.090868655 | AZ60: 0.089689734 | BA60: 0.11195753 | BB60: 0.12200907 | BC60: 0.16707407 | BD60: 0.15141849 | BE60: 0.1386099 | BF60: 0.15839751 | BG60: 0.16157435 | BH60: 0.14652109 | BI60: 0.15327173 | BJ60: 0.14331439 | BK60: 0.13555563 | BL60: 0.13147724 | BM60: 0.12178525 | BN60: 0.14679974 | BO60: 0.12614163 | BP60: 0.14005242 | BQ60: 0.13481576 | BR60: 0.15007232 | BS60: 0.13310609 | BT60: 0.14524609 | BV60: RFID-Based Fixed Kiosks | BW60: CMI_Trend_56 | BX60: CMI_Trend_52 | BY60: CMI_Trend_60 | BZ60: CMI_Trend_52 | CA60: CMI_Trend_56 | CB60: CMI_Trend_52 | CC60: CMI_Trend_60 | CD60: CMI_Trend_38 | CE60: CMI_Trend_25 | CF60: CMI_Trend_25 | CG60: CMI_Trend_56 | CH60: CMI_Trend_25 | CI60: CMI_Trend_52 | CJ60: CMI_Trend_25 | CK60: CMI_Trend_38 | CL60: CMI_Trend_25 | CM60: CMI_Trend_20 | CN60: CMI_Trend_25 | CO60: CMI_Trend_60 | CP60: CMI_Trend_20 | CQ60: CMI_Trend_20 | CR60: CMI_Trend_46 | CS60: CMI_Trend_56 | CT60: CMI_Trend_46 | CU60: CMI_Trend_20 | CV60: CMI_Trend_38 | CW60: CMI_Trend_46 | CX60: CMI_Trend_46 | CY60: CMI_Trend_52 | CZ60: CMI_Trend_52 | DA60: CMI_Trend_38 | DB60: CMI_Trend_46 | DC60: CMI_Trend_46 | DD60: CMI_Trend_60
B61: Computer Vision / AI-Based Fixed Kiosks | C61: 0.1133133 | D61: 0.1305133 | E61: 0.1269133 | F61: 0.1251133 | G61: 0.1015133 | H61: 0.1212133 | I61: 0.1179133 | J61: 0.1006133 | K61: 0.1261133 | L61: 0.1144133 | M61: 0.1269133 | N61: 0.1044133 | O61: 0.1293133 | P61: 0.1101133 | Q61: 0.1069133 | R61: 0.1205133 | S61: 0.1095133 | T61: 0.1186133 | U61: 0.1079133 | V61: 0.1078133 | W61: 0.1062133 | X61: 0.1265133 | Y61: 0.1275133 | Z61: 0.098313297 | AA61: 0.099013297 | AB61: 0.1159133 | AC61: 0.1164133 | AD61: 0.1193133 | AE61: 0.097113297 | AF61: 0.1041133 | AG61: 0.1029133 | AH61: 0.1261133 | AI61: 0.1267133 | AJ61: 0.099113297 | AL61: Computer Vision / AI-Based Fixed Kiosks | AM61: 0.18600622 | AN61: 0.17806115 | AO61: 0.20170441 | AP61: 0.20787879 | AQ61: 0.17971691 | AR61: 0.19954091 | AS61: 0.18100074 | AT61: 0.13974584 | AU61: 0.19455084 | AV61: 0.19294007 | AW61: 0.1881658 | AX61: 0.18100517 | AY61: 0.1718437 | AZ61: 0.14687772 | BA61: 0.17953233 | BB61: 0.18373981 | BC61: 0.2122797 | BD61: 0.20090374 | BE61: 0.19443807 | BF61: 0.20545749 | BG61: 0.20769784 | BH61: 0.19701109 | BI61: 0.20080706 | BJ61: 0.19748442 | BK61: 0.19082552 | BL61: 0.18901432 | BM61: 0.18351599 | BN61: 0.19831489 | BO61: 0.18787237 | BP61: 0.19422244 | BQ61: 0.19293402 | BR61: 0.19906271 | BS61: 0.19122436 | BT61: 0.19941612 | BV61: Computer Vision / AI-Based Fixed Kiosks | BW61: CMI_Trend_52 | BX61: CMI_Trend_20 | BY61: CMI_Trend_25 | BZ61: CMI_Trend_38 | CA61: CMI_Trend_56 | CB61: CMI_Trend_20 | CC61: CMI_Trend_52 | CD61: CMI_Trend_20 | CE61: CMI_Trend_52 | CF61: CMI_Trend_20 | CG61: CMI_Trend_38 | CH61: CMI_Trend_25 | CI61: CMI_Trend_38 | CJ61: CMI_Trend_46 | CK61: CMI_Trend_20 | CL61: CMI_Trend_25 | CM61: CMI_Trend_56 | CN61: CMI_Trend_38 | CO61: CMI_Trend_38 | CP61: CMI_Trend_20 | CQ61: CMI_Trend_60 | CR61: CMI_Trend_25 | CS61: CMI_Trend_25 | CT61: CMI_Trend_60 | CU61: CMI_Trend_25 | CV61: CMI_Trend_38 | CW61: CMI_Trend_56 | CX61: CMI_Trend_25 | CY61: CMI_Trend_46 | CZ61: CMI_Trend_56 | DA61: CMI_Trend_38 | DB61: CMI_Trend_56 | DC61: CMI_Trend_20 | DD61: CMI_Trend_60
B62: Mobile Self-Scanning Solutions | C62: =C93 -> 0.1323668 | D62: =D93 -> 0.1188668 | E62: =E93 -> 0.1272668 | F62: =F93 -> 0.1235668 | G62: =G93 -> 0.1482668 | H62: =H93 -> 0.1196668 | I62: =I93 -> 0.1328668 | J62: =J93 -> 0.1476668 | ... AJ62: =AJ93 -> 0.1225668 | AL62: Mobile Self-Scanning Solutions | AM62: =AM63*C63+SUMPRODUCT(AM67:AM68,C67:C68) -> 0.17203577 | AN62: =AN63*D63+SUMPRODUCT(AN67:AN68,D67:D68) -> 0.16446311 | AO62: =AO63*E63+SUMPRODUCT(AO67:AO68,E67:E68) -> 0.2047986 | AP62: =AP63*F63+SUMPRODUCT(AP67:AP68,F67:F68) -> 0.21293484 | AQ62: =AQ63*G63+SUMPRODUCT(AQ67:AQ68,G67:G68) -> 0.14635156 | AR62: =AR63*H63+SUMPRODUCT(AR67:AR68,H67:H68) -> 0.19806459 | AS62: =AS63*I63+SUMPRODUCT(AS67:AS68,I67:I68) -> 0.16559138 | AT62: =AT63*J63+SUMPRODUCT(AT67:AT68,J67:J68) -> 0.1258188 | ... BT62: =BT63*AJ63+SUMPRODUCT(BT67:BT68,AJ67:AJ68) -> 0.19289804 | BV62: Mobile Self-Scanning Solutions | BW62: CMI_Trend_60 | BX62: CMI_Trend_38 | BY62: CMI_Trend_60 | BZ62: CMI_Trend_56 | CA62: CMI_Trend_38 | CB62: CMI_Trend_56 | CC62: CMI_Trend_56 | CD62: CMI_Trend_56 | CE62: CMI_Trend_25 | CF62: CMI_Trend_60 | CG62: CMI_Trend_38 | CH62: CMI_Trend_56 | CI62: CMI_Trend_46 | CJ62: CMI_Trend_25 | CK62: CMI_Trend_20 | CL62: CMI_Trend_60 | CM62: CMI_Trend_56 | CN62: CMI_Trend_56 | CO62: CMI_Trend_20 | CP62: CMI_Trend_20 | CQ62: CMI_Trend_56 | CR62: CMI_Trend_38 | CS62: CMI_Trend_46 | CT62: CMI_Trend_20 | CU62: CMI_Trend_46 | CV62: CMI_Trend_20 | CW62: CMI_Trend_46 | CX62: CMI_Trend_38 | CY62: CMI_Trend_25 | CZ62: CMI_Trend_60 | DA62: CMI_Trend_52 | DB62: CMI_Trend_52 | DC62: CMI_Trend_60 | DD62: CMI_Trend_52
B63: Barcode-Based Mobile Self-Scanning | C63: =1-SUM(C67:C68) -> 0.9065328 | D63: =1-SUM(D67:D68) -> 0.8986328 | E63: =1-SUM(E67:E68) -> 0.9086328 | F63: =1-SUM(F67:F68) -> 0.8974328 | G63: =1-SUM(G67:G68) -> 0.9073328 | H63: =1-SUM(H67:H68) -> 0.9155328 | I63: =1-SUM(I67:I68) -> 0.9089328 | J63: =1-SUM(J67:J68) -> 0.8970328 | ... AJ63: =1-SUM(AJ67:AJ68) -> 0.9062328 | AL63: Barcode-Based Mobile Self-Scanning | AM63: =SUMPRODUCT(AM64:AM66,C64:C66) -> 0.17151446 | AN63: =SUMPRODUCT(AN64:AN66,D64:D66) -> 0.16394878 | AO63: =SUMPRODUCT(AO64:AO66,E64:E66) -> 0.20458863 | AP63: =SUMPRODUCT(AP64:AP66,F64:F66) -> 0.21224978 | AQ63: =SUMPRODUCT(AQ64:AQ66,G64:G66) -> 0.14606186 | AR63: =SUMPRODUCT(AR64:AR66,H64:H66) -> 0.1978188 | AS63: =SUMPRODUCT(AS64:AS66,I64:I66) -> 0.16518353 | AT63: =SUMPRODUCT(AT64:AT66,J64:J66) -> 0.12505542 | ... BT63: =SUMPRODUCT(BT64:BT66,AJ64:AJ66) -> 0.19243021 | BV63: Barcode-Based Mobile Self-Scanning | BW63: CMI_Trend_52 | BX63: CMI_Trend_52 | BY63: CMI_Trend_60 | BZ63: CMI_Trend_38 | CA63: CMI_Trend_56 | CB63: CMI_Trend_60 | CC63: CMI_Trend_56 | CD63: CMI_Trend_52 | CE63: CMI_Trend_25 | CF63: CMI_Trend_56 | CG63: CMI_Trend_25 | CH63: CMI_Trend_38 | CI63: CMI_Trend_56 | CJ63: CMI_Trend_20 | CK63: CMI_Trend_38 | CL63: CMI_Trend_25 | CM63: CMI_Trend_25 | CN63: CMI_Trend_25 | CO63: CMI_Trend_46 | CP63: CMI_Trend_52 | CQ63: CMI_Trend_46 | CR63: CMI_Trend_25 | CS63: CMI_Trend_56 | CT63: CMI_Trend_52 | CU63: CMI_Trend_56 | CV63: CMI_Trend_52 | CW63: CMI_Trend_52 | CX63: CMI_Trend_52 | CY63: CMI_Trend_60 | CZ63: CMI_Trend_25 | DA63: CMI_Trend_56 | DB63: CMI_Trend_20 | DC63: CMI_Trend_60 | DD63: CMI_Trend_56
B64: Dedicated Mobile Self-Scanning Devices | C64: =1-SUM(C65:C66) -> 0.50221314 | D64: =1-SUM(D65:D66) -> 0.50821314 | E64: =1-SUM(E65:E66) -> 0.49991314 | F64: =1-SUM(F65:F66) -> 0.51551314 | G64: =1-SUM(G65:G66) -> 0.51551314 | H64: =1-SUM(H65:H66) -> 0.49021314 | I64: =1-SUM(I65:I66) -> 0.51171314 | J64: =1-SUM(J65:J66) -> 0.50931314 | ... AJ64: =1-SUM(AJ65:AJ66) -> 0.51351314 | AL64: Dedicated Mobile Self-Scanning Devices | AM64: 0.15074003 | AN64: 0.14336197 | AO64: 0.18380005 | AP64: 0.19195407 | AQ64: 0.1259695 | AR64: 0.1764353 | AS64: 0.14489242 | AT64: 0.10445541 | AU64: 0.16956732 | AV64: 0.16466352 | AW64: 0.15676995 | AX64: 0.13144355 | AY64: 0.12022694 | AZ64: 0.11252129 | BA64: 0.13693924 | BB64: 0.15085313 | BC64: 0.19452913 | BD64: 0.18144626 | BE64: 0.16542248 | BF64: 0.1858038 | BG64: 0.19136828 | BH64: 0.17563733 | BI64: 0.18226811 | BJ64: 0.16970816 | BK64: 0.16322929 | BL64: 0.15803754 | BM64: 0.14918244 | BN64: 0.17458466 | BO64: 0.15000036 | BP64: 0.16681391 | BQ64: 0.16007928 | BR64: 0.17921123 | BS64: 0.16002503 | BT64: 0.17220131 | BV64: Dedicated Mobile Self-Scanning Devices | BW64: CMI_Trend_25 | BX64: CMI_Trend_38 | BY64: CMI_Trend_60 | BZ64: CMI_Trend_20 | CA64: CMI_Trend_60 | CB64: CMI_Trend_25 | CC64: CMI_Trend_60 | CD64: CMI_Trend_56 | CE64: CMI_Trend_56 | CF64: CMI_Trend_56 | CG64: CMI_Trend_56 | CH64: CMI_Trend_25 | CI64: CMI_Trend_56 | CJ64: CMI_Trend_38 | CK64: CMI_Trend_56 | CL64: CMI_Trend_56 | CM64: CMI_Trend_46 | CN64: CMI_Trend_25 | CO64: CMI_Trend_60 | CP64: CMI_Trend_60 | CQ64: CMI_Trend_25 | CR64: CMI_Trend_46 | CS64: CMI_Trend_60 | CT64: CMI_Trend_20 | CU64: CMI_Trend_52 | CV64: CMI_Trend_20 | CW64: CMI_Trend_60 | CX64: CMI_Trend_38 | CY64: CMI_Trend_60 | CZ64: CMI_Trend_25 | DA64: CMI_Trend_60 | DB64: CMI_Trend_38 | DC64: CMI_Trend_38 | DD64: CMI_Trend_46
B65: Smartphone-Based Self-Scanning | C65: 0.23186308 | D65: 0.22536308 | E65: 0.23776308 | F65: 0.22116308 | G65: 0.23316308 | H65: 0.23106308 | I65: 0.23256308 | J65: 0.22136308 | K65: 0.23666308 | L65: 0.23666308 | M65: 0.23386308 | N65: 0.23936308 | O65: 0.23626308 | P65: 0.22816308 | Q65: 0.23586308 | R65: 0.21936308 | S65: 0.23536308 | T65: 0.23146308 | U65: 0.24126308 | V65: 0.23746308 | W65: 0.22276308 | X65: 0.23576308 | Y65: 0.21786308 | Z65: 0.24526308 | AA65: 0.24536308 | AB65: 0.24106308 | AC65: 0.21626308 | AD65: 0.21816308 | AE65: 0.23276308 | AF65: 0.22736308 | AG65: 0.23866308 | AH65: 0.23246308 | AI65: 0.22696308 | AJ65: 0.23096308 | AL65: Smartphone-Based Self-Scanning | AM65: 0.18342101 | AN65: 0.17604295 | AO65: 0.21648103 | AP65: 0.22463505 | AQ65: 0.15865047 | AR65: 0.20911628 | AS65: 0.1775734 | AT65: 0.13713639 | AU65: 0.2022483 | AV65: 0.1973445 | AW65: 0.18945093 | AX65: 0.16412453 | AY65: 0.15290792 | AZ65: 0.14520227 | BA65: 0.16962022 | BB65: 0.18353411 | BC65: 0.22721011 | BD65: 0.21412724 | BE65: 0.19810346 | BF65: 0.21848478 | BG65: 0.22404926 | BH65: 0.20831831 | BI65: 0.21494909 | BJ65: 0.20238913 | BK65: 0.19591027 | BL65: 0.19071852 | BM65: 0.18186342 | BN65: 0.20726564 | BO65: 0.18268134 | BP65: 0.19949489 | BQ65: 0.19276026 | BR65: 0.21189221 | BS65: 0.19270601 | BT65: 0.20488229 | BV65: Smartphone-Based Self-Scanning | BW65: CMI_Trend_56 | BX65: CMI_Trend_25 | BY65: CMI_Trend_52 | BZ65: CMI_Trend_25 | CA65: CMI_Trend_46 | CB65: CMI_Trend_25 | CC65: CMI_Trend_60 | CD65: CMI_Trend_38 | CE65: CMI_Trend_52 | CF65: CMI_Trend_56 | CG65: CMI_Trend_38 | CH65: CMI_Trend_20 | CI65: CMI_Trend_60 | CJ65: CMI_Trend_56 | CK65: CMI_Trend_38 | CL65: CMI_Trend_25 | CM65: CMI_Trend_56 | CN65: CMI_Trend_56 | CO65: CMI_Trend_52 | CP65: CMI_Trend_20 | CQ65: CMI_Trend_38 | CR65: CMI_Trend_60 | CS65: CMI_Trend_52 | CT65: CMI_Trend_56 | CU65: CMI_Trend_60 | CV65: CMI_Trend_38 | CW65: CMI_Trend_25 | CX65: CMI_Trend_20 | CY65: CMI_Trend_60 | CZ65: CMI_Trend_60 | DA65: CMI_Trend_52 | DB65: CMI_Trend_60 | DC65: CMI_Trend_56 | DD65: CMI_Trend_46
B66: Smart-Cart Barcode Self-Scanning | C66: 0.26592378 | D66: 0.26642378 | E66: 0.26232378 | F66: 0.26332378 | G66: 0.25132378 | H66: 0.27872378 | I66: 0.25572378 | J66: 0.26932378 | K66: 0.28212378 | L66: 0.26162378 | M66: 0.28112378 | N66: 0.25002378 | O66: 0.25442378 | P66: 0.25932378 | Q66: 0.26432378 | R66: 0.25732378 | S66: 0.27732378 | T66: 0.25592378 | U66: 0.25042378 | V66: 0.25982378 | W66: 0.25372378 | X66: 0.26052378 | Y66: 0.27952378 | Z66: 0.26502378 | AA66: 0.25082378 | AB66: 0.27412378 | AC66: 0.26722378 | AD66: 0.26442378 | AE66: 0.27842378 | AF66: 0.26382378 | AG66: 0.25692378 | AH66: 0.25832378 | AI66: 0.28242378 | AJ66: 0.25552378 | AL66: Smart-Cart Barcode Self-Scanning | AM66: 0.2003667 | AN66: 0.19298864 | AO66: 0.23342672 | AP66: 0.24158074 | AQ66: 0.17559617 | AR66: 0.22606197 | AS66: 0.19451909 | AT66: 0.15408208 | AU66: 0.21919399 | AV66: 0.21429019 | AW66: 0.20639663 | AX66: 0.18107022 | AY66: 0.16985362 | AZ66: 0.16214797 | BA66: 0.18656591 | BB66: 0.20047981 | BC66: 0.2441558 | BD66: 0.23107293 | BE66: 0.21504915 | BF66: 0.23543047 | BG66: 0.24099495 | BH66: 0.225264 | BI66: 0.23189478 | BJ66: 0.21933483 | BK66: 0.21285596 | BL66: 0.20766421 | BM66: 0.19880911 | BN66: 0.22421134 | BO66: 0.19962703 | BP66: 0.21644059 | BQ66: 0.20970595 | BR66: 0.2288379 | BS66: 0.2096517 | BT66: 0.22182798 | BV66: Smart-Cart Barcode Self-Scanning | BW66: CMI_Trend_60 | BX66: CMI_Trend_20 | BY66: CMI_Trend_52 | BZ66: CMI_Trend_56 | CA66: CMI_Trend_56 | CB66: CMI_Trend_20 | CC66: CMI_Trend_56 | CD66: CMI_Trend_56 | CE66: CMI_Trend_52 | CF66: CMI_Trend_56 | CG66: CMI_Trend_52 | CH66: CMI_Trend_38 | CI66: CMI_Trend_20 | CJ66: CMI_Trend_56 | CK66: CMI_Trend_25 | CL66: CMI_Trend_60 | CM66: CMI_Trend_25 | CN66: CMI_Trend_60 | CO66: CMI_Trend_20 | CP66: CMI_Trend_56 | CQ66: CMI_Trend_46 | CR66: CMI_Trend_56 | CS66: CMI_Trend_25 | CT66: CMI_Trend_20 | CU66: CMI_Trend_60 | CV66: CMI_Trend_60 | CW66: CMI_Trend_25 | CX66: CMI_Trend_25 | CY66: CMI_Trend_60 | CZ66: CMI_Trend_25 | DA66: CMI_Trend_25 | DB66: CMI_Trend_46 | DC66: CMI_Trend_20 | DD66: CMI_Trend_60
B67: RFID-Based Mobile Self-Scanning Solutions | C67: 0.043133209 | D67: 0.048533209 | E67: 0.049633209 | F67: 0.045733209 | G67: 0.050033209 | H67: 0.043333209 | I67: 0.045633209 | J67: 0.043233209 | K67: 0.038333209 | L67: 0.049633209 | M67: 0.036433209 | N67: 0.050433209 | O67: 0.036933209 | P67: 0.049833209 | Q67: 0.042633209 | R67: 0.049333209 | S67: 0.046233209 | T67: 0.047933209 | U67: 0.049633209 | V67: 0.042433209 | W67: 0.049833209 | X67: 0.045333209 | Y67: 0.041933209 | Z67: 0.036233209 | AA67: 0.039033209 | AB67: 0.048833209 | AC67: 0.044733209 | AD67: 0.037133209 | AE67: 0.036833209 | AF67: 0.047733209 | AG67: 0.047933209 | AH67: 0.042833209 | AI67: 0.036733209 | AJ67: 0.045933209 | AL67: RFID-Based Mobile Self-Scanning Solutions | AM67: 0.15558166 | AN67: 0.14820359 | AO67: 0.18864167 | AP67: 0.1967957 | AQ67: 0.13081112 | AR67: 0.18127693 | AS67: 0.14973405 | AT67: 0.10929704 | AU67: 0.17440895 | AV67: 0.16950515 | AW67: 0.16161158 | AX67: 0.13628518 | AY67: 0.12506857 | AZ67: 0.11736292 | BA67: 0.14178087 | BB67: 0.15569476 | BC67: 0.19937076 | BD67: 0.18628789 | BE67: 0.17026411 | BF67: 0.19064543 | BG67: 0.19620991 | BH67: 0.18047895 | BI67: 0.18710974 | BJ67: 0.17454978 | BK67: 0.16807092 | BL67: 0.16287917 | BM67: 0.15402406 | BN67: 0.17942629 | BO67: 0.15484199 | BP67: 0.17165554 | BQ67: 0.1649209 | BR67: 0.18405286 | BS67: 0.16486666 | BT67: 0.17704294 | BV67: RFID-Based Mobile Self-Scanning Solutions | BW67: CMI_Trend_46 | BX67: CMI_Trend_20 | BY67: CMI_Trend_20 | BZ67: CMI_Trend_38 | CA67: CMI_Trend_52 | CB67: CMI_Trend_60 | CC67: CMI_Trend_60 | CD67: CMI_Trend_52 | CE67: CMI_Trend_56 | CF67: CMI_Trend_38 | CG67: CMI_Trend_52 | CH67: CMI_Trend_56 | CI67: CMI_Trend_60 | CJ67: CMI_Trend_46 | CK67: CMI_Trend_38 | CL67: CMI_Trend_46 | CM67: CMI_Trend_38 | CN67: CMI_Trend_46 | CO67: CMI_Trend_60 | CP67: CMI_Trend_52 | CQ67: CMI_Trend_56 | CR67: CMI_Trend_60 | CS67: CMI_Trend_60 | CT67: CMI_Trend_52 | CU67: CMI_Trend_56 | CV67: CMI_Trend_38 | CW67: CMI_Trend_38 | CX67: CMI_Trend_56 | CY67: CMI_Trend_25 | CZ67: CMI_Trend_46 | DA67: CMI_Trend_38 | DB67: CMI_Trend_52 | DC67: CMI_Trend_20 | DD67: CMI_Trend_38
B68: Computer Vision / AI Smart-Cart Self-Scanning | C68: 0.050333994 | D68: 0.052833994 | E68: 0.041733994 | F68: 0.056833994 | G68: 0.042633994 | H68: 0.041133994 | I68: 0.045433994 | J68: 0.059733994 | K68: 0.055433994 | L68: 0.048333994 | M68: 0.046333994 | N68: 0.050533994 | O68: 0.048433994 | P68: 0.047033994 | Q68: 0.041633994 | R68: 0.040633994 | S68: 0.055133994 | T68: 0.041533994 | U68: 0.040133994 | V68: 0.058733994 | W68: 0.058033994 | X68: 0.052033994 | Y68: 0.041433994 | Z68: 0.040533994 | AA68: 0.047833994 | AB68: 0.044233994 | AC68: 0.050533994 | AD68: 0.059433994 | AE68: 0.047533994 | AF68: 0.056133994 | AG68: 0.059733994 | AH68: 0.041233994 | AI68: 0.049133994 | AJ68: 0.047833994 | AL68: Computer Vision / AI Smart-Cart Self-Scanning | AM68: 0.19552508 | AN68: 0.18814701 | AO68: 0.22858509 | AP68: 0.23673912 | AQ68: 0.17075454 | AR68: 0.22122035 | AS68: 0.18967747 | AT68: 0.14924046 | AU68: 0.21435237 | AV68: 0.20944857 | AW68: 0.201555 | AX68: 0.17622859 | AY68: 0.16501199 | AZ68: 0.15730634 | BA68: 0.18172429 | BB68: 0.19563818 | BC68: 0.23931417 | BD68: 0.22623131 | BE68: 0.21020753 | BF68: 0.23058885 | BG68: 0.23615333 | BH68: 0.22042237 | BI68: 0.22705316 | BJ68: 0.2144932 | BK68: 0.20801434 | BL68: 0.20282258 | BM68: 0.19396748 | BN68: 0.21936971 | BO68: 0.19478541 | BP68: 0.21159896 | BQ68: 0.20486432 | BR68: 0.22399628 | BS68: 0.20481008 | BT68: 0.21698636 | BV68: Computer Vision / AI Smart-Cart Self-Scanning | BW68: CMI_Trend_20 | BX68: CMI_Trend_25 | BY68: CMI_Trend_52 | BZ68: CMI_Trend_38 | CA68: CMI_Trend_60 | CB68: CMI_Trend_56 | CC68: CMI_Trend_46 | CD68: CMI_Trend_46 | CE68: CMI_Trend_56 | CF68: CMI_Trend_60 | CG68: CMI_Trend_20 | CH68: CMI_Trend_38 | CI68: CMI_Trend_52 | CJ68: CMI_Trend_60 | CK68: CMI_Trend_25 | CL68: CMI_Trend_46 | CM68: CMI_Trend_52 | CN68: CMI_Trend_52 | CO68: CMI_Trend_60 | CP68: CMI_Trend_38 | CQ68: CMI_Trend_56 | CR68: CMI_Trend_25 | CS68: CMI_Trend_20 | CT68: CMI_Trend_25 | CU68: CMI_Trend_52 | CV68: CMI_Trend_46 | CW68: CMI_Trend_20 | CX68: CMI_Trend_60 | CY68: CMI_Trend_25 | CZ68: CMI_Trend_25 | DA68: CMI_Trend_56 | DB68: CMI_Trend_25 | DC68: CMI_Trend_20 | DD68: CMI_Trend_20
B70: Cross - By Product Type, by Retail Format | AL70: Cross - By Product Type, by Retail Format | BV70: Cross - By Product Type, by Retail Format
B71: Fixed-Position Self-Scanning Kiosks | C71: =1-C93 -> 0.8676332 | D71: =1-D93 -> 0.8811332 | E71: =1-E93 -> 0.8727332 | F71: =1-F93 -> 0.8764332 | G71: =1-G93 -> 0.8517332 | H71: =1-H93 -> 0.8803332 | I71: =1-I93 -> 0.8671332 | J71: =1-J93 -> 0.8523332 | ... AJ71: =1-AJ93 -> 0.8774332 | AL71: Fixed-Position Self-Scanning Kiosks | AM71: =AM72*C72+AM79*C79+AM86*C86 -> 0.11499798 | AN71: =AN72*D72+AN79*D79+AN86*D86 -> 0.1075435 | AO71: =AO72*E72+AO79*E79+AO86*E86 -> 0.14719862 | AP71: =AP72*F72+AP79*F79+AP86*F86 -> 0.15656005 | AQ71: =AQ72*G72+AQ79*G79+AQ86*G86 -> 0.088982032 | AR71: =AR72*H72+AR79*H79+AR86*H86 -> 0.14129813 | AS71: =AS72*I72+AS79*I79+AS86*I86 -> 0.10841588 | AT71: =AT72*J72+AT79*J79+AT86*J86 -> 0.068466925 | ... BT71: =BT72*AJ72+BT79*AJ79+BT86*AJ86 -> 0.13622082 | BV71: Fixed-Position Self-Scanning Kiosks | BW71: CMI_Trend_25 | BX71: CMI_Trend_46 | BY71: CMI_Trend_38 | BZ71: CMI_Trend_60 | CA71: CMI_Trend_60 | CB71: CMI_Trend_60 | CC71: CMI_Trend_46 | CD71: CMI_Trend_38 | CE71: CMI_Trend_52 | CF71: CMI_Trend_52 | CG71: CMI_Trend_25 | CH71: CMI_Trend_20 | CI71: CMI_Trend_20 | CJ71: CMI_Trend_56 | CK71: CMI_Trend_38 | CL71: CMI_Trend_56 | CM71: CMI_Trend_38 | CN71: CMI_Trend_60 | CO71: CMI_Trend_52 | CP71: CMI_Trend_46 | CQ71: CMI_Trend_52 | CR71: CMI_Trend_46 | CS71: CMI_Trend_25 | CT71: CMI_Trend_56 | CU71: CMI_Trend_25 | CV71: CMI_Trend_20 | CW71: CMI_Trend_46 | CX71: CMI_Trend_46 | CY71: CMI_Trend_25 | CZ71: CMI_Trend_46 | DA71: CMI_Trend_52 | DB71: CMI_Trend_56 | DC71: CMI_Trend_52 | DD71: CMI_Trend_38
B72: Single-Plane Self-Scanning Kiosks | C72: =1-SUM(C79,C86) -> 0.37799855 | D72: =1-SUM(D79,D86) -> 0.37049855 | E72: =1-SUM(E79,E86) -> 0.39259855 | F72: =1-SUM(F79,F86) -> 0.38059855 | G72: =1-SUM(G79,G86) -> 0.39029855 | H72: =1-SUM(H79,H86) -> 0.37919855 | I72: =1-SUM(I79,I86) -> 0.37409855 | J72: =1-SUM(J79,J86) -> 0.39649855 | ... AJ72: =1-SUM(AJ79,AJ86) -> 0.38199855 | AL72: Single-Plane Self-Scanning Kiosks | AM72: =SUMPRODUCT(AM73:AM78,C73:C78) -> 0.10635961 | AN72: =SUMPRODUCT(AN73:AN78,D73:D78) -> 0.098786495 | AO72: =SUMPRODUCT(AO73:AO78,E73:E78) -> 0.13873346 | AP72: =SUMPRODUCT(AP73:AP78,F73:F78) -> 0.14798896 | AQ72: =SUMPRODUCT(AQ73:AQ78,G73:G78) -> 0.080544311 | AR72: =SUMPRODUCT(AR73:AR78,H73:H78) -> 0.13258846 | AS72: =SUMPRODUCT(AS73:AS78,I73:I78) -> 0.099703867 | AT72: =SUMPRODUCT(AT73:AT78,J73:J78) -> 0.060003192 | ... BT72: =SUMPRODUCT(BT73:BT78,AJ73:AJ78) -> 0.12762544 | BV72: Single-Plane Self-Scanning Kiosks | BW72: CMI_Trend_38 | BX72: CMI_Trend_60 | BY72: CMI_Trend_56 | BZ72: CMI_Trend_46 | CA72: CMI_Trend_25 | CB72: CMI_Trend_52 | CC72: CMI_Trend_38 | CD72: CMI_Trend_25 | CE72: CMI_Trend_60 | CF72: CMI_Trend_25 | CG72: CMI_Trend_20 | CH72: CMI_Trend_46 | CI72: CMI_Trend_38 | CJ72: CMI_Trend_38 | CK72: CMI_Trend_52 | CL72: CMI_Trend_38 | CM72: CMI_Trend_46 | CN72: CMI_Trend_46 | CO72: CMI_Trend_60 | CP72: CMI_Trend_20 | CQ72: CMI_Trend_52 | CR72: CMI_Trend_60 | CS72: CMI_Trend_52 | CT72: CMI_Trend_52 | CU72: CMI_Trend_60 | CV72: CMI_Trend_56 | CW72: CMI_Trend_52 | CX72: CMI_Trend_60 | CY72: CMI_Trend_52 | CZ72: CMI_Trend_46 | DA72: CMI_Trend_56 | DB72: CMI_Trend_20 | DC72: CMI_Trend_20 | DD72: CMI_Trend_38
B73: Supermarkets & Hypermarkets | C73: =1-SUM(C74:C78) -> 0.57868336 | D73: =1-SUM(D74:D78) -> 0.56218336 | E73: =1-SUM(E74:E78) -> 0.58658336 | F73: =1-SUM(F74:F78) -> 0.58748336 | G73: =1-SUM(G74:G78) -> 0.55638336 | H73: =1-SUM(H74:H78) -> 0.53608336 | I73: =1-SUM(I74:I78) -> 0.57998336 | J73: =1-SUM(J74:J78) -> 0.56078336 | ... AJ73: =1-SUM(AJ74:AJ78) -> 0.57438336 | AL73: Supermarkets & Hypermarkets | AM73: 0.10700318 | AN73: 0.099201809 | AO73: 0.13928793 | AP73: 0.14844364 | AQ73: 0.081433171 | AR73: 0.13340879 | AS73: 0.10020085 | AT73: 0.060763137 | AU73: 0.12649219 | AV73: 0.12068634 | AW73: 0.114096 | AX73: 0.087997867 | AY73: 0.075125505 | AZ73: 0.068161907 | BA73: 0.093545204 | BB73: 0.10591729 | BC73: 0.1519815 | BD73: 0.13674439 | BE73: 0.12133543 | BF73: 0.14271584 | BG73: 0.14633302 | BH73: 0.13129005 | BI73: 0.13908772 | BJ73: 0.12604445 | BK73: 0.11865558 | BL73: 0.11530373 | BM73: 0.10462606 | BN73: 0.13103167 | BO73: 0.10730849 | BP73: 0.12323659 | BQ73: 0.11680614 | BR73: 0.13549298 | BS73: 0.11727591 | BT73: 0.12848549 | BV73: Supermarkets & Hypermarkets | BW73: CMI_Trend_56 | BX73: CMI_Trend_60 | BY73: CMI_Trend_56 | BZ73: CMI_Trend_38 | CA73: CMI_Trend_56 | CB73: CMI_Trend_25 | CC73: CMI_Trend_38 | CD73: CMI_Trend_56 | CE73: CMI_Trend_38 | CF73: CMI_Trend_25 | CG73: CMI_Trend_60 | CH73: CMI_Trend_52 | CI73: CMI_Trend_25 | CJ73: CMI_Trend_25 | CK73: CMI_Trend_25 | CL73: CMI_Trend_56 | CM73: CMI_Trend_60 | CN73: CMI_Trend_60 | CO73: CMI_Trend_20 | CP73: CMI_Trend_20 | CQ73: CMI_Trend_46 | CR73: CMI_Trend_25 | CS73: CMI_Trend_52 | CT73: CMI_Trend_56 | CU73: CMI_Trend_46 | CV73: CMI_Trend_60 | CW73: CMI_Trend_38 | CX73: CMI_Trend_25 | CY73: CMI_Trend_25 | CZ73: CMI_Trend_52 | DA73: CMI_Trend_52 | DB73: CMI_Trend_38 | DC73: CMI_Trend_52 | DD73: CMI_Trend_56
B74: Convenience Stores | C74: 0.12509333 | D74: 0.13889333 | E74: 0.11379333 | F74: 0.11519333 | G74: 0.13139333 | H74: 0.14159333 | I74: 0.13439333 | J74: 0.13659333 | K74: 0.13329333 | L74: 0.14019333 | M74: 0.13279333 | N74: 0.12159333 | O74: 0.14039333 | P74: 0.13069333 | Q74: 0.11369333 | R74: 0.13519333 | S74: 0.11709333 | T74: 0.12919333 | U74: 0.13029333 | V74: 0.12899333 | W74: 0.13629333 | X74: 0.11339333 | Y74: 0.11629333 | Z74: 0.12049333 | AA74: 0.12249333 | AB74: 0.12849333 | AC74: 0.11349333 | AD74: 0.12809333 | AE74: 0.13989333 | AF74: 0.13009333 | AG74: 0.11129333 | AH74: 0.13769333 | AI74: 0.13329333 | AJ74: 0.12899333 | AL74: Convenience Stores | AM74: 0.11379612 | AN74: 0.10599476 | AO74: 0.14608088 | AP74: 0.15523659 | AQ74: 0.088226117 | AR74: 0.14020173 | AS74: 0.1069938 | AT74: 0.067556084 | AU74: 0.13328514 | AV74: 0.12747929 | AW74: 0.12088894 | AX74: 0.094790814 | AY74: 0.081918451 | AZ74: 0.074954853 | BA74: 0.10033815 | BB74: 0.11271023 | BC74: 0.15877444 | BD74: 0.14353734 | BE74: 0.12812838 | BF74: 0.14950879 | BG74: 0.15312597 | BH74: 0.13808299 | BI74: 0.14588067 | BJ74: 0.1328374 | BK74: 0.12544852 | BL74: 0.12209668 | BM74: 0.11141901 | BN74: 0.13782462 | BO74: 0.11410144 | BP74: 0.13002953 | BQ74: 0.12359909 | BR74: 0.14228592 | BS74: 0.12406886 | BT74: 0.13527844 | BV74: Convenience Stores | BW74: CMI_Trend_38 | BX74: CMI_Trend_52 | BY74: CMI_Trend_60 | BZ74: CMI_Trend_38 | CA74: CMI_Trend_20 | CB74: CMI_Trend_46 | CC74: CMI_Trend_46 | CD74: CMI_Trend_38 | CE74: CMI_Trend_56 | CF74: CMI_Trend_56 | CG74: CMI_Trend_46 | CH74: CMI_Trend_38 | CI74: CMI_Trend_20 | CJ74: CMI_Trend_56 | CK74: CMI_Trend_38 | CL74: CMI_Trend_52 | CM74: CMI_Trend_25 | CN74: CMI_Trend_56 | CO74: CMI_Trend_25 | CP74: CMI_Trend_60 | CQ74: CMI_Trend_60 | CR74: CMI_Trend_56 | CS74: CMI_Trend_46 | CT74: CMI_Trend_60 | CU74: CMI_Trend_52 | CV74: CMI_Trend_25 | CW74: CMI_Trend_20 | CX74: CMI_Trend_25 | CY74: CMI_Trend_46 | CZ74: CMI_Trend_20 | DA74: CMI_Trend_56 | DB74: CMI_Trend_20 | DC74: CMI_Trend_20 | DD74: CMI_Trend_25
A75: 0.001 | B75: Specialty and Discount Stores | C75: 0.099270692 | D75: 0.090370692 | E75: 0.10387069 | F75: 0.091870692 | G75: 0.10307069 | H75: 0.10747069 | I75: 0.096370692 | J75: 0.11507069 | K75: 0.091770692 | L75: 0.085570692 | M75: 0.10817069 | N75: 0.10467069 | O75: 0.11447069 | P75: 0.092470692 | Q75: 0.089070692 | R75: 0.085070692 | S75: 0.11347069 | T75: 0.10707069 | U75: 0.11187069 | V75: 0.11397069 | W75: 0.092670692 | X75: 0.092270692 | Y75: 0.11437069 | Z75: 0.11017069 | AA75: 0.11417069 | AB75: 0.087270692 | AC75: 0.088570692 | AD75: 0.10177069 | AE75: 0.11347069 | AF75: 0.096370692 | AG75: 0.094370692 | AH75: 0.10277069 | AI75: 0.11027069 | AJ75: 0.11247069 | AL75: Specialty and Discount Stores | AM75: 0.099328905 | AN75: 0.091527536 | AO75: 0.13161366 | AP75: 0.14076937 | AQ75: 0.073758898 | AR75: 0.12573451 | AS75: 0.092526579 | AT75: 0.053088864 | AU75: 0.11881792 | AV75: 0.11301207 | AW75: 0.10642172 | AX75: 0.080323595 | AY75: 0.067451232 | AZ75: 0.060487634 | BA75: 0.085870932 | BB75: 0.098243015 | BC75: 0.14430722 | BD75: 0.12907012 | BE75: 0.11366116 | BF75: 0.13504157 | BG75: 0.13865875 | BH75: 0.12361577 | BI75: 0.13141345 | BJ75: 0.11837018 | BK75: 0.1109813 | BL75: 0.10762946 | BM75: 0.096951787 | BN75: 0.1233574 | BO75: 0.099634219 | BP75: 0.11556231 | BQ75: 0.10913187 | BR75: 0.1278187 | BS75: 0.10960164 | BT75: 0.12081122 | BV75: Specialty and Discount Stores | BW75: CMI_Trend_38 | BX75: CMI_Trend_46 | BY75: CMI_Trend_52 | BZ75: CMI_Trend_46 | CA75: CMI_Trend_20 | CB75: CMI_Trend_52 | CC75: CMI_Trend_38 | CD75: CMI_Trend_56 | CE75: CMI_Trend_20 | CF75: CMI_Trend_20 | CG75: CMI_Trend_52 | CH75: CMI_Trend_25 | CI75: CMI_Trend_46 | CJ75: CMI_Trend_25 | CK75: CMI_Trend_38 | CL75: CMI_Trend_46 | CM75: CMI_Trend_56 | CN75: CMI_Trend_56 | CO75: CMI_Trend_56 | CP75: CMI_Trend_20 | CQ75: CMI_Trend_38 | CR75: CMI_Trend_20 | CS75: CMI_Trend_60 | CT75: CMI_Trend_56 | CU75: CMI_Trend_25 | CV75: CMI_Trend_25 | CW75: CMI_Trend_25 | CX75: CMI_Trend_46 | CY75: CMI_Trend_60 | CZ75: CMI_Trend_60 | DA75: CMI_Trend_38 | DB75: CMI_Trend_25 | DC75: CMI_Trend_56 | DD75: CMI_Trend_52
B76: Department Stores | C76: 0.054825928 | D76: 0.050925928 | E76: 0.045325928 | F76: 0.058925928 | G76: 0.064325928 | H76: 0.060325928 | I76: 0.045725928 | J76: 0.051525928 | K76: 0.047225928 | L76: 0.048125928 | M76: 0.063725928 | N76: 0.059125928 | O76: 0.057325928 | P76: 0.064725928 | Q76: 0.061425928 | R76: 0.064625928 | S76: 0.061625928 | T76: 0.054425928 | U76: 0.057725928 | V76: 0.055125928 | W76: 0.063325928 | X76: 0.046025928 | Y76: 0.060325928 | Z76: 0.064425928 | AA76: 0.049725928 | AB76: 0.064425928 | AC76: 0.057525928 | AD76: 0.056125928 | AE76: 0.063925928 | AF76: 0.060725928 | AG76: 0.045925928 | AH76: 0.060025928 | AI76: 0.063225928 | AJ76: 0.046725928 | AL76: Department Stores | AM76: 0.082453358 | AN76: 0.074651989 | AO76: 0.11473811 | AP76: 0.12389382 | AQ76: 0.056883351 | AR76: 0.10885897 | AS76: 0.075651032 | AT76: 0.036213317 | AU76: 0.10194237 | AV76: 0.096136524 | AW76: 0.089546176 | AX76: 0.063448048 | AY76: 0.050575685 | AZ76: 0.043612087 | BA76: 0.068995385 | BB76: 0.081367468 | BC76: 0.12743168 | BD76: 0.11219457 | BE76: 0.09678561 | BF76: 0.11816602 | BG76: 0.1217832 | BH76: 0.10674023 | BI76: 0.1145379 | BJ76: 0.10149463 | BK76: 0.094105756 | BL76: 0.090753913 | BM76: 0.080076241 | BN76: 0.10648185 | BO76: 0.082758673 | BP76: 0.098686767 | BQ76: 0.092256324 | BR76: 0.11094316 | BS76: 0.092726092 | BT76: 0.10393567 | BV76: Department Stores | BW76: CMI_Trend_25 | BX76: CMI_Trend_60 | BY76: CMI_Trend_46 | BZ76: CMI_Trend_46 | CA76: CMI_Trend_52 | CB76: CMI_Trend_52 | CC76: CMI_Trend_46 | CD76: CMI_Trend_60 | CE76: CMI_Trend_25 | CF76: CMI_Trend_56 | CG76: CMI_Trend_56 | CH76: CMI_Trend_20 | CI76: CMI_Trend_46 | CJ76: CMI_Trend_38 | CK76: CMI_Trend_25 | CL76: CMI_Trend_25 | CM76: CMI_Trend_38 | CN76: CMI_Trend_46 | CO76: CMI_Trend_25 | CP76: CMI_Trend_25 | CQ76: CMI_Trend_56 | CR76: CMI_Trend_56 | CS76: CMI_Trend_52 | CT76: CMI_Trend_46 | CU76: CMI_Trend_38 | CV76: CMI_Trend_56 | CW76: CMI_Trend_56 | CX76: CMI_Trend_52 | CY76: CMI_Trend_60 | CZ76: CMI_Trend_52 | DA76: CMI_Trend_56 | DB76: CMI_Trend_38 | DC76: CMI_Trend_52 | DD76: CMI_Trend_25
B77: Pharmacies & Drugstores | C77: 0.091832589 | D77: 0.098632589 | E77: 0.094932589 | F77: 0.10403259 | G77: 0.092332589 | H77: 0.095032589 | I77: 0.087132589 | J77: 0.083632589 | K77: 0.077832589 | L77: 0.089032589 | M77: 0.082332589 | N77: 0.081932589 | O77: 0.098932589 | P77: 0.093732589 | Q77: 0.091732589 | R77: 0.085732589 | S77: 0.095732589 | T77: 0.078732589 | U77: 0.099732589 | V77: 0.10663259 | W77: 0.078832589 | X77: 0.10423259 | Y77: 0.10013259 | Z77: 0.099432589 | AA77: 0.096932589 | AB77: 0.084132589 | AC77: 0.095632589 | AD77: 0.10303259 | AE77: 0.098632589 | AF77: 0.081632589 | AG77: 0.10093259 | AH77: 0.090632589 | AI77: 0.089032589 | AJ77: 0.078132589 | AL77: Warehouse Clubs | AM77: 0.12195297 | AN77: 0.1141516 | AO77: 0.15423773 | AP77: 0.16339343 | AQ77: 0.096382964 | AR77: 0.14835858 | AS77: 0.11515065 | AT77: 0.075712931 | AU77: 0.14144198 | AV77: 0.13563614 | AW77: 0.12904579 | AX77: 0.10294766 | AY77: 0.090075298 | AZ77: 0.0831117 | BA77: 0.108495 | BB77: 0.12086708 | BC77: 0.16693129 | BD77: 0.15169418 | BE77: 0.13628522 | BF77: 0.15766563 | BG77: 0.16128282 | BH77: 0.14623984 | BI77: 0.15403752 | BJ77: 0.14099424 | BK77: 0.13360537 | BL77: 0.13025353 | BM77: 0.11957585 | BN77: 0.14598146 | BO77: 0.12225829 | BP77: 0.13818638 | BQ77: 0.13175594 | BR77: 0.15044277 | BS77: 0.13222571 | BT77: 0.14343529 | BV77: Warehouse Clubs | BW77: CMI_Trend_52 | BX77: CMI_Trend_56 | BY77: CMI_Trend_52 | BZ77: CMI_Trend_52 | CA77: CMI_Trend_20 | CB77: CMI_Trend_38 | CC77: CMI_Trend_56 | CD77: CMI_Trend_25 | CE77: CMI_Trend_56 | CF77: CMI_Trend_56 | CG77: CMI_Trend_52 | CH77: CMI_Trend_25 | CI77: CMI_Trend_52 | CJ77: CMI_Trend_38 | CK77: CMI_Trend_25 | CL77: CMI_Trend_25 | CM77: CMI_Trend_25 | CN77: CMI_Trend_20 | CO77: CMI_Trend_52 | CP77: CMI_Trend_20 | CQ77: CMI_Trend_20 | CR77: CMI_Trend_56 | CS77: CMI_Trend_25 | CT77: CMI_Trend_60 | CU77: CMI_Trend_46 | CV77: CMI_Trend_25 | CW77: CMI_Trend_46 | CX77: CMI_Trend_60 | CY77: CMI_Trend_60 | CZ77: CMI_Trend_20 | DA77: CMI_Trend_56 | DB77: CMI_Trend_25 | DC77: CMI_Trend_38 | DD77: CMI_Trend_52
B78: Warehouse Clubs | C78: 0.050294093 | D78: 0.058994093 | E78: 0.055494093 | F78: 0.042494093 | G78: 0.052494093 | H78: 0.059494093 | I78: 0.056394093 | J78: 0.052394093 | K78: 0.051194093 | L78: 0.053694093 | M78: 0.059194093 | N78: 0.050694093 | O78: 0.041194093 | P78: 0.046094093 | Q78: 0.057394093 | R78: 0.057794093 | S78: 0.054994093 | T78: 0.050094093 | U78: 0.044094093 | V78: 0.041294093 | W78: 0.045094093 | X78: 0.059894093 | Y78: 0.042694093 | Z78: 0.055594093 | AA78: 0.059194093 | AB78: 0.049894093 | AC78: 0.045594093 | AD78: 0.041494093 | AE78: 0.052294093 | AF78: 0.054594093 | AG78: 0.043394093 | AH78: 0.057494093 | AI78: 0.041194093 | AJ78: 0.059294093 | AL78: Pharmacies & Drugstores | AM78: 0.0919238 | AN78: 0.084122431 | AO78: 0.12420855 | AP78: 0.13336426 | AQ78: 0.066353793 | AR78: 0.11832941 | AS78: 0.085121474 | AT78: 0.04568376 | AU78: 0.11141281 | AV78: 0.10560697 | AW78: 0.099016618 | AX78: 0.07291849 | AY78: 0.060046127 | AZ78: 0.053082529 | BA78: 0.078465827 | BB78: 0.090837911 | BC78: 0.13690212 | BD78: 0.12166501 | BE78: 0.10625605 | BF78: 0.12763646 | BG78: 0.13125364 | BH78: 0.11621067 | BI78: 0.12400834 | BJ78: 0.11096507 | BK78: 0.1035762 | BL78: 0.10022436 | BM78: 0.089546683 | BN78: 0.11595229 | BO78: 0.092229115 | BP78: 0.10815721 | BQ78: 0.10172677 | BR78: 0.1204136 | BS78: 0.10219653 | BT78: 0.11340612 | BV78: Pharmacies & Drugstores | BW78: CMI_Trend_25 | BX78: CMI_Trend_56 | BY78: CMI_Trend_20 | BZ78: CMI_Trend_38 | CA78: CMI_Trend_60 | CB78: CMI_Trend_25 | CC78: CMI_Trend_20 | CD78: CMI_Trend_52 | CE78: CMI_Trend_38 | CF78: CMI_Trend_46 | CG78: CMI_Trend_52 | CH78: CMI_Trend_60 | CI78: CMI_Trend_52 | CJ78: CMI_Trend_20 | CK78: CMI_Trend_25 | CL78: CMI_Trend_25 | CM78: CMI_Trend_20 | CN78: CMI_Trend_46 | CO78: CMI_Trend_56 | CP78: CMI_Trend_25 | CQ78: CMI_Trend_60 | CR78: CMI_Trend_56 | CS78: CMI_Trend_60 | CT78: CMI_Trend_60 | CU78: CMI_Trend_52 | CV78: CMI_Trend_38 | CW78: CMI_Trend_25 | CX78: CMI_Trend_20 | CY78: CMI_Trend_52 | CZ78: CMI_Trend_56 | DA78: CMI_Trend_52 | DB78: CMI_Trend_52 | DC78: CMI_Trend_20 | DD78: CMI_Trend_56
B79: Multi-Plane Self-Scanning Kiosks | C79: 0.44083482 | D79: 0.44803482 | E79: 0.43433482 | F79: 0.43493482 | G79: 0.42823482 | H79: 0.45143482 | I79: 0.44613482 | J79: 0.43843482 | K79: 0.42793482 | L79: 0.44083482 | M79: 0.42483482 | N79: 0.45453482 | O79: 0.43493482 | P79: 0.43813482 | Q79: 0.43243482 | R79: 0.44223482 | S79: 0.43513482 | T79: 0.42883482 | U79: 0.42673482 | V79: 0.42833482 | W79: 0.44013482 | X79: 0.44833482 | Y79: 0.44923482 | Z79: 0.43033482 | AA79: 0.43843482 | AB79: 0.43253482 | AC79: 0.43223482 | AD79: 0.43803482 | AE79: 0.42783482 | AF79: 0.42853482 | AG79: 0.44003482 | AH79: 0.43083482 | AI79: 0.44713482 | AJ79: 0.43963482 | AL79: Multi-Plane Self-Scanning Kiosks | AM79: =SUMPRODUCT(AM80:AM85,C80:C85) -> 0.12248521 | AN79: =SUMPRODUCT(AN80:AN85,D80:D85) -> 0.1149121 | AO79: =SUMPRODUCT(AO80:AO85,E80:E85) -> 0.15485906 | AP79: =SUMPRODUCT(AP80:AP85,F80:F85) -> 0.16411457 | AQ79: =SUMPRODUCT(AQ80:AQ85,G80:G85) -> 0.096669917 | AR79: =SUMPRODUCT(AR80:AR85,H80:H85) -> 0.14871406 | AS79: =SUMPRODUCT(AS80:AS85,I80:I85) -> 0.11582947 | AT79: =SUMPRODUCT(AT80:AT85,J80:J85) -> 0.076128798 | ... BT79: =SUMPRODUCT(BT80:BT85,AJ80:AJ85) -> 0.14375105 | BV79: Multi-Plane Self-Scanning Kiosks | BW79: CMI_Trend_46 | BX79: CMI_Trend_20 | BY79: CMI_Trend_38 | BZ79: CMI_Trend_20 | CA79: CMI_Trend_52 | CB79: CMI_Trend_38 | CC79: CMI_Trend_25 | CD79: CMI_Trend_25 | CE79: CMI_Trend_38 | CF79: CMI_Trend_52 | CG79: CMI_Trend_20 | CH79: CMI_Trend_56 | CI79: CMI_Trend_20 | CJ79: CMI_Trend_56 | CK79: CMI_Trend_60 | CL79: CMI_Trend_38 | CM79: CMI_Trend_46 | CN79: CMI_Trend_46 | CO79: CMI_Trend_52 | CP79: CMI_Trend_56 | CQ79: CMI_Trend_38 | CR79: CMI_Trend_25 | CS79: CMI_Trend_20 | CT79: CMI_Trend_38 | CU79: CMI_Trend_25 | CV79: CMI_Trend_52 | CW79: CMI_Trend_52 | CX79: CMI_Trend_56 | CY79: CMI_Trend_56 | CZ79: CMI_Trend_52 | DA79: CMI_Trend_52 | DB79: CMI_Trend_20 | DC79: CMI_Trend_25 | DD79: CMI_Trend_52
B80: Supermarkets & Hypermarkets | C80: =1-SUM(C81:C85) -> 0.58460992 | D80: =1-SUM(D81:D85) -> 0.59550992 | E80: =1-SUM(E81:E85) -> 0.56130992 | F80: =1-SUM(F81:F85) -> 0.60880992 | G80: =1-SUM(G81:G85) -> 0.56170992 | H80: =1-SUM(H81:H85) -> 0.57410992 | I80: =1-SUM(I81:I85) -> 0.57570992 | J80: =1-SUM(J81:J85) -> 0.59700992 | ... AJ80: =1-SUM(AJ81:AJ85) -> 0.57050992 | AL80: Supermarkets & Hypermarkets | AM80: 0.12309537 | AN80: 0.11602918 | AO80: 0.15607065 | AP80: 0.16452018 | AQ80: 0.097037306 | AR80: 0.14892797 | AS80: 0.11599338 | AT80: 0.07694895 | AU80: 0.14264308 | AV80: 0.13680699 | AW80: 0.12985882 | AX80: 0.10373134 | AY80: 0.091488188 | AZ80: 0.084502773 | BA80: 0.10926277 | BB80: 0.12181143 | BC80: 0.16813624 | BD80: 0.15294604 | BE80: 0.1376965 | BF80: 0.15872788 | BG80: 0.16189852 | BH80: 0.14741479 | BI80: 0.15557604 | BJ80: 0.14154419 | BK80: 0.13445363 | BL80: 0.13127416 | BM80: 0.12121996 | BN80: 0.14752882 | BO80: 0.12308475 | BP80: 0.13893981 | BQ80: 0.13371316 | BR80: 0.15198584 | BS80: 0.13345701 | BT80: 0.14420045 | BV80: Supermarkets & Hypermarkets | BW80: CMI_Trend_20 | BX80: CMI_Trend_38 | BY80: CMI_Trend_56 | BZ80: CMI_Trend_38 | CA80: CMI_Trend_46 | CB80: CMI_Trend_25 | CC80: CMI_Trend_52 | CD80: CMI_Trend_46 | CE80: CMI_Trend_56 | CF80: CMI_Trend_56 | CG80: CMI_Trend_20 | CH80: CMI_Trend_56 | CI80: CMI_Trend_56 | CJ80: CMI_Trend_52 | CK80: CMI_Trend_20 | CL80: CMI_Trend_25 | CM80: CMI_Trend_20 | CN80: CMI_Trend_52 | CO80: CMI_Trend_46 | CP80: CMI_Trend_25 | CQ80: CMI_Trend_60 | CR80: CMI_Trend_56 | CS80: CMI_Trend_38 | CT80: CMI_Trend_25 | CU80: CMI_Trend_60 | CV80: CMI_Trend_20 | CW80: CMI_Trend_38 | CX80: CMI_Trend_38 | CY80: CMI_Trend_52 | CZ80: CMI_Trend_52 | DA80: CMI_Trend_60 | DB80: CMI_Trend_38 | DC80: CMI_Trend_60 | DD80: CMI_Trend_38
B81: Convenience Stores | C81: 0.12886886 | D81: 0.11436886 | E81: 0.12656886 | F81: 0.13856886 | G81: 0.14496886 | H81: 0.12936886 | I81: 0.13206886 | J81: 0.11346886 | K81: 0.12006886 | L81: 0.13646886 | M81: 0.14076886 | N81: 0.13196886 | O81: 0.13956886 | P81: 0.11466886 | Q81: 0.11866886 | R81: 0.13926886 | S81: 0.12136886 | T81: 0.12856886 | U81: 0.12696886 | V81: 0.13356886 | W81: 0.13246886 | X81: 0.12456886 | Y81: 0.11686886 | Z81: 0.14456886 | AA81: 0.14606886 | AB81: 0.12836886 | AC81: 0.13996886 | AD81: 0.14176886 | AE81: 0.13636886 | AF81: 0.14346886 | AG81: 0.12146886 | AH81: 0.11786886 | AI81: 0.11456886 | AJ81: 0.12666886 | AL81: Convenience Stores | AM81: 0.13037614 | AN81: 0.12330995 | AO81: 0.16335142 | AP81: 0.17180095 | AQ81: 0.10431808 | AR81: 0.15620874 | AS81: 0.12327415 | AT81: 0.08422972 | AU81: 0.14992385 | AV81: 0.14408776 | AW81: 0.13713959 | AX81: 0.11101211 | AY81: 0.098768959 | AZ81: 0.091783544 | BA81: 0.11654354 | BB81: 0.1290922 | BC81: 0.17541701 | BD81: 0.16022681 | BE81: 0.14497727 | BF81: 0.16600865 | BG81: 0.16917929 | BH81: 0.15469556 | BI81: 0.16285681 | BJ81: 0.14882497 | BK81: 0.1417344 | BL81: 0.13855493 | BM81: 0.12850073 | BN81: 0.15480959 | BO81: 0.13036552 | BP81: 0.14622058 | BQ81: 0.14099393 | BR81: 0.15926661 | BS81: 0.14073778 | BT81: 0.15148122 | BV81: Convenience Stores | BW81: CMI_Trend_60 | BX81: CMI_Trend_60 | BY81: CMI_Trend_60 | BZ81: CMI_Trend_60 | CA81: CMI_Trend_56 | CB81: CMI_Trend_20 | CC81: CMI_Trend_38 | CD81: CMI_Trend_60 | CE81: CMI_Trend_56 | CF81: CMI_Trend_25 | CG81: CMI_Trend_60 | CH81: CMI_Trend_38 | CI81: CMI_Trend_25 | CJ81: CMI_Trend_46 | CK81: CMI_Trend_52 | CL81: CMI_Trend_25 | CM81: CMI_Trend_60 | CN81: CMI_Trend_56 | CO81: CMI_Trend_20 | CP81: CMI_Trend_52 | CQ81: CMI_Trend_25 | CR81: CMI_Trend_56 | CS81: CMI_Trend_46 | CT81: CMI_Trend_52 | CU81: CMI_Trend_25 | CV81: CMI_Trend_56 | CW81: CMI_Trend_38 | CX81: CMI_Trend_52 | CY81: CMI_Trend_56 | CZ81: CMI_Trend_60 | DA81: CMI_Trend_20 | DB81: CMI_Trend_25 | DC81: CMI_Trend_52 | DD81: CMI_Trend_25
B82: Specialty and Discount Stores | C82: 0.095421162 | D82: 0.10652116 | E82: 0.10352116 | F82: 0.086021162 | G82: 0.092721162 | H82: 0.10342116 | I82: 0.089221162 | J82: 0.090221162 | K82: 0.10092116 | L82: 0.099921162 | M82: 0.089321162 | N82: 0.10792116 | O82: 0.099521162 | P82: 0.10762116 | Q82: 0.10082116 | R82: 0.096721162 | S82: 0.099721162 | T82: 0.092321162 | U82: 0.10562116 | V82: 0.080021162 | W82: 0.088121162 | X82: 0.090721162 | Y82: 0.10732116 | Z82: 0.099721162 | AA82: 0.082621162 | AB82: 0.091221162 | AC82: 0.086221162 | AD82: 0.087321162 | AE82: 0.10362116 | AF82: 0.086621162 | AG82: 0.098021162 | AH82: 0.11202116 | AI82: 0.10772116 | AJ82: 0.085821162 | AL82: Specialty and Discount Stores | AM82: 0.1149074 | AN82: 0.10784121 | AO82: 0.14788268 | AP82: 0.15633221 | AQ82: 0.088849335 | AR82: 0.14074 | AS82: 0.10780541 | AT82: 0.068760978 | AU82: 0.13445511 | AV82: 0.12861902 | AW82: 0.12167085 | AX82: 0.095543369 | AY82: 0.083300217 | AZ82: 0.076314802 | BA82: 0.1010748 | BB82: 0.11362346 | BC82: 0.15994827 | BD82: 0.14475807 | BE82: 0.12950853 | BF82: 0.15053991 | BG82: 0.15371055 | BH82: 0.13922681 | BI82: 0.14738807 | BJ82: 0.13335622 | BK82: 0.12626566 | BL82: 0.12308619 | BM82: 0.11303199 | BN82: 0.13934085 | BO82: 0.11489678 | BP82: 0.13075184 | BQ82: 0.12552519 | BR82: 0.14379787 | BS82: 0.12526904 | BT82: 0.13601248 | BV82: Specialty and Discount Stores | BW82: CMI_Trend_56 | BX82: CMI_Trend_56 | BY82: CMI_Trend_38 | BZ82: CMI_Trend_46 | CA82: CMI_Trend_52 | CB82: CMI_Trend_46 | CC82: CMI_Trend_38 | CD82: CMI_Trend_46 | CE82: CMI_Trend_38 | CF82: CMI_Trend_25 | CG82: CMI_Trend_38 | CH82: CMI_Trend_25 | CI82: CMI_Trend_25 | CJ82: CMI_Trend_20 | CK82: CMI_Trend_46 | CL82: CMI_Trend_56 | CM82: CMI_Trend_52 | CN82: CMI_Trend_52 | CO82: CMI_Trend_46 | CP82: CMI_Trend_60 | CQ82: CMI_Trend_38 | CR82: CMI_Trend_20 | CS82: CMI_Trend_52 | CT82: CMI_Trend_38 | CU82: CMI_Trend_46 | CV82: CMI_Trend_52 | CW82: CMI_Trend_56 | CX82: CMI_Trend_25 | CY82: CMI_Trend_56 | CZ82: CMI_Trend_56 | DA82: CMI_Trend_60 | DB82: CMI_Trend_25 | DC82: CMI_Trend_25 | DD82: CMI_Trend_46
B83: Department Stores | C83: 0.057605685 | D83: 0.057905685 | E83: 0.069905685 | F83: 0.050905685 | G83: 0.053605685 | H83: 0.051005685 | I83: 0.050905685 | J83: 0.069405685 | K83: 0.058905685 | L83: 0.053205685 | M83: 0.059105685 | N83: 0.066305685 | O83: 0.051005685 | P83: 0.069905685 | Q83: 0.050305685 | R83: 0.058305685 | S83: 0.065405685 | T83: 0.069805685 | U83: 0.061905685 | V83: 0.052405685 | W83: 0.055205685 | X83: 0.050905685 | Y83: 0.056005685 | Z83: 0.061405685 | AA83: 0.068005685 | AB83: 0.050705685 | AC83: 0.068605685 | AD83: 0.063505685 | AE83: 0.051105685 | AF83: 0.056905685 | AG83: 0.062005685 | AH83: 0.068205685 | AI83: 0.051205685 | AJ83: 0.056605685 | AL83: Department Stores | AM83: 0.10057223 | AN83: 0.093506035 | AO83: 0.1335475 | AP83: 0.14199704 | AQ83: 0.074514158 | AR83: 0.12640482 | AS83: 0.093470235 | AT83: 0.054425801 | AU83: 0.12011993 | AV83: 0.11428384 | AW83: 0.10733567 | AX83: 0.081208192 | AY83: 0.068965039 | AZ83: 0.061979624 | BA83: 0.086739624 | BB83: 0.099288283 | BC83: 0.14561309 | BD83: 0.13042289 | BE83: 0.11517335 | BF83: 0.13620473 | BG83: 0.13937537 | BH83: 0.12489164 | BI83: 0.13305289 | BJ83: 0.11902105 | BK83: 0.11193048 | BL83: 0.10875101 | BM83: 0.098696813 | BN83: 0.12500567 | BO83: 0.1005616 | BP83: 0.11641666 | BQ83: 0.11119001 | BR83: 0.12946269 | BS83: 0.11093386 | BT83: 0.1216773 | BV83: Department Stores | BW83: CMI_Trend_38 | BX83: CMI_Trend_46 | BY83: CMI_Trend_60 | BZ83: CMI_Trend_38 | CA83: CMI_Trend_60 | CB83: CMI_Trend_52 | CC83: CMI_Trend_38 | CD83: CMI_Trend_56 | CE83: CMI_Trend_38 | CF83: CMI_Trend_38 | CG83: CMI_Trend_46 | CH83: CMI_Trend_60 | CI83: CMI_Trend_60 | CJ83: CMI_Trend_52 | CK83: CMI_Trend_20 | CL83: CMI_Trend_60 | CM83: CMI_Trend_60 | CN83: CMI_Trend_38 | CO83: CMI_Trend_25 | CP83: CMI_Trend_25 | CQ83: CMI_Trend_52 | CR83: CMI_Trend_52 | CS83: CMI_Trend_52 | CT83: CMI_Trend_38 | CU83: CMI_Trend_38 | CV83: CMI_Trend_52 | CW83: CMI_Trend_52 | CX83: CMI_Trend_25 | CY83: CMI_Trend_20 | CZ83: CMI_Trend_56 | DA83: CMI_Trend_38 | DB83: CMI_Trend_20 | DC83: CMI_Trend_38 | DD83: CMI_Trend_38
B84: Pharmacies & Drugstores | C84: 0.085619226 | D84: 0.071419226 | E84: 0.080119226 | F84: 0.073419226 | G84: 0.092919226 | H84: 0.10041923 | I84: 0.10251923 | J84: 0.088019226 | K84: 0.098919226 | L84: 0.097919226 | M84: 0.071419226 | N84: 0.10001923 | O84: 0.070319226 | P84: 0.10151923 | Q84: 0.095319226 | R84: 0.084919226 | S84: 0.085519226 | T84: 0.073419226 | U84: 0.089419226 | V84: 0.082619226 | W84: 0.097719226 | X84: 0.096719226 | Y84: 0.076219226 | Z84: 0.097719226 | AA84: 0.10191923 | AB84: 0.073219226 | AC84: 0.073819226 | AD84: 0.083119226 | AE84: 0.097819226 | AF84: 0.088519226 | AG84: 0.076219226 | AH84: 0.082019226 | AI84: 0.077119226 | AJ84: 0.10181923 | AL84: Warehouse Clubs | AM84: 0.13770233 | AN84: 0.13063614 | AO84: 0.1706776 | AP84: 0.17912714 | AQ84: 0.11164426 | AR84: 0.16353492 | AS84: 0.13060034 | AT84: 0.091555903 | AU84: 0.15725004 | AV84: 0.15141394 | AW84: 0.14446577 | AX84: 0.11833829 | AY84: 0.10609514 | AZ84: 0.099109727 | BA84: 0.12386973 | BB84: 0.13641839 | BC84: 0.18274319 | BD84: 0.167553 | BE84: 0.15230346 | BF84: 0.17333483 | BG84: 0.17650548 | BH84: 0.16202174 | BI84: 0.170183 | BJ84: 0.15615115 | BK84: 0.14906058 | BL84: 0.14588112 | BM84: 0.13582692 | BN84: 0.16213577 | BO84: 0.1376917 | BP84: 0.15354677 | BQ84: 0.14832012 | BR84: 0.16659279 | BS84: 0.14806396 | BT84: 0.1588074 | BV84: Warehouse Clubs | BW84: CMI_Trend_25 | BX84: CMI_Trend_20 | BY84: CMI_Trend_56 | BZ84: CMI_Trend_38 | CA84: CMI_Trend_60 | CB84: CMI_Trend_52 | CC84: CMI_Trend_25 | CD84: CMI_Trend_46 | CE84: CMI_Trend_25 | CF84: CMI_Trend_20 | CG84: CMI_Trend_20 | CH84: CMI_Trend_38 | CI84: CMI_Trend_25 | CJ84: CMI_Trend_20 | CK84: CMI_Trend_25 | CL84: CMI_Trend_52 | CM84: CMI_Trend_46 | CN84: CMI_Trend_46 | CO84: CMI_Trend_56 | CP84: CMI_Trend_38 | CQ84: CMI_Trend_60 | CR84: CMI_Trend_52 | CS84: CMI_Trend_60 | CT84: CMI_Trend_38 | CU84: CMI_Trend_20 | CV84: CMI_Trend_46 | CW84: CMI_Trend_20 | CX84: CMI_Trend_60 | CY84: CMI_Trend_46 | CZ84: CMI_Trend_20 | DA84: CMI_Trend_46 | DB84: CMI_Trend_46 | DC84: CMI_Trend_46 | DD84: CMI_Trend_46
B85: Warehouse Clubs | C85: 0.047875142 | D85: 0.054275142 | E85: 0.058575142 | F85: 0.042275142 | G85: 0.054075142 | H85: 0.041675142 | I85: 0.049575142 | J85: 0.041875142 | K85: 0.050375142 | L85: 0.050975142 | M85: 0.052975142 | N85: 0.041275142 | O85: 0.052575142 | P85: 0.051975142 | Q85: 0.053375142 | R85: 0.055075142 | S85: 0.057075142 | T85: 0.040875142 | U85: 0.051275142 | V85: 0.040575142 | W85: 0.047075142 | X85: 0.055975142 | Y85: 0.059975142 | Z85: 0.040875142 | AA85: 0.048175142 | AB85: 0.055375142 | AC85: 0.059375142 | AD85: 0.056275142 | AE85: 0.058275142 | AF85: 0.058075142 | AG85: 0.054575142 | AH85: 0.053775142 | AI85: 0.050775142 | AJ85: 0.058575142 | AL85: Pharmacies & Drugstores | AM85: 0.10805013 | AN85: 0.10098394 | AO85: 0.1410254 | AP85: 0.14947494 | AQ85: 0.081992059 | AR85: 0.13388272 | AS85: 0.10094814 | AT85: 0.061903702 | AU85: 0.12759783 | AV85: 0.12176174 | AW85: 0.11481357 | AX85: 0.088686093 | AY85: 0.076442941 | AZ85: 0.069457526 | BA85: 0.094217525 | BB85: 0.10676618 | BC85: 0.15309099 | BD85: 0.1379008 | BE85: 0.12265125 | BF85: 0.14368263 | BG85: 0.14685328 | BH85: 0.13236954 | BI85: 0.1405308 | BJ85: 0.12649895 | BK85: 0.11940838 | BL85: 0.11622892 | BM85: 0.10617471 | BN85: 0.13248357 | BO85: 0.1080395 | BP85: 0.12389456 | BQ85: 0.11866792 | BR85: 0.13694059 | BS85: 0.11841176 | BT85: 0.1291552 | BV85: Pharmacies & Drugstores | BW85: CMI_Trend_52 | BX85: CMI_Trend_38 | BY85: CMI_Trend_38 | BZ85: CMI_Trend_20 | CA85: CMI_Trend_25 | CB85: CMI_Trend_46 | CC85: CMI_Trend_38 | CD85: CMI_Trend_60 | CE85: CMI_Trend_46 | CF85: CMI_Trend_38 | CG85: CMI_Trend_25 | CH85: CMI_Trend_38 | CI85: CMI_Trend_38 | CJ85: CMI_Trend_52 | CK85: CMI_Trend_25 | CL85: CMI_Trend_60 | CM85: CMI_Trend_25 | CN85: CMI_Trend_52 | CO85: CMI_Trend_52 | CP85: CMI_Trend_56 | CQ85: CMI_Trend_25 | CR85: CMI_Trend_25 | CS85: CMI_Trend_46 | CT85: CMI_Trend_56 | CU85: CMI_Trend_52 | CV85: CMI_Trend_25 | CW85: CMI_Trend_38 | CX85: CMI_Trend_20 | CY85: CMI_Trend_56 | CZ85: CMI_Trend_20 | DA85: CMI_Trend_46 | DB85: CMI_Trend_52 | DC85: CMI_Trend_56 | DD85: CMI_Trend_25
B86: Presentation Self-Scanning Kiosks | C86: 0.18116663 | D86: 0.18146663 | E86: 0.17306663 | F86: 0.18446663 | G86: 0.18146663 | H86: 0.16936663 | I86: 0.17976663 | J86: 0.16506663 | K86: 0.17306663 | L86: 0.17046663 | M86: 0.18876663 | N86: 0.18876663 | O86: 0.18816663 | P86: 0.17126663 | Q86: 0.18566663 | R86: 0.17076663 | S86: 0.19826663 | T86: 0.18076663 | U86: 0.17196663 | V86: 0.17856663 | W86: 0.18046663 | X86: 0.17696663 | Y86: 0.18596663 | Z86: 0.18556663 | AA86: 0.17396663 | AB86: 0.18976663 | AC86: 0.17506663 | AD86: 0.16556663 | AE86: 0.17006663 | AF86: 0.18516663 | AG86: 0.18286663 | AH86: 0.18116663 | AI86: 0.18296663 | AJ86: 0.17836663 | AL86: Presentation Self-Scanning Kiosks | AM86: =SUMPRODUCT(AM87:AM92,C87:C92) -> 0.1148029 | AN86: =SUMPRODUCT(AN87:AN92,D87:D92) -> 0.10722978 | AO86: =SUMPRODUCT(AO87:AO92,E87:E92) -> 0.14717675 | AP86: =SUMPRODUCT(AP87:AP92,F87:F92) -> 0.15643225 | AQ86: =SUMPRODUCT(AQ87:AQ92,G87:G92) -> 0.088987601 | AR86: =SUMPRODUCT(AR87:AR92,H87:H92) -> 0.14103174 | AS86: =SUMPRODUCT(AS87:AS92,I87:I92) -> 0.10814716 | AT86: =SUMPRODUCT(AT87:AT92,J87:J92) -> 0.068446482 | ... BT86: =SUMPRODUCT(BT87:BT92,AJ87:AJ92) -> 0.13606873 | BV86: Presentation Self-Scanning Kiosks | BW86: CMI_Trend_20 | BX86: CMI_Trend_56 | BY86: CMI_Trend_60 | BZ86: CMI_Trend_38 | CA86: CMI_Trend_56 | CB86: CMI_Trend_25 | CC86: CMI_Trend_52 | CD86: CMI_Trend_20 | CE86: CMI_Trend_25 | CF86: CMI_Trend_52 | CG86: CMI_Trend_56 | CH86: CMI_Trend_25 | CI86: CMI_Trend_52 | CJ86: CMI_Trend_25 | CK86: CMI_Trend_38 | CL86: CMI_Trend_56 | CM86: CMI_Trend_20 | CN86: CMI_Trend_38 | CO86: CMI_Trend_52 | CP86: CMI_Trend_38 | CQ86: CMI_Trend_25 | CR86: CMI_Trend_25 | CS86: CMI_Trend_20 | CT86: CMI_Trend_52 | CU86: CMI_Trend_20 | CV86: CMI_Trend_60 | CW86: CMI_Trend_46 | CX86: CMI_Trend_38 | CY86: CMI_Trend_25 | CZ86: CMI_Trend_60 | DA86: CMI_Trend_46 | DB86: CMI_Trend_20 | DC86: CMI_Trend_46 | DD86: CMI_Trend_56
B87: Supermarkets & Hypermarkets | C87: =1-SUM(C88:C92) -> 0.58209351 | D87: =1-SUM(D88:D92) -> 0.58069351 | E87: =1-SUM(E88:E92) -> 0.53889351 | F87: =1-SUM(F88:F92) -> 0.59169351 | G87: =1-SUM(G88:G92) -> 0.60289351 | H87: =1-SUM(H88:H92) -> 0.58139351 | I87: =1-SUM(I88:I92) -> 0.54389351 | J87: =1-SUM(J88:J92) -> 0.58909351 | ... AJ87: =1-SUM(AJ88:AJ92) -> 0.58539351 | AL87: Supermarkets & Hypermarkets | AM87: 0.11555587 | AN87: 0.1078507 | AO87: 0.1482299 | AP87: 0.15678311 | AQ87: 0.08934247 | AR87: 0.14209079 | AS87: 0.10874452 | AT87: 0.068916041 | AU87: 0.13482009 | AV87: 0.12983689 | AW87: 0.12208545 | AX87: 0.096610474 | AY87: 0.084119293 | AZ87: 0.076475481 | BA87: 0.10174478 | BB87: 0.1140161 | BC87: 0.16032402 | BD87: 0.14518806 | BE87: 0.13054594 | BF87: 0.15153703 | BG87: 0.15510015 | BH87: 0.13989666 | BI87: 0.14795133 | BJ87: 0.13452394 | BK87: 0.12706759 | BL87: 0.12309279 | BM87: 0.11334058 | BN87: 0.13982884 | BO87: 0.11640053 | BP87: 0.13128602 | BQ87: 0.12559496 | BR87: 0.14379533 | BS87: 0.12584931 | BT87: 0.13685002 | BV87: Supermarkets & Hypermarkets | BW87: CMI_Trend_46 | BX87: CMI_Trend_60 | BY87: CMI_Trend_20 | BZ87: CMI_Trend_56 | CA87: CMI_Trend_25 | CB87: CMI_Trend_20 | CC87: CMI_Trend_38 | CD87: CMI_Trend_20 | CE87: CMI_Trend_52 | CF87: CMI_Trend_25 | CG87: CMI_Trend_25 | CH87: CMI_Trend_20 | CI87: CMI_Trend_38 | CJ87: CMI_Trend_56 | CK87: CMI_Trend_25 | CL87: CMI_Trend_25 | CM87: CMI_Trend_52 | CN87: CMI_Trend_25 | CO87: CMI_Trend_52 | CP87: CMI_Trend_46 | CQ87: CMI_Trend_52 | CR87: CMI_Trend_60 | CS87: CMI_Trend_46 | CT87: CMI_Trend_25 | CU87: CMI_Trend_46 | CV87: CMI_Trend_56 | CW87: CMI_Trend_60 | CX87: CMI_Trend_56 | CY87: CMI_Trend_46 | CZ87: CMI_Trend_25 | DA87: CMI_Trend_20 | DB87: CMI_Trend_25 | DC87: CMI_Trend_25 | DD87: CMI_Trend_52
B88: Convenience Stores | C88: 0.11549399 | D88: 0.10689399 | E88: 0.11169399 | F88: 0.13049399 | G88: 0.12639399 | H88: 0.10659399 | I88: 0.13129399 | J88: 0.11229399 | K88: 0.11829399 | L88: 0.13049399 | M88: 0.10829399 | N88: 0.10569399 | O88: 0.10019399 | P88: 0.10239399 | Q88: 0.11919399 | R88: 0.11249399 | S88: 0.11169399 | T88: 0.11039399 | U88: 0.11019399 | V88: 0.11929399 | W88: 0.10509399 | X88: 0.11399399 | Y88: 0.11029399 | Z88: 0.11819399 | AA88: 0.10459399 | AB88: 0.13119399 | AC88: 0.12119399 | AD88: 0.12469399 | AE88: 0.10659399 | AF88: 0.10169399 | AG88: 0.10009399 | AH88: 0.11139399 | AI88: 0.10099399 | AJ88: 0.10859399 | AL88: Convenience Stores | AM88: 0.12398413 | AN88: 0.11627896 | AO88: 0.15665816 | AP88: 0.16521137 | AQ88: 0.097770731 | AR88: 0.15051905 | AS88: 0.11717278 | AT88: 0.077344302 | AU88: 0.14324835 | AV88: 0.13826515 | AW88: 0.13051371 | AX88: 0.10503873 | AY88: 0.092547554 | AZ88: 0.084903741 | BA88: 0.11017305 | BB88: 0.12244436 | BC88: 0.16875228 | BD88: 0.15361632 | BE88: 0.1389742 | BF88: 0.15996529 | BG88: 0.16352841 | BH88: 0.14832492 | BI88: 0.15637959 | BJ88: 0.1429522 | BK88: 0.13549585 | BL88: 0.13152105 | BM88: 0.12176884 | BN88: 0.1482571 | BO88: 0.12482879 | BP88: 0.13971428 | BQ88: 0.13402322 | BR88: 0.15222359 | BS88: 0.13427757 | BT88: 0.14527828 | BV88: Convenience Stores | BW88: CMI_Trend_60 | BX88: CMI_Trend_38 | BY88: CMI_Trend_56 | BZ88: CMI_Trend_20 | CA88: CMI_Trend_60 | CB88: CMI_Trend_38 | CC88: CMI_Trend_20 | CD88: CMI_Trend_20 | CE88: CMI_Trend_60 | CF88: CMI_Trend_46 | CG88: CMI_Trend_25 | CH88: CMI_Trend_60 | CI88: CMI_Trend_25 | CJ88: CMI_Trend_60 | CK88: CMI_Trend_52 | CL88: CMI_Trend_46 | CM88: CMI_Trend_38 | CN88: CMI_Trend_52 | CO88: CMI_Trend_56 | CP88: CMI_Trend_52 | CQ88: CMI_Trend_56 | CR88: CMI_Trend_60 | CS88: CMI_Trend_20 | CT88: CMI_Trend_20 | CU88: CMI_Trend_56 | CV88: CMI_Trend_52 | CW88: CMI_Trend_46 | CX88: CMI_Trend_38 | CY88: CMI_Trend_20 | CZ88: CMI_Trend_38 | DA88: CMI_Trend_52 | DB88: CMI_Trend_56 | DC88: CMI_Trend_20 | DD88: CMI_Trend_46
B89: Specialty and Discount Stores | C89: 0.10324797 | D89: 0.10644797 | E89: 0.11384797 | F89: 0.088047974 | G89: 0.089447974 | H89: 0.10234797 | I89: 0.094147974 | J89: 0.093847974 | K89: 0.10154797 | L89: 0.11254797 | M89: 0.089847974 | N89: 0.087347974 | O89: 0.10774797 | P89: 0.10054797 | Q89: 0.11714797 | R89: 0.10294797 | S89: 0.096647974 | T89: 0.11214797 | U89: 0.092747974 | V89: 0.10764797 | W89: 0.090147974 | X89: 0.11474797 | Y89: 0.10274797 | Z89: 0.10384797 | AA89: 0.088847974 | AB89: 0.11244797 | AC89: 0.11324797 | AD89: 0.11394797 | AE89: 0.11994797 | AF89: 0.092947974 | AG89: 0.096247974 | AH89: 0.093447974 | AI89: 0.099847974 | AJ89: 0.099147974 | AL89: Specialty and Discount Stores | AM89: 0.10618848 | AN89: 0.098483303 | AO89: 0.13886251 | AP89: 0.14741572 | AQ89: 0.079975075 | AR89: 0.1327234 | AS89: 0.099377128 | AT89: 0.059548645 | AU89: 0.1254527 | AV89: 0.12046949 | AW89: 0.11271805 | AX89: 0.087243078 | AY89: 0.074751897 | AZ89: 0.067108085 | BA89: 0.092377389 | BB89: 0.10464871 | BC89: 0.15095662 | BD89: 0.13582067 | BE89: 0.12117855 | BF89: 0.14216963 | BG89: 0.14573275 | BH89: 0.13052926 | BI89: 0.13858394 | BJ89: 0.12515654 | BK89: 0.1177002 | BL89: 0.11372539 | BM89: 0.10397318 | BN89: 0.13046144 | BO89: 0.10703313 | BP89: 0.12191862 | BQ89: 0.11622757 | BR89: 0.13442793 | BS89: 0.11648191 | BT89: 0.12748263 | BV89: Specialty and Discount Stores | BW89: CMI_Trend_25 | BX89: CMI_Trend_46 | BY89: CMI_Trend_46 | BZ89: CMI_Trend_60 | CA89: CMI_Trend_46 | CB89: CMI_Trend_38 | CC89: CMI_Trend_38 | CD89: CMI_Trend_60 | CE89: CMI_Trend_60 | CF89: CMI_Trend_20 | CG89: CMI_Trend_20 | CH89: CMI_Trend_38 | CI89: CMI_Trend_56 | CJ89: CMI_Trend_46 | CK89: CMI_Trend_52 | CL89: CMI_Trend_25 | CM89: CMI_Trend_46 | CN89: CMI_Trend_56 | CO89: CMI_Trend_56 | CP89: CMI_Trend_38 | CQ89: CMI_Trend_60 | CR89: CMI_Trend_60 | CS89: CMI_Trend_20 | CT89: CMI_Trend_20 | CU89: CMI_Trend_60 | CV89: CMI_Trend_38 | CW89: CMI_Trend_52 | CX89: CMI_Trend_56 | CY89: CMI_Trend_52 | CZ89: CMI_Trend_25 | DA89: CMI_Trend_60 | DB89: CMI_Trend_46 | DC89: CMI_Trend_60 | DD89: CMI_Trend_60
A90: 0.001 | B90: Department Stores | C90: 0.059361207 | D90: 0.050061207 | E90: 0.068561207 | F90: 0.056761207 | G90: 0.053161207 | H90: 0.065661207 | I90: 0.064661207 | J90: 0.053761207 | K90: 0.056561207 | L90: 0.069661207 | M90: 0.050561207 | N90: 0.069461207 | O90: 0.068861207 | P90: 0.062661207 | Q90: 0.058561207 | R90: 0.065461207 | S90: 0.061261207 | T90: 0.067061207 | U90: 0.069761207 | V90: 0.052861207 | W90: 0.068461207 | X90: 0.050861207 | Y90: 0.061961207 | Z90: 0.059261207 | AA90: 0.053461207 | AB90: 0.051761207 | AC90: 0.054761207 | AD90: 0.051461207 | AE90: 0.063661207 | AF90: 0.050561207 | AG90: 0.054961207 | AH90: 0.068761207 | AI90: 0.050261207 | AJ90: 0.064061207 | AL90: Department Stores | AM90: 0.09182333 | AN90: 0.084118154 | AO90: 0.12449736 | AP90: 0.13305057 | AQ90: 0.065609926 | AR90: 0.11835825 | AS90: 0.085011979 | AT90: 0.045183497 | AU90: 0.11108755 | AV90: 0.10610434 | AW90: 0.098352904 | AX90: 0.07287793 | AY90: 0.060386749 | AZ90: 0.052742937 | BA90: 0.07801224 | BB90: 0.090283559 | BC90: 0.13659147 | BD90: 0.12145552 | BE90: 0.1068134 | BF90: 0.12780449 | BG90: 0.1313676 | BH90: 0.11616411 | BI90: 0.12421879 | BJ90: 0.1107914 | BK90: 0.10333505 | BL90: 0.099360244 | BM90: 0.089608034 | BN90: 0.11609629 | BO90: 0.092667983 | BP90: 0.10755348 | BQ90: 0.10186242 | BR90: 0.12006278 | BS90: 0.10211676 | BT90: 0.11311748 | BV90: Department Stores | BW90: CMI_Trend_60 | BX90: CMI_Trend_20 | BY90: CMI_Trend_60 | BZ90: CMI_Trend_38 | CA90: CMI_Trend_20 | CB90: CMI_Trend_25 | CC90: CMI_Trend_20 | CD90: CMI_Trend_38 | CE90: CMI_Trend_46 | CF90: CMI_Trend_52 | CG90: CMI_Trend_52 | CH90: CMI_Trend_46 | CI90: CMI_Trend_52 | CJ90: CMI_Trend_52 | CK90: CMI_Trend_46 | CL90: CMI_Trend_60 | CM90: CMI_Trend_38 | CN90: CMI_Trend_60 | CO90: CMI_Trend_38 | CP90: CMI_Trend_56 | CQ90: CMI_Trend_52 | CR90: CMI_Trend_38 | CS90: CMI_Trend_56 | CT90: CMI_Trend_46 | CU90: CMI_Trend_20 | CV90: CMI_Trend_20 | CW90: CMI_Trend_60 | CX90: CMI_Trend_25 | CY90: CMI_Trend_20 | CZ90: CMI_Trend_52 | DA90: CMI_Trend_38 | DB90: CMI_Trend_38 | DC90: CMI_Trend_56 | DD90: CMI_Trend_38
B91: Pharmacies & Drugstores | C91: 0.091787588 | D91: 0.10048759 | E91: 0.10728759 | F91: 0.090487588 | G91: 0.086687588 | H91: 0.091187588 | I91: 0.10718759 | J91: 0.10028759 | K91: 0.10678759 | L91: 0.076787588 | M91: 0.080687588 | N91: 0.088287588 | O91: 0.094687588 | P91: 0.10878759 | Q91: 0.10188759 | R91: 0.10628759 | S91: 0.084487588 | T91: 0.096987588 | U91: 0.079087588 | V91: 0.094787588 | W91: 0.088187588 | X91: 0.089887588 | Y91: 0.081287588 | Z91: 0.086287588 | AA91: 0.089787588 | AB91: 0.10738759 | AC91: 0.085987588 | AD91: 0.094387588 | AE91: 0.079787588 | AF91: 0.091887588 | AG91: 0.093187588 | AH91: 0.10698759 | AI91: 0.081787588 | AJ91: 0.096487588 | AL91: Warehouse Clubs | AM91: 0.13140244 | AN91: 0.12369726 | AO91: 0.16407647 | AP91: 0.17262968 | AQ91: 0.10518903 | AR91: 0.15793736 | AS91: 0.12459109 | AT91: 0.084762604 | AU91: 0.15066666 | AV91: 0.14568345 | AW91: 0.13793201 | AX91: 0.11245704 | AY91: 0.099965857 | AZ91: 0.092322044 | BA91: 0.11759135 | BB91: 0.12986267 | BC91: 0.17617058 | BD91: 0.16103462 | BE91: 0.14639251 | BF91: 0.16738359 | BG91: 0.17094671 | BH91: 0.15574322 | BI91: 0.1637979 | BJ91: 0.1503705 | BK91: 0.14291416 | BL91: 0.13893935 | BM91: 0.12918714 | BN91: 0.1556754 | BO91: 0.13224709 | BP91: 0.14713258 | BQ91: 0.14144153 | BR91: 0.15964189 | BS91: 0.14169587 | BT91: 0.15269659 | BV91: Warehouse Clubs | BW91: CMI_Trend_20 | BX91: CMI_Trend_56 | BY91: CMI_Trend_52 | BZ91: CMI_Trend_46 | CA91: CMI_Trend_25 | CB91: CMI_Trend_38 | CC91: CMI_Trend_38 | CD91: CMI_Trend_25 | CE91: CMI_Trend_60 | CF91: CMI_Trend_46 | CG91: CMI_Trend_56 | CH91: CMI_Trend_52 | CI91: CMI_Trend_25 | CJ91: CMI_Trend_60 | CK91: CMI_Trend_56 | CL91: CMI_Trend_38 | CM91: CMI_Trend_56 | CN91: CMI_Trend_25 | CO91: CMI_Trend_52 | CP91: CMI_Trend_38 | CQ91: CMI_Trend_60 | CR91: CMI_Trend_46 | CS91: CMI_Trend_20 | CT91: CMI_Trend_60 | CU91: CMI_Trend_60 | CV91: CMI_Trend_60 | CW91: CMI_Trend_25 | CX91: CMI_Trend_38 | CY91: CMI_Trend_46 | CZ91: CMI_Trend_38 | DA91: CMI_Trend_20 | DB91: CMI_Trend_56 | DC91: CMI_Trend_52 | DD91: CMI_Trend_38
B92: Warehouse Clubs | C92: 0.048015731 | D92: 0.055415731 | E92: 0.059715731 | F92: 0.042515731 | G92: 0.041415731 | H92: 0.052815731 | I92: 0.058815731 | J92: 0.050715731 | K92: 0.050515731 | L92: 0.040615731 | M92: 0.050715731 | N92: 0.057315731 | O92: 0.043315731 | P92: 0.043715731 | Q92: 0.047815731 | R92: 0.040615731 | S92: 0.048115731 | T92: 0.040815731 | U92: 0.059015731 | V92: 0.059815731 | W92: 0.058415731 | X92: 0.040515731 | Y92: 0.054915731 | Z92: 0.058515731 | AA92: 0.052515731 | AB92: 0.044415731 | AC92: 0.052115731 | AD92: 0.058815731 | AE92: 0.058515731 | AF92: 0.047615731 | AG92: 0.041815731 | AH92: 0.049215731 | AI92: 0.055615731 | AJ92: 0.046315731 | AL92: Pharmacies & Drugstores | AM92: 0.098791561 | AN92: 0.091086385 | AO92: 0.13146559 | AP92: 0.1400188 | AQ92: 0.072578157 | AR92: 0.12532648 | AS92: 0.09198021 | AT92: 0.052151728 | AU92: 0.11805578 | AV92: 0.11307257 | AW92: 0.10532114 | AX92: 0.079846161 | AY92: 0.06735498 | AZ92: 0.059711168 | BA92: 0.084980471 | BB92: 0.09725179 | BC92: 0.1435597 | BD92: 0.12842375 | BE92: 0.11378163 | BF92: 0.13477272 | BG92: 0.13833583 | BH92: 0.12313234 | BI92: 0.13118702 | BJ92: 0.11775963 | BK92: 0.11030328 | BL92: 0.10632847 | BM92: 0.096576265 | BN92: 0.12306453 | BO92: 0.099636214 | BP92: 0.11452171 | BQ92: 0.10883065 | BR92: 0.12703101 | BS92: 0.10908499 | BT92: 0.12008571 | BV92: Pharmacies & Drugstores | BW92: CMI_Trend_52 | BX92: CMI_Trend_52 | BY92: CMI_Trend_20 | BZ92: CMI_Trend_60 | CA92: CMI_Trend_56 | CB92: CMI_Trend_38 | CC92: CMI_Trend_56 | CD92: CMI_Trend_46 | CE92: CMI_Trend_25 | CF92: CMI_Trend_56 | CG92: CMI_Trend_60 | CH92: CMI_Trend_46 | CI92: CMI_Trend_52 | CJ92: CMI_Trend_52 | CK92: CMI_Trend_52 | CL92: CMI_Trend_20 | CM92: CMI_Trend_52 | CN92: CMI_Trend_60 | CO92: CMI_Trend_25 | CP92: CMI_Trend_38 | CQ92: CMI_Trend_60 | CR92: CMI_Trend_60 | CS92: CMI_Trend_25 | CT92: CMI_Trend_46 | CU92: CMI_Trend_20 | CV92: CMI_Trend_25 | CW92: CMI_Trend_52 | CX92: CMI_Trend_60 | CY92: CMI_Trend_46 | CZ92: CMI_Trend_60 | DA92: CMI_Trend_60 | DB92: CMI_Trend_25 | DC92: CMI_Trend_38 | DD92: CMI_Trend_52
B93: Mobile Self-Scanning Solutions | C93: 0.1323668 | D93: 0.1188668 | E93: 0.1272668 | F93: 0.1235668 | G93: 0.1482668 | H93: 0.1196668 | I93: 0.1328668 | J93: 0.1476668 | K93: 0.1248668 | L93: 0.1178668 | M93: 0.1213668 | N93: 0.1403668 | O93: 0.1279668 | P93: 0.1419668 | Q93: 0.1352668 | R93: 0.1433668 | S93: 0.1260668 | T93: 0.1344668 | U93: 0.1480668 | V93: 0.1290668 | W93: 0.1207668 | X93: 0.1488668 | Y93: 0.1469668 | Z93: 0.1304668 | AA93: 0.1189668 | AB93: 0.1219668 | AC93: 0.1422668 | AD93: 0.1362668 | AE93: 0.1334668 | AF93: 0.1399668 | AG93: 0.1200668 | AH93: 0.1444668 | AI93: 0.1319668 | AJ93: 0.1225668 | AL93: Mobile Self-Scanning Solutions | AM93: =AM94*C94+AM101*C101+AM108*C108 -> 0.17203577 | AN93: =AN94*D94+AN101*D101+AN108*D108 -> 0.16413758 | AO93: =AO94*E94+AO101*E101+AO108*E108 -> 0.20472979 | AP93: =AP94*F94+AP101*F101+AP108*F108 -> 0.21378262 | AQ93: =AQ94*G94+AQ101*G101+AQ108*G108 -> 0.14568071 | AR93: =AR94*H94+AR101*H101+AR108*H108 -> 0.19819252 | AS93: =AS94*I94+AS101*I101+AS108*I108 -> 0.16541887 | AT93: =AT94*J94+AT101*J101+AT108*J108 -> 0.12634974 | ... BT93: =BT94*AJ94+BT101*AJ101+BT108*AJ108 -> 0.1935505 | BV93: Mobile Self-Scanning Solutions | BW93: CMI_Trend_56 | BX93: CMI_Trend_60 | BY93: CMI_Trend_20 | BZ93: CMI_Trend_46 | CA93: CMI_Trend_20 | CB93: CMI_Trend_38 | CC93: CMI_Trend_38 | CD93: CMI_Trend_20 | CE93: CMI_Trend_56 | CF93: CMI_Trend_52 | CG93: CMI_Trend_38 | CH93: CMI_Trend_25 | CI93: CMI_Trend_25 | CJ93: CMI_Trend_38 | CK93: CMI_Trend_46 | CL93: CMI_Trend_46 | CM93: CMI_Trend_20 | CN93: CMI_Trend_56 | CO93: CMI_Trend_20 | CP93: CMI_Trend_60 | CQ93: CMI_Trend_46 | CR93: CMI_Trend_46 | CS93: CMI_Trend_25 | CT93: CMI_Trend_56 | CU93: CMI_Trend_52 | CV93: CMI_Trend_60 | CW93: CMI_Trend_38 | CX93: CMI_Trend_38 | CY93: CMI_Trend_46 | CZ93: CMI_Trend_52 | DA93: CMI_Trend_46 | DB93: CMI_Trend_56 | DC93: CMI_Trend_56 | DD93: CMI_Trend_25
B94: Dedicated Mobile Self-Scanning Devices | C94: =1-SUM(C101,C108) -> 0.50546101 | D94: =1-SUM(D101,D108) -> 0.50926101 | E94: =1-SUM(E101,E108) -> 0.49956101 | F94: =1-SUM(F101,F108) -> 0.50276101 | G94: =1-SUM(G101,G108) -> 0.52476101 | H94: =1-SUM(H101,H108) -> 0.50326101 | I94: =1-SUM(I101,I108) -> 0.50846101 | J94: =1-SUM(J101,J108) -> 0.48666101 | ... AJ94: =1-SUM(AJ101,AJ108) -> 0.49236101 | AL94: Dedicated Mobile Self-Scanning Devices | AM94: =SUMPRODUCT(AM95:AM100,C95:C100) -> 0.15546195 | AN94: =SUMPRODUCT(AN95:AN100,D95:D100) -> 0.14788884 | AO94: =SUMPRODUCT(AO95:AO100,E95:E100) -> 0.1878358 | AP94: =SUMPRODUCT(AP95:AP100,F95:F100) -> 0.19709131 | AQ94: =SUMPRODUCT(AQ95:AQ100,G95:G100) -> 0.12964666 | AR94: =SUMPRODUCT(AR95:AR100,H95:H100) -> 0.1816908 | AS94: =SUMPRODUCT(AS95:AS100,I95:I100) -> 0.14880621 | AT94: =SUMPRODUCT(AT95:AT100,J95:J100) -> 0.10910554 | ... BT94: =SUMPRODUCT(BT95:BT100,AJ95:AJ100) -> 0.17672779 | BV94: Dedicated Mobile Self-Scanning Devices | BW94: CMI_Trend_46 | BX94: CMI_Trend_25 | BY94: CMI_Trend_25 | BZ94: CMI_Trend_20 | CA94: CMI_Trend_38 | CB94: CMI_Trend_60 | CC94: CMI_Trend_25 | CD94: CMI_Trend_56 | CE94: CMI_Trend_46 | CF94: CMI_Trend_46 | CG94: CMI_Trend_46 | CH94: CMI_Trend_46 | CI94: CMI_Trend_25 | CJ94: CMI_Trend_20 | CK94: CMI_Trend_20 | CL94: CMI_Trend_46 | CM94: CMI_Trend_60 | CN94: CMI_Trend_52 | CO94: CMI_Trend_56 | CP94: CMI_Trend_38 | CQ94: CMI_Trend_52 | CR94: CMI_Trend_56 | CS94: CMI_Trend_46 | CT94: CMI_Trend_38 | CU94: CMI_Trend_38 | CV94: CMI_Trend_20 | CW94: CMI_Trend_20 | CX94: CMI_Trend_52 | CY94: CMI_Trend_38 | CZ94: CMI_Trend_25 | DA94: CMI_Trend_38 | DB94: CMI_Trend_38 | DC94: CMI_Trend_46 | DD94: CMI_Trend_46
B95: Supermarkets & Hypermarkets | C95: =1-SUM(C96:C100) -> 0.37505447 | D95: =1-SUM(D96:D100) -> 0.38065447 | E95: =1-SUM(E96:E100) -> 0.36905447 | F95: =1-SUM(F96:F100) -> 0.36425447 | G95: =1-SUM(G96:G100) -> 0.37295447 | H95: =1-SUM(H96:H100) -> 0.34795447 | I95: =1-SUM(I96:I100) -> 0.35015447 | J95: =1-SUM(J96:J100) -> 0.35925447 | ... AJ95: =1-SUM(AJ96:AJ100) -> 0.39065447 | AL95: Supermarkets & Hypermarkets | AM95: 0.15315274 | AN95: 0.14596895 | AO95: 0.18603345 | AP95: 0.19487022 | AQ95: 0.12733325 | AR95: 0.17951226 | AS95: 0.14686595 | AT95: 0.10648106 | AU95: 0.17284937 | AV95: 0.16674075 | AW95: 0.1599054 | AX95: 0.13430479 | AY95: 0.12164133 | AZ95: 0.11457193 | BA95: 0.13931086 | BB95: 0.15194162 | BC95: 0.1973967 | BD95: 0.18240671 | BE95: 0.16703927 | BF95: 0.18937763 | BG95: 0.19210694 | BH95: 0.17755164 | BI95: 0.18502363 | BJ95: 0.17143186 | BK95: 0.16490871 | BL95: 0.16102125 | BM95: 0.15036916 | BN95: 0.17756447 | BO95: 0.153212 | BP95: 0.16945189 | BQ95: 0.16338583 | BR95: 0.18135697 | BS95: 0.16371244 | BT95: 0.17480171 | BV95: Supermarkets & Hypermarkets | BW95: CMI_Trend_52 | BX95: CMI_Trend_46 | BY95: CMI_Trend_52 | BZ95: CMI_Trend_46 | CA95: CMI_Trend_56 | CB95: CMI_Trend_56 | CC95: CMI_Trend_46 | CD95: CMI_Trend_38 | CE95: CMI_Trend_56 | CF95: CMI_Trend_20 | CG95: CMI_Trend_52 | CH95: CMI_Trend_20 | CI95: CMI_Trend_25 | CJ95: CMI_Trend_52 | CK95: CMI_Trend_56 | CL95: CMI_Trend_46 | CM95: CMI_Trend_38 | CN95: CMI_Trend_46 | CO95: CMI_Trend_25 | CP95: CMI_Trend_56 | CQ95: CMI_Trend_38 | CR95: CMI_Trend_60 | CS95: CMI_Trend_38 | CT95: CMI_Trend_46 | CU95: CMI_Trend_56 | CV95: CMI_Trend_25 | CW95: CMI_Trend_52 | CX95: CMI_Trend_20 | CY95: CMI_Trend_52 | CZ95: CMI_Trend_38 | DA95: CMI_Trend_60 | DB95: CMI_Trend_25 | DC95: CMI_Trend_52 | DD95: CMI_Trend_20
B96: Convenience Stores | C96: 0.16208443 | D96: 0.14818443 | E96: 0.16248443 | F96: 0.17588443 | G96: 0.15818443 | H96: 0.16918443 | I96: 0.16688443 | J96: 0.17788443 | K96: 0.17248443 | L96: 0.16938443 | M96: 0.16348443 | N96: 0.16468443 | O96: 0.15848443 | P96: 0.15308443 | Q96: 0.16028443 | R96: 0.17348443 | S96: 0.16938443 | T96: 0.14868443 | U96: 0.16968443 | V96: 0.16198443 | W96: 0.15108443 | X96: 0.16918443 | Y96: 0.16408443 | Z96: 0.16728443 | AA96: 0.15358443 | AB96: 0.16388443 | AC96: 0.16128443 | AD96: 0.16628443 | AE96: 0.17628443 | AF96: 0.17778443 | AG96: 0.17638443 | AH96: 0.15298443 | AI96: 0.14958443 | AJ96: 0.15288443 | AL96: Convenience Stores | AM96: 0.16000569 | AN96: 0.1528219 | AO96: 0.1928864 | AP96: 0.20172317 | AQ96: 0.1341862 | AR96: 0.18636521 | AS96: 0.15371889 | AT96: 0.11333401 | AU96: 0.17970232 | AV96: 0.1735937 | AW96: 0.16675835 | AX96: 0.14115774 | AY96: 0.12849428 | AZ96: 0.12142487 | BA96: 0.1461638 | BB96: 0.15879456 | BC96: 0.20424965 | BD96: 0.18925966 | BE96: 0.17389222 | BF96: 0.19623058 | BG96: 0.19895989 | BH96: 0.18440459 | BI96: 0.19187658 | BJ96: 0.1782848 | BK96: 0.17176165 | BL96: 0.1678742 | BM96: 0.15722211 | BN96: 0.18441742 | BO96: 0.16006495 | BP96: 0.17630484 | BQ96: 0.17023878 | BR96: 0.18820992 | BS96: 0.17056539 | BT96: 0.18165466 | BV96: Convenience Stores | BW96: CMI_Trend_20 | BX96: CMI_Trend_20 | BY96: CMI_Trend_25 | BZ96: CMI_Trend_60 | CA96: CMI_Trend_38 | CB96: CMI_Trend_56 | CC96: CMI_Trend_60 | CD96: CMI_Trend_52 | CE96: CMI_Trend_20 | CF96: CMI_Trend_60 | CG96: CMI_Trend_52 | CH96: CMI_Trend_52 | CI96: CMI_Trend_20 | CJ96: CMI_Trend_20 | CK96: CMI_Trend_52 | CL96: CMI_Trend_20 | CM96: CMI_Trend_25 | CN96: CMI_Trend_46 | CO96: CMI_Trend_20 | CP96: CMI_Trend_20 | CQ96: CMI_Trend_25 | CR96: CMI_Trend_52 | CS96: CMI_Trend_52 | CT96: CMI_Trend_60 | CU96: CMI_Trend_38 | CV96: CMI_Trend_20 | CW96: CMI_Trend_20 | CX96: CMI_Trend_60 | CY96: CMI_Trend_60 | CZ96: CMI_Trend_25 | DA96: CMI_Trend_52 | DB96: CMI_Trend_46 | DC96: CMI_Trend_25 | DD96: CMI_Trend_56
B97: Specialty and Discount Stores | C97: 0.086356458 | D97: 0.10345646 | E97: 0.099756458 | F97: 0.093156458 | G97: 0.080356458 | H97: 0.093956458 | I97: 0.099556458 | J97: 0.078556458 | K97: 0.088856458 | L97: 0.092656458 | M97: 0.091256458 | N97: 0.099356458 | O97: 0.075556458 | P97: 0.096856458 | Q97: 0.091256458 | R97: 0.095856458 | S97: 0.075656458 | T97: 0.080756458 | U97: 0.092356458 | V97: 0.089456458 | W97: 0.088856458 | X97: 0.098156458 | Y97: 0.074256458 | Z97: 0.074956458 | AA97: 0.079056458 | AB97: 0.077056458 | AC97: 0.076556458 | AD97: 0.097156458 | AE97: 0.071556458 | AF97: 0.075856458 | AG97: 0.079856458 | AH97: 0.088056458 | AI97: 0.10115646 | AJ97: 0.071256458 | AL97: Specialty and Discount Stores | AM97: 0.1465816 | AN97: 0.13939781 | AO97: 0.17946231 | AP97: 0.18829908 | AQ97: 0.12076211 | AR97: 0.17294113 | AS97: 0.14029481 | AT97: 0.099909923 | AU97: 0.16627824 | AV97: 0.16016962 | AW97: 0.15333426 | AX97: 0.12773365 | AY97: 0.11507019 | AZ97: 0.10800079 | BA97: 0.13273972 | BB97: 0.14537048 | BC97: 0.19082556 | BD97: 0.17583557 | BE97: 0.16046813 | BF97: 0.18280649 | BG97: 0.1855358 | BH97: 0.1709805 | BI97: 0.1784525 | BJ97: 0.16486072 | BK97: 0.15833757 | BL97: 0.15445011 | BM97: 0.14379802 | BN97: 0.17099333 | BO97: 0.14664086 | BP97: 0.16288075 | BQ97: 0.15681469 | BR97: 0.17478583 | BS97: 0.1571413 | BT97: 0.16823057 | BV97: Specialty and Discount Stores | BW97: CMI_Trend_38 | BX97: CMI_Trend_56 | BY97: CMI_Trend_56 | BZ97: CMI_Trend_52 | CA97: CMI_Trend_20 | CB97: CMI_Trend_38 | CC97: CMI_Trend_38 | CD97: CMI_Trend_56 | CE97: CMI_Trend_56 | CF97: CMI_Trend_60 | CG97: CMI_Trend_20 | CH97: CMI_Trend_46 | CI97: CMI_Trend_56 | CJ97: CMI_Trend_38 | CK97: CMI_Trend_20 | CL97: CMI_Trend_25 | CM97: CMI_Trend_25 | CN97: CMI_Trend_60 | CO97: CMI_Trend_56 | CP97: CMI_Trend_25 | CQ97: CMI_Trend_38 | CR97: CMI_Trend_52 | CS97: CMI_Trend_25 | CT97: CMI_Trend_52 | CU97: CMI_Trend_25 | CV97: CMI_Trend_56 | CW97: CMI_Trend_60 | CX97: CMI_Trend_25 | CY97: CMI_Trend_46 | CZ97: CMI_Trend_20 | DA97: CMI_Trend_38 | DB97: CMI_Trend_20 | DC97: CMI_Trend_60 | DD97: CMI_Trend_52
B98: Department Stores | C98: 0.070814061 | D98: 0.067014061 | E98: 0.084114061 | F98: 0.074414061 | G98: 0.070714061 | H98: 0.083214061 | I98: 0.078214061 | J98: 0.069914061 | K98: 0.081814061 | L98: 0.063914061 | M98: 0.086414061 | N98: 0.082214061 | O98: 0.087714061 | P98: 0.067814061 | Q98: 0.058714061 | R98: 0.077214061 | S98: 0.068014061 | T98: 0.057814061 | U98: 0.060314061 | V98: 0.079614061 | W98: 0.066414061 | X98: 0.061714061 | Y98: 0.069314061 | Z98: 0.056714061 | AA98: 0.070814061 | AB98: 0.075914061 | AC98: 0.062114061 | AD98: 0.075714061 | AE98: 0.079514061 | AF98: 0.085714061 | AG98: 0.073014061 | AH98: 0.057814061 | AI98: 0.072914061 | AJ98: 0.080814061 | AL98: Department Stores | AM98: 0.13231824 | AN98: 0.12513445 | AO98: 0.16519895 | AP98: 0.17403572 | AQ98: 0.10649875 | AR98: 0.15867777 | AS98: 0.12603145 | AT98: 0.085646564 | AU98: 0.15201488 | AV98: 0.14590626 | AW98: 0.1390709 | AX98: 0.11347029 | AY98: 0.10080683 | AZ98: 0.093737428 | BA98: 0.11847636 | BB98: 0.13110712 | BC98: 0.1765622 | BD98: 0.16157221 | BE98: 0.14620477 | BF98: 0.16854313 | BG98: 0.17127244 | BH98: 0.15671714 | BI98: 0.16418914 | BJ98: 0.15059736 | BK98: 0.14407421 | BL98: 0.14018675 | BM98: 0.12953466 | BN98: 0.15672997 | BO98: 0.1323775 | BP98: 0.14861739 | BQ98: 0.14255133 | BR98: 0.16052247 | BS98: 0.14287794 | BT98: 0.15396721 | BV98: Department Stores | BW98: CMI_Trend_38 | BX98: CMI_Trend_52 | BY98: CMI_Trend_46 | BZ98: CMI_Trend_25 | CA98: CMI_Trend_52 | CB98: CMI_Trend_56 | CC98: CMI_Trend_60 | CD98: CMI_Trend_56 | CE98: CMI_Trend_20 | CF98: CMI_Trend_56 | CG98: CMI_Trend_52 | CH98: CMI_Trend_56 | CI98: CMI_Trend_38 | CJ98: CMI_Trend_46 | CK98: CMI_Trend_25 | CL98: CMI_Trend_52 | CM98: CMI_Trend_20 | CN98: CMI_Trend_52 | CO98: CMI_Trend_20 | CP98: CMI_Trend_52 | CQ98: CMI_Trend_38 | CR98: CMI_Trend_46 | CS98: CMI_Trend_56 | CT98: CMI_Trend_56 | CU98: CMI_Trend_46 | CV98: CMI_Trend_20 | CW98: CMI_Trend_56 | CX98: CMI_Trend_46 | CY98: CMI_Trend_52 | CZ98: CMI_Trend_20 | DA98: CMI_Trend_52 | DB98: CMI_Trend_60 | DC98: CMI_Trend_38 | DD98: CMI_Trend_52
B99: Pharmacies & Drugstores | C99: 0.27422218 | D99: 0.26232218 | E99: 0.25812218 | F99: 0.26502218 | G99: 0.28012218 | H99: 0.27882218 | I99: 0.26822218 | J99: 0.28362218 | K99: 0.28382218 | L99: 0.29142218 | M99: 0.29112218 | N99: 0.26972218 | O99: 0.28412218 | P99: 0.26072218 | Q99: 0.26212218 | R99: 0.28082218 | S99: 0.28752218 | T99: 0.28692218 | U99: 0.28982218 | V99: 0.27922218 | W99: 0.29032218 | X99: 0.27942218 | Y99: 0.27172218 | Z99: 0.28502218 | AA99: 0.26412218 | AB99: 0.28832218 | AC99: 0.28962218 | AD99: 0.27982218 | AE99: 0.27452218 | AF99: 0.25842218 | AG99: 0.25942218 | AH99: 0.26002218 | AI99: 0.26102218 | AJ99: 0.26602218 | AL99: Warehouse Clubs | AM99: 0.16664174 | AN99: 0.15945795 | AO99: 0.19952245 | AP99: 0.20835922 | AQ99: 0.14082225 | AR99: 0.19300127 | AS99: 0.16035495 | AT99: 0.11997006 | AU99: 0.18633838 | AV99: 0.18022976 | AW99: 0.1733944 | AX99: 0.14779379 | AY99: 0.13513033 | AZ99: 0.12806093 | BA99: 0.15279986 | BB99: 0.16543062 | BC99: 0.2108857 | BD99: 0.19589571 | BE99: 0.18052827 | BF99: 0.20286663 | BG99: 0.20559594 | BH99: 0.19104064 | BI99: 0.19851264 | BJ99: 0.18492086 | BK99: 0.17839771 | BL99: 0.17451025 | BM99: 0.16385816 | BN99: 0.19105347 | BO99: 0.166701 | BP99: 0.18294089 | BQ99: 0.17687483 | BR99: 0.19484597 | BS99: 0.17720144 | BT99: 0.18829071 | BV99: Warehouse Clubs | BW99: CMI_Trend_20 | BX99: CMI_Trend_20 | BY99: CMI_Trend_38 | BZ99: CMI_Trend_56 | CA99: CMI_Trend_60 | CB99: CMI_Trend_25 | CC99: CMI_Trend_25 | CD99: CMI_Trend_60 | CE99: CMI_Trend_20 | CF99: CMI_Trend_38 | CG99: CMI_Trend_25 | CH99: CMI_Trend_25 | CI99: CMI_Trend_25 | CJ99: CMI_Trend_60 | CK99: CMI_Trend_38 | CL99: CMI_Trend_46 | CM99: CMI_Trend_38 | CN99: CMI_Trend_38 | CO99: CMI_Trend_60 | CP99: CMI_Trend_60 | CQ99: CMI_Trend_56 | CR99: CMI_Trend_56 | CS99: CMI_Trend_38 | CT99: CMI_Trend_60 | CU99: CMI_Trend_52 | CV99: CMI_Trend_56 | CW99: CMI_Trend_38 | CX99: CMI_Trend_60 | CY99: CMI_Trend_20 | CZ99: CMI_Trend_52 | DA99: CMI_Trend_46 | DB99: CMI_Trend_56 | DC99: CMI_Trend_56 | DD99: CMI_Trend_52
B100: Warehouse Clubs | C100: 0.031468411 | D100: 0.038368411 | E100: 0.026468411 | F100: 0.027268411 | G100: 0.037668411 | H100: 0.026868411 | I100: 0.036968411 | J100: 0.030768411 | K100: 0.037368411 | L100: 0.032168411 | M100: 0.034968411 | N100: 0.039468411 | O100: 0.033168411 | P100: 0.036368411 | Q100: 0.026668411 | R100: 0.039268411 | S100: 0.029168411 | T100: 0.039368411 | U100: 0.025768411 | V100: 0.039168411 | W100: 0.034168411 | X100: 0.039168411 | Y100: 0.027968411 | Z100: 0.038668411 | AA100: 0.032968411 | AB100: 0.028368411 | AC100: 0.029868411 | AD100: 0.034568411 | AE100: 0.026768411 | AF100: 0.033168411 | AG100: 0.026168411 | AH100: 0.025668411 | AI100: 0.032968411 | AJ100: 0.038368411 | AL100: Pharmacies & Drugstores | AM100: 0.13860842 | AN100: 0.13142463 | AO100: 0.17148913 | AP100: 0.1803259 | AQ100: 0.11278893 | AR100: 0.16496795 | AS100: 0.13232163 | AT100: 0.091936744 | AU100: 0.15830506 | AV100: 0.15219644 | AW100: 0.14536108 | AX100: 0.11976047 | AY100: 0.10709701 | AZ100: 0.10002761 | BA100: 0.12476654 | BB100: 0.1373973 | BC100: 0.18285238 | BD100: 0.16786239 | BE100: 0.15249495 | BF100: 0.17483331 | BG100: 0.17756262 | BH100: 0.16300732 | BI100: 0.17047932 | BJ100: 0.15688754 | BK100: 0.15036439 | BL100: 0.14647693 | BM100: 0.13582484 | BN100: 0.16302015 | BO100: 0.13866768 | BP100: 0.15490757 | BQ100: 0.14884151 | BR100: 0.16681265 | BS100: 0.14916812 | BT100: 0.16025739 | BV100: Pharmacies & Drugstores | BW100: CMI_Trend_25 | BX100: CMI_Trend_56 | BY100: CMI_Trend_38 | BZ100: CMI_Trend_25 | CA100: CMI_Trend_38 | CB100: CMI_Trend_60 | CC100: CMI_Trend_25 | CD100: CMI_Trend_46 | CE100: CMI_Trend_60 | CF100: CMI_Trend_25 | CG100: CMI_Trend_20 | CH100: CMI_Trend_52 | CI100: CMI_Trend_60 | CJ100: CMI_Trend_25 | CK100: CMI_Trend_60 | CL100: CMI_Trend_60 | CM100: CMI_Trend_56 | CN100: CMI_Trend_56 | CO100: CMI_Trend_20 | CP100: CMI_Trend_56 | CQ100: CMI_Trend_38 | CR100: CMI_Trend_46 | CS100: CMI_Trend_20 | CT100: CMI_Trend_20 | CU100: CMI_Trend_25 | CV100: CMI_Trend_20 | CW100: CMI_Trend_52 | CX100: CMI_Trend_25 | CY100: CMI_Trend_20 | CZ100: CMI_Trend_56 | DA100: CMI_Trend_52 | DB100: CMI_Trend_52 | DC100: CMI_Trend_25 | DD100: CMI_Trend_46
B101: Smartphone-Based Self-Scanning | C101: 0.22930479 | D101: 0.23890479 | E101: 0.22500479 | F101: 0.22900479 | G101: 0.21420479 | H101: 0.23870479 | I101: 0.21990479 | J101: 0.23570479 | K101: 0.23000479 | L101: 0.22630479 | M101: 0.21910479 | N101: 0.24200479 | O101: 0.22260479 | P101: 0.22340479 | Q101: 0.23810479 | R101: 0.24590479 | S101: 0.24550479 | T101: 0.23900479 | U101: 0.23220479 | V101: 0.23650479 | W101: 0.22170479 | X101: 0.22780479 | Y101: 0.23910479 | Z101: 0.24620479 | AA101: 0.21580479 | AB101: 0.22850479 | AC101: 0.21440479 | AD101: 0.24020479 | AE101: 0.21830479 | AF101: 0.22830479 | AG101: 0.21350479 | AH101: 0.22710479 | AI101: 0.22990479 | AJ101: 0.24630479 | AL101: Smartphone-Based Self-Scanning | AM101: =SUMPRODUCT(AM102:AM107,C102:C107) -> 0.179642 | AN101: =SUMPRODUCT(AN102:AN107,D102:D107) -> 0.17206888 | AO101: =SUMPRODUCT(AO102:AO107,E102:E107) -> 0.21201585 | AP101: =SUMPRODUCT(AP102:AP107,F102:F107) -> 0.22127135 | AQ101: =SUMPRODUCT(AQ102:AQ107,G102:G107) -> 0.1538267 | AR101: =SUMPRODUCT(AR102:AR107,H102:H107) -> 0.20587084 | AS101: =SUMPRODUCT(AS102:AS107,I102:I107) -> 0.17298626 | AT101: =SUMPRODUCT(AT102:AT107,J102:J107) -> 0.13328558 | ... BT101: =SUMPRODUCT(BT102:BT107,AJ102:AJ107) -> 0.20090783 | BV101: Smartphone-Based Self-Scanning | BW101: CMI_Trend_60 | BX101: CMI_Trend_20 | BY101: CMI_Trend_20 | BZ101: CMI_Trend_56 | CA101: CMI_Trend_38 | CB101: CMI_Trend_52 | CC101: CMI_Trend_20 | CD101: CMI_Trend_20 | CE101: CMI_Trend_20 | CF101: CMI_Trend_20 | CG101: CMI_Trend_52 | CH101: CMI_Trend_56 | CI101: CMI_Trend_46 | CJ101: CMI_Trend_20 | CK101: CMI_Trend_52 | CL101: CMI_Trend_25 | CM101: CMI_Trend_56 | CN101: CMI_Trend_46 | CO101: CMI_Trend_20 | CP101: CMI_Trend_56 | CQ101: CMI_Trend_60 | CR101: CMI_Trend_20 | CS101: CMI_Trend_52 | CT101: CMI_Trend_38 | CU101: CMI_Trend_46 | CV101: CMI_Trend_60 | CW101: CMI_Trend_46 | CX101: CMI_Trend_38 | CY101: CMI_Trend_20 | CZ101: CMI_Trend_38 | DA101: CMI_Trend_60 | DB101: CMI_Trend_38 | DC101: CMI_Trend_38 | DD101: CMI_Trend_52
B102: Supermarkets & Hypermarkets | C102: =1-SUM(C103:C107) -> 0.37825421 | D102: =1-SUM(D103:D107) -> 0.37765421 | E102: =1-SUM(E103:E107) -> 0.39375421 | F102: =1-SUM(F103:F107) -> 0.35965421 | G102: =1-SUM(G103:G107) -> 0.40745421 | H102: =1-SUM(H103:H107) -> 0.36735421 | I102: =1-SUM(I103:I107) -> 0.38775421 | J102: =1-SUM(J103:J107) -> 0.40675421 | ... AJ102: =1-SUM(AJ103:AJ107) -> 0.36745421 | AL102: Supermarkets & Hypermarkets | AM102: 0.17681714 | AN102: 0.16976205 | AO102: 0.20887112 | AP102: 0.21869135 | AQ102: 0.15124977 | AR102: 0.20326183 | AS102: 0.16970257 | AT102: 0.13024066 | AU102: 0.1961309 | AV102: 0.19091239 | AW102: 0.18352381 | AX102: 0.15774936 | AY102: 0.14467699 | AZ102: 0.13809764 | BA102: 0.16306124 | BB102: 0.17519623 | BC102: 0.22127136 | BD102: 0.20589308 | BE102: 0.19141537 | BF102: 0.21246825 | BG102: 0.21543754 | BH102: 0.20095183 | BI102: 0.20870287 | BJ102: 0.19558106 | BK102: 0.18849729 | BL102: 0.18536371 | BM102: 0.17428958 | BN102: 0.2008232 | BO102: 0.17653693 | BP102: 0.19255482 | BQ102: 0.18689201 | BR102: 0.20522412 | BS102: 0.18699152 | BT102: 0.19825442 | BV102: Supermarkets & Hypermarkets | BW102: CMI_Trend_56 | BX102: CMI_Trend_25 | BY102: CMI_Trend_46 | BZ102: CMI_Trend_38 | CA102: CMI_Trend_52 | CB102: CMI_Trend_46 | CC102: CMI_Trend_25 | CD102: CMI_Trend_20 | CE102: CMI_Trend_25 | CF102: CMI_Trend_56 | CG102: CMI_Trend_38 | CH102: CMI_Trend_60 | CI102: CMI_Trend_38 | CJ102: CMI_Trend_56 | CK102: CMI_Trend_38 | CL102: CMI_Trend_38 | CM102: CMI_Trend_25 | CN102: CMI_Trend_56 | CO102: CMI_Trend_38 | CP102: CMI_Trend_38 | CQ102: CMI_Trend_46 | CR102: CMI_Trend_20 | CS102: CMI_Trend_56 | CT102: CMI_Trend_38 | CU102: CMI_Trend_20 | CV102: CMI_Trend_20 | CW102: CMI_Trend_52 | CX102: CMI_Trend_46 | CY102: CMI_Trend_20 | CZ102: CMI_Trend_60 | DA102: CMI_Trend_20 | DB102: CMI_Trend_52 | DC102: CMI_Trend_52 | DD102: CMI_Trend_52
B103: Convenience Stores | C103: 0.15313936 | D103: 0.13763936 | E103: 0.13823936 | F103: 0.15473936 | G103: 0.15103936 | H103: 0.13743936 | I103: 0.15373936 | J103: 0.14273936 | K103: 0.15743936 | L103: 0.16833936 | M103: 0.14323936 | N103: 0.14903936 | O103: 0.16773936 | P103: 0.15063936 | Q103: 0.15373936 | R103: 0.14193936 | S103: 0.14873936 | T103: 0.16033936 | U103: 0.16803936 | V103: 0.14703936 | W103: 0.14733936 | X103: 0.16363936 | Y103: 0.13873936 | Z103: 0.15123936 | AA103: 0.14893936 | AB103: 0.15253936 | AC103: 0.14773936 | AD103: 0.14863936 | AE103: 0.16603936 | AF103: 0.13803936 | AG103: 0.14003936 | AH103: 0.14593936 | AI103: 0.16553936 | AJ103: 0.15803936 | AL103: Convenience Stores | AM103: 0.1839464 | AN103: 0.17689131 | AO103: 0.21600038 | AP103: 0.2258206 | AQ103: 0.15837902 | AR103: 0.21039109 | AS103: 0.17683183 | AT103: 0.13736992 | AU103: 0.20326015 | AV103: 0.19804165 | AW103: 0.19065307 | AX103: 0.16487862 | AY103: 0.15180624 | AZ103: 0.14522689 | BA103: 0.1701905 | BB103: 0.18232549 | BC103: 0.22840062 | BD103: 0.21302233 | BE103: 0.19854463 | BF103: 0.21959751 | BG103: 0.22256679 | BH103: 0.20808109 | BI103: 0.21583213 | BJ103: 0.20271032 | BK103: 0.19562654 | BL103: 0.19249297 | BM103: 0.18141884 | BN103: 0.20795246 | BO103: 0.18366619 | BP103: 0.19968408 | BQ103: 0.19402126 | BR103: 0.21235338 | BS103: 0.19412078 | BT103: 0.20538368 | BV103: Convenience Stores | BW103: CMI_Trend_38 | BX103: CMI_Trend_25 | BY103: CMI_Trend_38 | BZ103: CMI_Trend_60 | CA103: CMI_Trend_60 | CB103: CMI_Trend_25 | CC103: CMI_Trend_46 | CD103: CMI_Trend_46 | CE103: CMI_Trend_60 | CF103: CMI_Trend_56 | CG103: CMI_Trend_20 | CH103: CMI_Trend_38 | CI103: CMI_Trend_56 | CJ103: CMI_Trend_46 | CK103: CMI_Trend_38 | CL103: CMI_Trend_52 | CM103: CMI_Trend_46 | CN103: CMI_Trend_20 | CO103: CMI_Trend_56 | CP103: CMI_Trend_46 | CQ103: CMI_Trend_25 | CR103: CMI_Trend_20 | CS103: CMI_Trend_46 | CT103: CMI_Trend_60 | CU103: CMI_Trend_38 | CV103: CMI_Trend_60 | CW103: CMI_Trend_25 | CX103: CMI_Trend_38 | CY103: CMI_Trend_38 | CZ103: CMI_Trend_38 | DA103: CMI_Trend_38 | DB103: CMI_Trend_25 | DC103: CMI_Trend_56 | DD103: CMI_Trend_20
B104: Specialty and Discount Stores | C104: 0.081163859 | D104: 0.095063859 | E104: 0.069463859 | F104: 0.070763859 | G104: 0.067763859 | H104: 0.085763859 | I104: 0.077863859 | J104: 0.067663859 | K104: 0.067563859 | L104: 0.095363859 | M104: 0.077463859 | N104: 0.078863859 | O104: 0.081963859 | P104: 0.091663859 | Q104: 0.067963859 | R104: 0.083463859 | S104: 0.075563859 | T104: 0.083263859 | U104: 0.074463859 | V104: 0.081363859 | W104: 0.073863859 | X104: 0.097063859 | Y104: 0.087663859 | Z104: 0.067763859 | AA104: 0.087663859 | AB104: 0.091163859 | AC104: 0.082263859 | AD104: 0.064963859 | AE104: 0.079163859 | AF104: 0.072063859 | AG104: 0.095063859 | AH104: 0.075863859 | AI104: 0.087163859 | AJ104: 0.064963859 | AL104: Specialty and Discount Stores | AM104: 0.17010859 | AN104: 0.16305351 | AO104: 0.20216257 | AP104: 0.2119828 | AQ104: 0.14454122 | AR104: 0.19655328 | AS104: 0.16299403 | AT104: 0.12353211 | AU104: 0.18942235 | AV104: 0.18420384 | AW104: 0.17681527 | AX104: 0.15104082 | AY104: 0.13796844 | AZ104: 0.13138909 | BA104: 0.15635269 | BB104: 0.16848768 | BC104: 0.21456282 | BD104: 0.19918453 | BE104: 0.18470683 | BF104: 0.20575971 | BG104: 0.20872899 | BH104: 0.19424328 | BI104: 0.20199433 | BJ104: 0.18887251 | BK104: 0.18178874 | BL104: 0.17865516 | BM104: 0.16758103 | BN104: 0.19411465 | BO104: 0.16982838 | BP104: 0.18584628 | BQ104: 0.18018346 | BR104: 0.19851557 | BS104: 0.18028298 | BT104: 0.19154587 | BV104: Specialty and Discount Stores | BW104: CMI_Trend_60 | BX104: CMI_Trend_52 | BY104: CMI_Trend_25 | BZ104: CMI_Trend_25 | CA104: CMI_Trend_46 | CB104: CMI_Trend_56 | CC104: CMI_Trend_46 | CD104: CMI_Trend_60 | CE104: CMI_Trend_20 | CF104: CMI_Trend_20 | CG104: CMI_Trend_52 | CH104: CMI_Trend_38 | CI104: CMI_Trend_20 | CJ104: CMI_Trend_25 | CK104: CMI_Trend_20 | CL104: CMI_Trend_46 | CM104: CMI_Trend_52 | CN104: CMI_Trend_20 | CO104: CMI_Trend_56 | CP104: CMI_Trend_38 | CQ104: CMI_Trend_20 | CR104: CMI_Trend_56 | CS104: CMI_Trend_38 | CT104: CMI_Trend_38 | CU104: CMI_Trend_38 | CV104: CMI_Trend_52 | CW104: CMI_Trend_38 | CX104: CMI_Trend_38 | CY104: CMI_Trend_52 | CZ104: CMI_Trend_52 | DA104: CMI_Trend_20 | DB104: CMI_Trend_38 | DC104: CMI_Trend_38 | DD104: CMI_Trend_52
B105: Department Stores | C105: 0.078101072 | D105: 0.090001072 | E105: 0.066901072 | F105: 0.091201072 | G105: 0.083001072 | H105: 0.084601072 | I105: 0.063501072 | J105: 0.073501072 | K105: 0.067901072 | L105: 0.079701072 | M105: 0.087301072 | N105: 0.087101072 | O105: 0.062801072 | P105: 0.077101072 | Q105: 0.083001072 | R105: 0.073501072 | S105: 0.066301072 | T105: 0.068401072 | U105: 0.086901072 | V105: 0.062101072 | W105: 0.062101072 | X105: 0.064001072 | Y105: 0.073701072 | Z105: 0.081701072 | AA105: 0.082201072 | AB105: 0.085301072 | AC105: 0.078101072 | AD105: 0.062601072 | AE105: 0.065501072 | AF105: 0.066201072 | AG105: 0.076301072 | AH105: 0.079801072 | AI105: 0.094601072 | AJ105: 0.093301072 | AL105: Department Stores | AM105: 0.15384924 | AN105: 0.14679415 | AO105: 0.18590322 | AP105: 0.19572345 | AQ105: 0.12828187 | AR105: 0.18029393 | AS105: 0.14673467 | AT105: 0.10727276 | AU105: 0.173163 | AV105: 0.16794449 | AW105: 0.16055592 | AX105: 0.13478146 | AY105: 0.12170909 | AZ105: 0.11512974 | BA105: 0.14009334 | BB105: 0.15222833 | BC105: 0.19830346 | BD105: 0.18292518 | BE105: 0.16844747 | BF105: 0.18950036 | BG105: 0.19246964 | BH105: 0.17798393 | BI105: 0.18573498 | BJ105: 0.17261316 | BK105: 0.16552939 | BL105: 0.16239581 | BM105: 0.15132168 | BN105: 0.1778553 | BO105: 0.15356903 | BP105: 0.16958692 | BQ105: 0.16392411 | BR105: 0.18225622 | BS105: 0.16402362 | BT105: 0.17528652 | BV105: Department Stores | BW105: CMI_Trend_20 | BX105: CMI_Trend_25 | BY105: CMI_Trend_20 | BZ105: CMI_Trend_46 | CA105: CMI_Trend_56 | CB105: CMI_Trend_38 | CC105: CMI_Trend_56 | CD105: CMI_Trend_20 | CE105: CMI_Trend_52 | CF105: CMI_Trend_25 | CG105: CMI_Trend_25 | CH105: CMI_Trend_38 | CI105: CMI_Trend_60 | CJ105: CMI_Trend_20 | CK105: CMI_Trend_25 | CL105: CMI_Trend_52 | CM105: CMI_Trend_25 | CN105: CMI_Trend_46 | CO105: CMI_Trend_20 | CP105: CMI_Trend_20 | CQ105: CMI_Trend_60 | CR105: CMI_Trend_56 | CS105: CMI_Trend_60 | CT105: CMI_Trend_38 | CU105: CMI_Trend_52 | CV105: CMI_Trend_46 | CW105: CMI_Trend_60 | CX105: CMI_Trend_38 | CY105: CMI_Trend_38 | CZ105: CMI_Trend_20 | DA105: CMI_Trend_56 | DB105: CMI_Trend_25 | DC105: CMI_Trend_60 | DD105: CMI_Trend_52
...

Sheet ASP
D2: Price Table
D3: U.S. | E3: Canada | F3: U.K. | G3: Germany | H3: Italy | I3: France | J3: Spain | K3: Russia | L3: Netherlands | M3: Ireland | N3: Sweden | O3: Poland | P3: Hungary | Q3: Slovakia | R3: Turkey | S3: Rest of Europe | T3: China | U3: Japan | V3: India | W3: South Korea | X3: Singapore | Y3: Malaysia | Z3: Thailand | AA3: Indonesia | AB3: Rest of ASEAN | AC3: Australia | AD3: Rest of Asia Pacific | AE3: Brazil | AF3: Argentina | AG3: Mexico | AH3: Rest of Latin America | AI3: GCC | AJ3: South Africa | AK3: Rest of Middle East & Africa | AN3: U.S. | AO3: Canada | AP3: U.K. | AQ3: Germany | AR3: Italy | AS3: France | AT3: Spain | AU3: Russia | AV3: Netherlands | AW3: Ireland | AX3: Sweden | AY3: Poland | AZ3: Hungary | BA3: Slovakia | BB3: Turkey | BC3: Rest of Europe | BD3: China | BE3: Japan | BF3: India | BG3: South Korea | BH3: Singapore | BI3: Malaysia | BJ3: Thailand | BK3: Indonesia | BL3: Rest of ASEAN | BM3: Australia | BN3: Rest of Asia Pacific | BO3: Brazil | BP3: Argentina | BQ3: Mexico | BR3: Rest of Latin America | BS3: GCC | BT3: South Africa | BU3: Rest of Middle East & Africa
C4: By Component | AM4: By Component
B5: =B350 -> 1855654.2 | C5: Hardware | D5: =D235/D350*10^6 -> 980.21906 | E5: =E235/E350*10^6 -> 968.3155 | F5: =F235/F350*10^6 -> 964.01647 | G5: =G235/G350*10^6 -> 961.0949 | H5: =H235/H350*10^6 -> 972.79058 | I5: =I235/I350*10^6 -> 1008.9906 | J5: =J235/J350*10^6 -> 975.73805 | K5: =K235/K350*10^6 -> 941.9592 | ... AK5: =AK235/AK350*10^6 -> 915.03801 | AM5: Hardware | AN5: ASP8 | AO5: ASP6 | AP5: ASP8 | AQ5: ASP7 | AR5: ASP4 | AS5: ASP9 | AT5: ASP8 | AU5: ASP6 | AV5: ASP2 | AW5: ASP8 | AX5: ASP9 | AY5: ASP2 | AZ5: ASP7 | BA5: ASP2 | BB5: ASP6 | BC5: ASP6 | BD5: ASP5 | BE5: ASP1 | BF5: ASP3 | BG5: ASP6 | BH5: ASP2 | BI5: ASP7 | BJ5: ASP9 | BK5: ASP9 | BL5: ASP7 | BM5: ASP6 | BN5: ASP5 | BO5: ASP8 | BP5: ASP6 | BQ5: ASP1 | BR5: ASP2 | BS5: ASP2 | BT5: ASP4 | BU5: ASP6
B6: =B351 -> 445211.88 | C6: Kiosk Scanner Devices | D6: =D236/D351*10^6 -> 816.81973 | E6: =E236/E351*10^6 -> 848.07676 | F6: =F236/F351*10^6 -> 831.88513 | G6: =G236/G351*10^6 -> 821.67726 | H6: =H236/H351*10^6 -> 853.15233 | I6: =I236/I351*10^6 -> 858.10187 | J6: =J236/J351*10^6 -> 817.90596 | K6: =K236/K351*10^6 -> 860.92494 | ... AK6: =AK236/AK351*10^6 -> 871.38914 | AM6: Kiosk Scanner Devices | AN6: ASP6 | AO6: ASP8 | AP6: ASP4 | AQ6: ASP5 | AR6: ASP4 | AS6: ASP8 | AT6: ASP8 | AU6: ASP2 | AV6: ASP9 | AW6: ASP3 | AX6: ASP1 | AY6: ASP3 | AZ6: ASP3 | BA6: ASP7 | BB6: ASP5 | BC6: ASP7 | BD6: ASP2 | BE6: ASP9 | BF6: ASP7 | BG6: ASP4 | BH6: ASP7 | BI6: ASP2 | BJ6: ASP2 | BK6: ASP6 | BL6: ASP8 | BM6: ASP8 | BN6: ASP9 | BO6: ASP7 | BP6: ASP9 | BQ6: ASP3 | BR6: ASP7 | BS6: ASP1 | BT6: ASP6 | BU6: ASP7
B7: =B352 -> 235861.81 | C7: Single-plane Kiosk Scanners | D7: 382.35785 | E7: 388.80047 | F7: 393.21755 | G7: 394.31258 | H7: 397.73613 | I7: 395.46393 | J7: 396.57153 | K7: 408.26598 | L7: 386.62894 | M7: 392.07922 | N7: 385.57611 | O7: 409.44656 | P7: 411.88277 | Q7: 413.08439 | R7: 410.63398 | S7: 383.44035 | T7: 420.61429 | U7: 390.99654 | V7: 419.36852 | W7: 389.87101 | X7: 384.48153 | Y7: 401.16798 | Z7: 399.98323 | AA7: 416.84322 | AB7: 418.074 | AC7: 387.7358 | AD7: 402.30781 | AE7: 403.5064 | AF7: 414.34815 | AG7: 404.65957 | AH7: 407.03899 | AI7: 398.85652 | AJ7: 405.87223 | AK7: 415.56422 | AM7: Single-plane Kiosk Scanners | AN7: ASP3 | AO7: ASP8 | AP7: ASP7 | AQ7: ASP6 | AR7: ASP2 | AS7: ASP3 | AT7: ASP3 | AU7: ASP5 | AV7: ASP1 | AW7: ASP2 | AX7: ASP6 | AY7: ASP7 | AZ7: ASP5 | BA7: ASP6 | BB7: ASP4 | BC7: ASP7 | BD7: ASP7 | BE7: ASP2 | BF7: ASP3 | BG7: ASP9 | BH7: ASP8 | BI7: ASP1 | BJ7: ASP7 | BK7: ASP9 | BL7: ASP9 | BM7: ASP9 | BN7: ASP8 | BO7: ASP2 | BP7: ASP5 | BQ7: ASP5 | BR7: ASP7 | BS7: ASP7 | BT7: ASP1 | BU7: ASP9
B8: =B353 -> 101831.51 | C8: Multi-plane (Bioptic) Kiosk Scanners | D8: 2521.6969 | E8: 2480.0603 | F8: 2452.2338 | G8: 2445.3287 | H8: 2424.5104 | I8: 2438.4236 | J8: 2431.4155 | K8: 2361.9523 | L8: 2493.9735 | M8: 2459.2419 | N8: 2500.8786 | O8: 2355.0473 | P8: 2341.134 | Q8: 2334.1259 | R8: 2348.0391 | S8: 2514.7918 | T8: 2292.4892 | U8: 2466.147 | V8: 2299.3943 | W8: 2473.1552 | X8: 2507.8867 | Y8: 2403.589 | Z8: 2410.5971 | AA8: 2313.3075 | AB8: 2306.4025 | AC8: 2486.9654 | AD8: 2396.6839 | AE8: 2389.7788 | AF8: 2327.2208 | AG8: 2382.7707 | AH8: 2368.8574 | AI8: 2417.5022 | AJ8: 2375.8656 | AK8: 2320.3157 | AM8: Multi-plane (Bioptic) Kiosk Scanners | AN8: ASP2 | AO8: ASP3 | AP8: ASP6 | AQ8: ASP3 | AR8: ASP8 | AS8: ASP5 | AT8: ASP8 | AU8: ASP8 | AV8: ASP2 | AW8: ASP6 | AX8: ASP4 | AY8: ASP2 | AZ8: ASP7 | BA8: ASP4 | BB8: ASP5 | BC8: ASP8 | BD8: ASP7 | BE8: ASP7 | BF8: ASP6 | BG8: ASP6 | BH8: ASP9 | BI8: ASP2 | BJ8: ASP2 | BK8: ASP2 | BL8: ASP8 | BM8: ASP5 | BN8: ASP2 | BO8: ASP6 | BP8: ASP3 | BQ8: ASP5 | BR8: ASP2 | BS8: ASP6 | BT8: ASP2 | BU8: ASP8
B9: =B354 -> 107518.57 | C9: Presentation Kiosk Scanners | D9: 268.44232 | E9: 272.92372 | F9: 276.03914 | G9: 276.82914 | H9: 279.22651 | I9: 277.62368 | J9: 278.42279 | K9: 286.60361 | L9: 271.45571 | M9: 275.25364 | N9: 270.69604 | O9: 287.45532 | P9: 289.17404 | Q9: 290.04113 | R9: 288.31212 | S9: 269.18938 | T9: 295.27973 | U9: 274.47259 | V9: 294.38108 | W9: 273.69597 | X9: 269.9406 | Y9: 281.59743 | Z9: 280.78002 | AA9: 292.6001 | AB9: 293.48789 | AC9: 272.15583 | AD9: 282.41961 | AE9: 283.24661 | AF9: 290.84054 | AG9: 284.07846 | AH9: 285.75692 | AI9: 280.03489 | AJ9: 284.91522 | AK9: 291.71767 | AM9: Presentation Kiosk Scanners | AN9: ASP3 | AO9: ASP1 | AP9: ASP2 | AQ9: ASP2 | AR9: ASP9 | AS9: ASP9 | AT9: ASP4 | AU9: ASP1 | AV9: ASP5 | AW9: ASP4 | AX9: ASP6 | AY9: ASP4 | AZ9: ASP5 | BA9: ASP4 | BB9: ASP1 | BC9: ASP6 | BD9: ASP8 | BE9: ASP2 | BF9: ASP7 | BG9: ASP1 | BH9: ASP2 | BI9: ASP8 | BJ9: ASP5 | BK9: ASP2 | BL9: ASP2 | BM9: ASP6 | BN9: ASP5 | BO9: ASP9 | BP9: ASP1 | BQ9: ASP8 | BR9: ASP3 | BS9: ASP4 | BT9: ASP6 | BU9: ASP8
B10: =B355 -> 125940.94 | C10: Dedicated / Retailer-Supplied Mobile Devices | D10: 1363.1782 | E10: 1340.6238 | F10: 1325.5876 | G10: 1321.8698 | H10: 1310.6339 | I10: 1318.152 | J10: 1314.3517 | K10: 1276.8436 | L10: 1348.142 | M10: 1329.3879 | N10: 1351.9423 | O10: 1273.0432 | P10: 1265.5251 | Q10: 1261.8073 | R10: 1269.3255 | S10: 1359.4605 | T10: 1239.2529 | U10: 1333.1057 | V10: 1242.9707 | W10: 1336.9061 | X10: 1355.6601 | Y10: 1299.3154 | Z10: 1303.1158 | AA10: 1250.4888 | AB10: 1246.7711 | AC10: 1344.4242 | AD10: 1295.5976 | AE10: 1291.7973 | AF10: 1258.007 | AG10: 1288.0795 | AH10: 1280.5614 | AI10: 1306.8335 | AJ10: 1284.2791 | AK10: 1254.2892 | AM10: Dedicated / Retailer-Supplied Mobile Devices | AN10: ASP1 | AO10: ASP9 | AP10: ASP3 | AQ10: ASP3 | AR10: ASP3 | AS10: ASP9 | AT10: ASP2 | AU10: ASP9 | AV10: ASP8 | AW10: ASP8 | AX10: ASP1 | AY10: ASP9 | AZ10: ASP1 | BA10: ASP9 | BB10: ASP2 | BC10: ASP3 | BD10: ASP9 | BE10: ASP1 | BF10: ASP5 | BG10: ASP4 | BH10: ASP2 | BI10: ASP2 | BJ10: ASP1 | BK10: ASP5 | BL10: ASP2 | BM10: ASP3 | BN10: ASP1 | BO10: ASP9 | BP10: ASP5 | BQ10: ASP3 | BR10: ASP3 | BS10: ASP2 | BT10: ASP6 | BU10: ASP1
B11: =B356 -> 26811.098 | C11: Smart-Cart Units | D11: 3816.899 | E11: 3753.7798 | F11: 3711.7278 | G11: 3701.2354 | H11: 3669.6758 | I11: 3690.7431 | J11: 3680.1681 | K11: 3575.0795 | L11: 3774.8471 | M11: 3722.3027 | N11: 3785.3394 | O11: 3564.5045 | P11: 3543.5198 | Q11: 3533.0275 | R11: 3554.0122 | S11: 3806.4067 | T11: 3469.9082 | U11: 3732.7951 | V11: 3480.4006 | W11: 3743.2874 | X11: 3795.8317 | Y11: 3638.1162 | Z11: 3648.6911 | AA11: 3501.4679 | AB11: 3490.9755 | AC11: 3764.3547 | AD11: 3627.6238 | AE11: 3617.1315 | AF11: 3522.4525 | AG11: 3606.6391 | AH11: 3585.5718 | AI11: 3659.1835 | AJ11: 3596.0642 | AK11: 3511.9602 | AM11: Smart-Cart Units | AN11: ASP8 | AO11: ASP1 | AP11: ASP5 | AQ11: ASP1 | AR11: ASP5 | AS11: ASP6 | AT11: ASP2 | AU11: ASP2 | AV11: ASP6 | AW11: ASP8 | AX11: ASP4 | AY11: ASP1 | AZ11: ASP5 | BA11: ASP9 | BB11: ASP7 | BC11: ASP7 | BD11: ASP6 | BE11: ASP4 | BF11: ASP8 | BG11: ASP5 | BH11: ASP7 | BI11: ASP4 | BJ11: ASP5 | BK11: ASP9 | BL11: ASP5 | BM11: ASP5 | BN11: ASP5 | BO11: ASP7 | BP11: ASP7 | BQ11: ASP5 | BR11: ASP8 | BS11: ASP4 | BT11: ASP4 | BU11: ASP2
B12: =B357 -> 215022.39 | C12: Kiosk Terminals / Display + Controller | D12: 1950.3 | E12: 1918.1 | F12: 1896.6 | G12: 1891.2 | H12: 1875.1 | I12: 1885.8 | J12: 1880.5 | K12: 1826.7 | L12: 1928.8 | M12: 1901.9 | N12: 1934.2 | O12: 1821.4 | P12: 1810.6 | Q12: 1805.2 | R12: 1816 | S12: 1944.9 | T12: 1773 | U12: 1907.3 | V12: 1778.4 | W12: 1912.7 | X12: 1939.6 | Y12: 1859 | Z12: 1864.3 | AA12: 1789.1 | AB12: 1783.7 | AC12: 1923.4 | AD12: 1853.6 | AE12: 1848.2 | AF12: 1799.9 | AG12: 1842.8 | AH12: 1832.1 | AI12: 1869.7 | AJ12: 1837.5 | AK12: 1794.5 | AM12: Kiosk Terminals / Display + Controller | AN12: ASP8 | AO12: ASP1 | AP12: ASP8 | AQ12: ASP4 | AR12: ASP3 | AS12: ASP4 | AT12: ASP8 | AU12: ASP8 | AV12: ASP5 | AW12: ASP5 | AX12: ASP7 | AY12: ASP3 | AZ12: ASP8 | BA12: ASP2 | BB12: ASP2 | BC12: ASP2 | BD12: ASP4 | BE12: ASP1 | BF12: ASP4 | BG12: ASP7 | BH12: ASP3 | BI12: ASP6 | BJ12: ASP2 | BK12: ASP3 | BL12: ASP9 | BM12: ASP4 | BN12: ASP8 | BO12: ASP8 | BP12: ASP9 | BQ12: ASP4 | BR12: ASP4 | BS12: ASP4 | BT12: ASP2 | BU12: ASP8
B13: =B358 -> 285702.47 | C13: Payment Units | D13: 330 | E13: 324.5 | F13: 320.9 | G13: 320 | H13: 317.3 | I13: 319.1 | J13: 318.2 | K13: 309.1 | L13: 326.4 | M13: 321.8 | N13: 327.3 | O13: 308.2 | P13: 306.4 | Q13: 305.5 | R13: 307.3 | S13: 329.1 | T13: 300 | U13: 322.7 | V13: 300.9 | W13: 323.6 | X13: 328.2 | Y13: 314.5 | Z13: 315.5 | AA13: 302.7 | AB13: 301.8 | AC13: 325.5 | AD13: 313.6 | AE13: 312.7 | AF13: 304.5 | AG13: 311.8 | AH13: 310 | AI13: 316.4 | AJ13: 310.9 | AK13: 303.6 | AM13: Payment Units | AN13: ASP2 | AO13: ASP4 | AP13: ASP6 | AQ13: ASP9 | AR13: ASP2 | AS13: ASP6 | AT13: ASP2 | AU13: ASP1 | AV13: ASP7 | AW13: ASP1 | AX13: ASP6 | AY13: ASP4 | AZ13: ASP9 | BA13: ASP9 | BB13: ASP5 | BC13: ASP7 | BD13: ASP1 | BE13: ASP7 | BF13: ASP5 | BG13: ASP5 | BH13: ASP3 | BI13: ASP4 | BJ13: ASP6 | BK13: ASP8 | BL13: ASP4 | BM13: ASP3 | BN13: ASP5 | BO13: ASP3 | BP13: ASP5 | BQ13: ASP8 | BR13: ASP8 | BS13: ASP2 | BT13: ASP9 | BU13: ASP5
B14: =B359 -> 228688.11 | C14: Kiosk Cabinet / Enclosure | D14: 1544.4 | E14: 1518.84 | F14: 1501.83 | G14: 1497.6 | H14: 1484.82 | I14: 1493.37 | J14: 1489.05 | K14: 1446.57 | L14: 1527.39 | M14: 1506.15 | N14: 1531.62 | O14: 1442.25 | P14: 1433.79 | Q14: 1429.56 | R14: 1438.02 | S14: 1540.17 | T14: 1404 | U14: 1510.38 | V14: 1408.23 | W14: 1514.61 | X14: 1535.85 | Y14: 1472.04 | Z14: 1476.36 | AA14: 1416.78 | AB14: 1412.55 | AC14: 1523.16 | AD14: 1467.81 | AE14: 1463.58 | AF14: 1425.24 | AG14: 1459.35 | AH14: 1450.8 | AI14: 1480.59 | AJ14: 1455.03 | AK14: 1421.01 | AM14: Kiosk Cabinet / Enclosure | AN14: ASP3 | AO14: ASP6 | AP14: ASP2 | AQ14: ASP2 | AR14: ASP2 | AS14: ASP7 | AT14: ASP4 | AU14: ASP2 | AV14: ASP5 | AW14: ASP8 | AX14: ASP6 | AY14: ASP1 | AZ14: ASP8 | BA14: ASP7 | BB14: ASP5 | BC14: ASP2 | BD14: ASP5 | BE14: ASP2 | BF14: ASP8 | BG14: ASP2 | BH14: ASP8 | BI14: ASP2 | BJ14: ASP8 | BK14: ASP9 | BL14: ASP8 | BM14: ASP9 | BN14: ASP3 | BO14: ASP4 | BP14: ASP2 | BQ14: ASP4 | BR14: ASP9 | BS14: ASP6 | BT14: ASP4 | BU14: ASP2
B15: =B360 -> 290787.33 | C15: Receipt Printer | D15: 433 | E15: 425.81818 | F15: 421.09091 | G15: 419.90909 | H15: 416.27273 | I15: 418.72727 | J15: 417.45455 | K15: 405.54545 | L15: 428.27273 | M15: 422.27273 | N15: 429.45455 | O15: 404.36364 | P15: 402 | Q15: 400.81818 | R15: 403.18182 | S15: 431.81818 | T15: 393.63636 | U15: 423.45455 | V15: 394.81818 | W15: 424.63636 | X15: 430.63636 | Y15: 412.72727 | Z15: 413.90909 | AA15: 397.18182 | AB15: 396 | AC15: 427 | AD15: 411.54545 | AE15: 410.36364 | AF15: 399.63636 | AG15: 409.18182 | AH15: 406.72727 | AI15: 415.09091 | AJ15: 407.90909 | AK15: 398.36364 | AM15: Receipt Printer | AN15: ASP9 | AO15: ASP7 | AP15: ASP8 | AQ15: ASP8 | AR15: ASP8 | AS15: ASP8 | AT15: ASP5 | AU15: ASP9 | AV15: ASP4 | AW15: ASP5 | AX15: ASP5 | AY15: ASP5 | AZ15: ASP2 | BA15: ASP2 | BB15: ASP6 | BC15: ASP3 | BD15: ASP7 | BE15: ASP5 | BF15: ASP3 | BG15: ASP9 | BH15: ASP4 | BI15: ASP3 | BJ15: ASP1 | BK15: ASP2 | BL15: ASP7 | BM15: ASP4 | BN15: ASP4 | BO15: ASP5 | BP15: ASP6 | BQ15: ASP7 | BR15: ASP7 | BS15: ASP2 | BT15: ASP1 | BU15: ASP6
B16: =B361 -> 237490.02 | C16: Others (Scale / Bagging Hardware, Power & Internal Electronics, Mounting / Wiring / Minor Internal Hardware, Embedded Scan Modules, Network & Accessories) | D16: 794.2 | E16: 781.1 | F16: 772.3 | G16: 770.1 | H16: 763.6 | I16: 767.9 | J16: 765.8 | K16: 743.9 | L16: 785.4 | M16: 774.5 | N16: 787.6 | O16: 741.7 | P16: 737.3 | Q16: 735.1 | R16: 739.5 | S16: 792 | T16: 722 | U16: 776.7 | V16: 724.2 | W16: 778.9 | X16: 789.8 | Y16: 757 | Z16: 759.2 | AA16: 728.6 | AB16: 726.4 | AC16: 783.3 | AD16: 754.8 | AE16: 752.6 | AF16: 732.9 | AG16: 750.4 | AH16: 746.1 | AI16: 761.4 | AJ16: 748.3 | AK16: 730.8 | AM16: Others (Scale / Bagging Hardware, Power & Internal Electronics, Mounting / Wiring / Minor Internal Hardware, Embedded Scan Modules, Network & Accessories) | AN16: ASP1 | AO16: ASP4 | AP16: ASP4 | AQ16: ASP5 | AR16: ASP9 | AS16: ASP8 | AT16: ASP2 | AU16: ASP2 | AV16: ASP3 | AW16: ASP6 | AX16: ASP4 | AY16: ASP9 | AZ16: ASP3 | BA16: ASP2 | BB16: ASP8 | BC16: ASP9 | BD16: ASP3 | BE16: ASP2 | BF16: ASP7 | BG16: ASP9 | BH16: ASP6 | BI16: ASP9 | BJ16: ASP5 | BK16: ASP9 | BL16: ASP4 | BM16: ASP6 | BN16: ASP2 | BO16: ASP2 | BP16: ASP4 | BQ16: ASP8 | BR16: ASP7 | BS16: ASP2 | BT16: ASP1 | BU16: ASP6
C17: Software | AM17: Software | AN17: ASP3 | AO17: ASP9 | AP17: ASP6 | AQ17: ASP2 | AR17: ASP2 | AS17: ASP3 | AT17: ASP3 | AU17: ASP8 | AV17: ASP8 | AW17: ASP8 | AX17: ASP2 | AY17: ASP1 | AZ17: ASP7 | BA17: ASP6 | BB17: ASP1 | BC17: ASP3 | BD17: ASP9 | BE17: ASP2 | BF17: ASP3 | BG17: ASP1 | BH17: ASP7 | BI17: ASP3 | BJ17: ASP7 | BK17: ASP8 | BL17: ASP8 | BM17: ASP1 | BN17: ASP7 | BO17: ASP9 | BP17: ASP5 | BQ17: ASP2 | BR17: ASP9 | BS17: ASP4 | BT17: ASP3 | BU17: ASP3
